Workbook

Sheet ENERO
A1: Claim amount | B1: Id | C1: Reference No | D1: Claim Handler | E1: CS Claim No | F1: Assured | G1: Opponent | H1: Vessel | I1: Place of Discharge | J1: Date of Discharge | K1: Surveyorco | L1: Voyage | M1: Summary | N1: Commodity | O1: Date of Loading | P1: TB | Q1: Fecha de Orden | R1: Participation | S1: Comentarios Reunión
A2: 5496.4 | B2: TRASPASADO | C2: PRE-FIS-MSC-2024-01/26-2982 | D2: Thomas Chatterton | E2: CS-2024-01337 | F2: Prize | G2: MSC | H2: MANZANILLO EXPRESS | I2: Hong Kong | J2: 23.01.2024 | K2: Teamhead | L2: 2346W | M2: TEMPERATURE | N2: CHERRIES | O2: 30.12.2023 | P2: 23.01.2026
A3: 57811.9 | B3: TRASPASADO | C3: PRE-FIS-MAE-2024-01/26-2979 | D3: Nicolas Nuñez | E3: CS-2024-01334 | F3: Prize | G3: Maersk | H3: MAERSK EINDHOVEN | I3: Nansha | J3: 04.01.2024 | K3: Teamhead | L3: 348W | M3: TEMPERATURE / INSPECTOR INDICA ORIGEN, POR LO QUE HABRÍA QUE ABORDAR EL CASO PARA QUE SE ENFOQUE EN TEMP. | N3: CHERRIES | O3: 13.12.2023 | P3: 04.01.2026 | S3: 17.04.2024: Hablar con Kelly para que enfoque caso en temperatura. Cuando sea traspasable, pasar a extrajudicial. | T3: Extensión hasta el 4 de mayo

Sheet FEBRERO
A1: Claim amount | B1: Id | C1: Reference No | D1: Claim Handler | E1: CS Claim No | F1: Assured | G1: Opponent | H1: Vessel | I1: Place of Discharge | J1: Date of Discharge | K1: Surveyorco | L1: Voyage | M1: Summary | N1: Commodity | O1: Date of Loading | P1: TB | Q1: Fecha de Orden | R1: Participation | S1: Comentarios Reunión
A2: 19361.54 | B2: SOLICITADO | C2: PRE-FIS-SEA-2025-02/26-3556 | D2: Thomas Chatterton | E2: CS-2024-02123 | F2: Fairtrasa | G2: Seatrade | H2: PACIFIC REEFER | I2: Vlissingen | J2: 29.02.2024 | K2: Fruit Inspection & Consultancy BV | M2: Temperature, 10 días delay | N2: Mangoes | O2: 04.02.2024 | P2: 28.02.2026
A3: 17219.43 | B3: SOLICITADO | C3: PRE-FIS-MSC-2024-02/26-3110 | D3: Nicolás Nuñez | E3: CS-2024-02186 | F3: Prize | G3: MSC | H3: LIMA EXPRESS | I3: Hong Kong | J3: 23.02.2024 | K3: Teamhead | L3: 2350W | M3: Inspector indica condicion de origen, pero termo muestra temp más baja de lo solicitada y retorno en alza. | N3: Plums | O3: 31.01.2024 | P3: 23.02.2026 | S3: 27.06.2024 Caso pasará una vez listo a Thomas para pedir data a MSC y con esa información ver si Kelly cambia visión y de estar limpio se da de baja.
A4: 25482.31 | B4: SOLICITADO | C4: PRE-FIS-MSC-2024-02/26-3108 | D4: Nicolás Nuñez | E4: CS-2024-01868 | F4: Prize | G4: MSC | H4: BUENAVENTURA EXPRESS | I4: Hong Kong | J4: 20.02.2024 | K4: Teamhead | L4: 2349W | M4: Temperatura | N4: Plums | O4: 20.01.2024 | P4: 20.02.2026
A5: 12155.32 | B5: A PRESENTAR | C5: PRE-FIS-MAE-2025-02/26-3411 | D5: Thomas Chatterton | E5: CS-2024-06994 | F5: FRUTAM | G5: Maersk | H5: MAERSK BULAN | I5: Manzanillo | J5: 25.02.2024 | K5: CSM | L5: 405N | M5: Temperature, delay 9 dias | N5: Nectarines | O5: 08.02.2024 | P5: 25.02.2026
A6: 42949.53 | B6: TRASPASADO | C6: PRE-FIS-HLL-2024-02/26-3090 | D6: Thomas Chatterton | E6: CS-2024-02125 | F6: RANCO | G6: Hapag Lloyd | H6: RIO DE JANEIRO EXPRESS | I6: Hai Phòng | J6: 26.02.2024 | K6: AIM Control Group | L6: 2348W | M6: Delay 12 dias app, TT43 dias e indica tiempo desde packing, pero solo fue 3 dias antes del embarque y cosecha 6 dias antes | N6: Cherries | O6: 16.01.2024 | P6: 26.02.2026 | S6: 19.06.2024 (LB) Traspasar una vez listo.
A7: 29376 | B7: SOLICITADO / se realizó seguimiento 06.01.2026 | C7: FIS-CMA-2025-02/26-3843 | D7: Thomas Chatterton | E7: CS-2025-03650 | F7: Pilz-Schindler | G7: CMA CGM | H7: CMA CGM MARSEILLE | I7: London Gateway | J7: 28.02.2025 | K7: MMS | L7: 0RTJSN1MA | M7: Delay (17 días) | N7: Limes | O7: 31.01.2025 | P7: 28.02.2026
A8: 45777.45 | B8: SOLICITADO PLATAFORMA | C8: PRE-FIS-CMA-2024-02/26-3221 | D8: Thomas Chatterton | E8: CS-2024-03135 | F8: Sunshine Peru | G8: CMA CGM | H8: CZECH | I8: Rotterdam | J8: 29.02.2024 | K8: Fruit Inspection & Consultancy BV | L8: 0WCHLS1MA | M8: Delay 9 dias + algunas temperaturas erráticas al comienzo del viaje | N8: Mangoes | O8: 01.02.2024 | P8: 29.02.2026
A9: 81418.16 | B9: SOLICITADO | C9: PRE-FIS-CMA-2024-02/26-3220 | D9: Thomas Chatterton | E9: CS-2024-08337 | F9: Sunshine Peru | G9: CMA CGM | H9: CMA CGM EXCELLENCE | I9: Rotterdam | J9: 28.02.2024 | L9: 0DVI0N1MA | M9: Delay 9 dias | N9: Mangoes | O9: 01.02.2024 | P9: 28.02.2026 | S9: 03.10.2024 Se solicitará a asegurado QC en destino, stuffing
A10: 20502 | B10: SOLICITADO | C10: PRE-FIS-CMA-2024-02/26-3071 | D10: Thomas Chatterton | E10: CS-2024-01867 | F10: Prize | G10: CMA CGM | H10: COSCO SHIPPING BRAZIL | I10: Busan | J10: 16.02.2024 | K10: Hyopsung | L10: 0HCGMW1MA | M10: Delay 16 dias. 80% atribuible transporte y 20% origen | N10: Blueberries | O10: 09.01.2024 | P10: 16.02.2026
A11: 25769.6 | B11: SOLICITADO | C11: PRE-FIS-CMA-2024-02/26-3069 | D11: Thomas Chatterton | E11: CS-2024-01345 | F11: Prize | G11: CMA CGM | H11: COSCO SHIPPING SEINE | I11: Busan | J11: 11.02.2024 | K11: Hyopsung | L11: 0HCGKW1MA | M11: Delay 12 dias. 30% ATRIBUIBLE A ORIGEN | N11: Blueberries | O11: 02.01.2024 | P11: 11.02.2026
A12: 27690 | B12: SOLICITADO | C12: PRE-FIS-CMA-2024-02/26-3063 | D12: Thomas Chatterton | E12: CS-2024-03628 | F12: Prize | G12: CMA CGM | H12: COSCO SHIPPING BRAZIL | I12: Busan | J12: 16.02.2024 | K12: Other | L12: 0HCGKW1MA | M12: Inspector indica no relacionado a transporte.pero está informe de gases que se ven con alzas durante viaje. registro de gases disponible no concuerdqa con solicitado. | N12: Blueberries | O12: 09.01.2024 | P12: 16.02.2026 | S12: 19.06.2024 (LB) Traspasar a Isi cuando esté listo, se presenta directo a Vicente Rios de Liventus
A13: 21453.83 | B13: SOLICITADO | C13: FIS-SLD-2025-02/26-4106 | D13: Thomas Chatterton | E13: CS-2025-03796 | F13: Pilz-Schindler | G13: SeaLand | H13: ZAGOR | I13: Nhava Sheva | J13: 08.02.2025 | K13: Zorro QC | L13: 45R1 | M13: Temperature | N13: Apples | O13: 22.01.2025 | P13: 08.02.2026

Sheet MARZO
A1: Claim amount | B1: Id | C1: Reference No | D1: Claim Handler | E1: CS Claim No | F1: Assured | G1: Opponent | H1: Vessel | I1: Place of Discharge | J1: Date of Discharge | K1: Surveyorco | L1: Voyage | M1: Summary | N1: Commodity | O1: Date of Loading | P1: TB | Q1: Fecha de Orden | R1: Participation | S1: Comentarios Reunión
A2: 18463.61 | B2: PRESENTAR | C2: PRE-FIS/TRV-HLL-2025-03/26-3961 | D2: Nicolás Nuñez | E2: CS-2025-02543 | F2: Tropicales del Valle S.A. | G2: Hapag Lloyd | H2: ACASTOS | I2: Antwerpen | J2: 01.03.2025 | K2: Fruit Inspection & Consultancy BV | M2: Delay | N2: Pineapples | O2: 03.02.2025 | P2: 01.03.2026
A3: 8021.47 | B3: SOLICITADO | C3: PRE-FIS-MSC-2024-03/26-3103 | D3: Matias Farcuh | E3: CS-2024-03074 | F3: Prize | G3: MSC | H3: BUENOS AIRES EXPRESS | I3: Hong Kong | J3: 15.03.2024 | K3: Teamhead | L3: 2352W | M3: Temperatura / DELAY 6 DIAS POL/ | N3: Nectarines | O3: 20.02.2024 | P3: 15.03.2026 | S3: 06.02.2025 TRASPASAR A MATIAS UNA VEZ LISTO
A4: 29083.05 | B4: SOLICITADO | C4: PRE-FIS-MAE-2024-03/26-3101 | D4: Nicolás Nuñez | E4: CS-2024-02527 | F4: Prize | G4: Maersk | H4: CAROLINE MAERSK | I4: Hong Kong | J4: 11.03.2024 | K4: Teamhead | L4: 405W | M4: Temperatura | N4: Nectarines | O4: 14.02.2024 | P4: 11.03.2026
A5: 39654.56 | B5: SOLICITADO | C5: PRE-FIS-MSC-2024-03/26-3100 | D5: Matias Farcuh | E5: CS-2024-02429 | F5: Prize | G5: MSC | H5: CAUTIN | I5: Hong Kong | J5: 02.03.2024 | K5: Teamhead | L5: 2351W | M5: Temperatura | N5: Plums | O5: 06.02.2024 | P5: 02.03.2026
A6: 33164.07 | B6: SOLICITADO | C6: PRE-FIS-CMA-2024-03/26-3109 | D6: Nicolás Nuñez | E6: CS-2024-03072 | F6: Prize | G6: CMA CGM | H6: CMA CGM BEIRA | I6: Algeciras | J6: 13.03.2024 | K6: Montalvao | L6: 0LIGFN1MA | M6: Temperatura | N6: Nectarines | O6: 16.02.2024 | P6: 13.03.2026
A7: 60292.66 | B7: SOLICITADO | C7: PRE-FIS-CMA-2024-03/26-3219 | D7: Emely Lambraño | E7: CS-2024-05873 | F7: Sunshine Peru | G7: CMA CGM | H7: CMA CGM BETTER WAYS | I7: Rotterdam | J7: 21.03.2024 | K7: McLeans | L7: 0DVI8N1MA | M7: Temperatura, se ve entre 10 y 11 durante viaje la de retorno y sum entre 9 y 10 y cuando llega a destino temp baja a los 8 grados del setting. | N7: Mangoes | O7: 28.02.2024 | P7: 21.03.2026
A8: 55526.66 | B8: SOLICITADO | C8: PRE-FIS-MAE-2024-03/26-3104 | D8: Nicolás Nuñez | E8: CS-2024-03073 | F8: Prize | G8: Maersk | H8: CORNELIUS MAERSK | I8: Hong Kong | J8: 17.03.2024 | K8: Teamhead | L8: 406W | M8: Temperatura / pérdida total | N8: Nectarines | O8: 21.02.2024 | P8: 17.03.2026
A9: 40519.43 | B9: SOLICITADO | C9: PRE-FIS-CMA-2024-03/26-3218 | D9: Emely Lambraño | E9: CS-2024-03293 | F9: Sunshine Peru | G9: CMA CGM | H9: GUAYAQUIL EXPRESS | I9: Rotterdam | J9: 21.03.2024 | K9: Fruit Inspection & Consultancy BV | L9: 0WCH8N1MA | M9: inspector indica potencialmente no relacionado a tránsito, indica fruta inconsistente como causal delay, que los problemas se pueden haber exacerbado con la demora. | N9: Mangoes | O9: 21.02.2024 | P9: 21.03.2026 | S9: 03.10.2024 Se solicitará a asegurado QC en destino, stuffing y se presenta sin reporte de inspección.
A10: 6199.43 | B10: SOLICITADO | C10: PRE-FIS-MAE-2024-03/26-3157 | D10: Thomas Chatterton | E10: CS-2024-07015 | F10: Vidimport Monterrey | G10: Maersk Line | H10: MAERSK BINTAN | I10: Manzanillo | J10: 14.03.2024 | K10: CMS | L10: 407N | M10: Temperature | N10: Grapes | O10: 21.02.2024 | P10: 14.03.2026
A11: 62394.1 | B11: SOLICITADO / revisar. | C11: PRE-FIS-MAE-2025-03/26-3407 | D11: Nicolás Nuñez | E11: CS-2024-07742 | F11: FRUTAM | G11: Maersk | H11: MAERSK BULAN | I11: Manzanillo | J11: 18.03.2024 | K11: CSM | L11: 405N | N11: Peaches | O11: 08.02.2024 | P11: 18.03.2026
A12: 31600.18 | B12: SOLICITADO | C12: PRE-FIS-MAE-2024-03/26-3293 | D12: Thomas Chatterton | E12: CS-2024-03103 | F12: FRUSAN | G12: Maersk | H12: MAERSK LABERINTO | I12: Hong Kong | J12: 31.03.2024 | K12: Teamhead | L12: 4058W | M12: TEMPERATURE | N12: Plums | O12: 05.03.2024 | P12: 31.03.2026 | S12: Casos Sugar Plums: Los cracks vienen de la condensación dentro de las bolsas por las variaciones (aunque pequeñas) durante el transporte... De repente Kelly puede incorporar ese dato al informe también. Según Frusan es común que condensación causa cracks en los plums....
A13: 21718.49 | B13: SOLICITADO | C13: PRE-FIS-MSC-2024-03/26-3115 | D13: Matias Farcuh | E13: CS-2024-03089 | F13: FRUSAN | G13: MSC | H13: MSC AVNI | I13: Rotterdam | J13: 17.03.2024 | K13: Fruit Inspection & Consultancy BV | L13: NX407R | M13: Temperature | N13: Plums | O13: 17.02.2024 | P13: 17.03.2026
A14: 52790.64 | B14: SOLICITADO | C14: PRE-FIS-MSC-2024-03/26-3068 | D14: Matias Farcuh | E14: CS-2024-03076 | F14: Prize | G14: MSC | H14: MSC YASHI B | I14: Philadelphia | J14: 13.03.2024 | K14: PCCC | L14: NX408R | M14: Registro de gases disponible no concuerda con solicitado. Se indica posible problema de temp, pero no figuran los termos disponibles. | N14: Blueberries | O14: 25.02.2024 | P14: 13.03.2026 | S14: 13.06.2024: Exhibición a future y asignar a Victor Vilches
A15: 5137.33 | B15: SOLICITADO | C15: PRE-FIS-MSC-2024-03/26-3056 | D15: Matias Farcuh | E15: CS-2024-03095 | F15: FRUSAN | G15: MSC | H15: MSC YASHI B | I15: London Gateway | J15: 22.03.2024 | K15: MMS | L15: NX408R | M15: TEMPERATURA, daños por frío, igual daños de origen encontrados.- | N15: Plums | O15: 25.02.2024 | P15: 22.03.2026
A16: 23916.41 | B16: SOLICITADO | C16: PRE-FIS-HLL-2024-03/26-3065 | D16: Thomas Chatterton | E16: CS-2024-02430 | F16: Prize | G16: Hapag Lloyd | H16: SANTOS EXPRESS | I16: Rotterdam | J16: 09.03.2024 | K16: Fruit Inspection & Consultancy BV | L16: 3252N | M16: Delay, registro de gases disponible no concuerdqa con solicitado. | N16: Blueberries | O16: 09.02.2024 | P16: 09.03.2026 | S16: 13.06.2024: Presentar extrajudicialmente cuando sea traspasable (isi martinez)
A17: 121874.26 | B17: SOLICITADO | C17: PRE-FIS-HLL-2024-03/26-3064 | D17: Thomas Chatterton | E17: CS-2024-02427 | F17: Prize | G17: Hapag Lloyd | H17: SANTOS EXPRESS | I17: Rotterdam | J17: 09.03.2024 | K17: Fruit Inspection & Consultancy BV | L17: 3252N | M17: DELAY exaserva condicion de la fruta. | N17: Blueberries | O17: 09.02.2024 | P17: 09.03.2026 | S17: 13.06.2024: Presentar extrajudicial en un futuro con el reporte, ya que no todo el daño es considerado preembarque (también considerar atmosfera). Si lo rechazan, evaluar pasar a judicial.
A18: 21199.5 | B18: SOLICITADO | C18: PRE-FIS-COS-2025-03/26-3554 | D18: Thomas Chatterton | E18: CS-2024-02535 | F18: Fairtrasa | G18: Cosco | H18: SANTOS EXPRESS | I18: Rotterdam | J18: 08.03.2024 | K18: Fruit Inspection & Consultancy BV | M18: Mishandling | P18: 08.03.2026
A19: 20290.82 | B19: SOLICITADO | C19: PRE-FIS-MSC-2024-03/26-3292 | D19: Eduardo Rojas | E19: CS-2024-03102 | F19: FRUSAN | G19: MSC | H19: SEASPAN BRIGHTNESS | I19: Hong Kong | J19: 26.03.2024 | K19: Teamhead | L19: 2402W | M19: TEMPERATURE | N19: Plums | O19: 22.02.2024 | P19: 26.03.2026 | S19: Casos Sugar Plums: Los cracks vienen de la condensación dentro de las bolsas por las variaciones (aunque pequeñas) durante el transporte... De repente Kelly puede incorporar ese dato al informe también. Según Frusan es común que condensación causa cracks en los plums....
A20: 9027.83 | B20: SOLICITADO | C20: PRE-FIS-MSC-2024-03/26-3280 | D20: Eduardo Rojas | E20: CS-2024-03100 | F20: FRUSAN | G20: MSC | H20: SEASPAN BRIGHTNESS | I20: Hong Kong | J20: 26.03.2024 | K20: Teamhead | M20: Temperatura | N20: Plums | O20: 22.02.2024 | P20: 26.03.2026

Sheet ABRIL
A1: Claim amount | B1: Id | C1: Reference No | D1: Claim Handler | E1: CS Claim No | F1: Assured | G1: Opponent | H1: Vessel | I1: Place of Discharge | J1: Date of Discharge | K1: Surveyorco | L1: Voyage | M1: Summary | N1: Commodity | O1: Date of Loading | P1: TB | Q1: Fecha de Orden | R1: Participation | S1: Comentarios Reunión | T1: Itinerario MSC | U1: TT OFRECIDO | V1: TT REAL
A2: 7598.75 | B2: A PRESENTAR | C2: PRE-FIS/TRV-HLL-2025-04/26-3965 | D2: Nicolás Nuñez | E2: CS-2025-05432 | F2: Tropicales del Valle S.A. | G2: Hapag Lloyd | H2: ACASTOS | I2: Antwerpen | J2: 26.04.2025 | K2: Fruit Inspection & Consultancy BV | M2: Delay (11 days) | N2: Pineapples | O2: 01.04.2025 | P2: 26.04.2026
A3: 44439 | B3: SOLICITADO | C3: PRE-FIS-CMA-2024-04/26-3331 | D3: Nicolás Nuñez | E3: CS-2024-07037 | F3: Rio Blanco SpA | G3: CMA CGM | H3: CMA CGM PREGOLIA | I3: Algeciras | J3: 03.04.2024 | M3: Robo de 16 pallets y otros dos destruidos. No se ve signos de manipulación, se debe solicitar pesaje oficial en POL. VGM | N3: Grapes | O3: 11.03.2024 | P3: 03.04.2026
A4: 49371.91 | B4: SOLICITADO | C4: PRE-FIS-SEA-2024-04/26-3216 | D4: Nicolás Nuñez | E4: CS-2024-05874 | F4: Asica Farms SAC | G4: Seatrade | H4: HOOD ISLAND | I4: Vlissingen | J4: 10.04.2024 | K4: Fruit Inspection & Consultancy BV | L4: SR24009 | M4: CA, pero inspector menciona que los niveles de ethanol presente en la fruta eran mínimos. | N4: Avocados | O4: 24.03.2024 | P4: 10.04.2026 | S4: 26.09.2024 Cuando caso esté listo extrajudicial si se consigue data y registro de atmosfera
A5: 41439.55 | B5: SOLICITADO | C5: PRE-FIS-MAE-2025-04/26-3402 | D5: Thomás Chatterton | E5: CS-2024-04109 | F5: Servicios Chilfresh | G5: Maersk | H5: JPO PISCES | I5: San Juan | J5: 10.04.2024 | K5: Other | L5: 411N | M5: Delay por falla en C/T | N5: Grapes | O5: 21.03.2024 | P5: 10.04.2026
A6: 42768.1 | B6: A PRESENTAR | C6: PRE-FIS-ONE-2025-04/26-3410 | D6: Thomás Chatterton | E6: CS-2024-03632 | F6: Monteco / Sun Fresh | G6: ONE | H6: NYK JOANNA | I6: Valparaiso | J6: 08.04.2024 | K6: Crawford, CHL | L6: 0182E | M6: Delay / Temperature | N6: Lemons | O6: 06.02.2024 | P6: 08.04.2026
B7: REVISADO | C7: PRE-FIS-HLL-2026-04/26-4373 | D7: Nicolás Nuñez | E7: CS-2025-04315 | F7: Dutoit Europe B.V. | G7: Hapag Lloyd | H7: ACASTOS | I7: Antwerpen | J7: 25.04.2025 | K7: Fruit Inspection & Consultancy BV | L7: 513N | M7: Temperature | N7: Pineapples | O7: 02.04.2025 | P7: 25.04.2026 | Q7: 25.02.2026

Sheet MAYO
A1: Claim amount | B1: Id | C1: Reference No | D1: Claim Handler | E1: CS Claim No | F1: Assured | G1: Opponent | H1: Vessel | I1: Place of Discharge | J1: Date of Discharge | K1: Surveyorco | L1: Voyage | M1: Status | N1: Summary | O1: Commodity | P1: Date of Loading | Q1: TB
A2: 18657.13 | B2: SOLICITADO | C2: PRE-FIS-CMA-2024-05/26-3179 | D2: Thomas Chatterton | E2: CS-2024-04777 | F2: FRUSAN | G2: CMA CGM | H2: VALPARAISO EXPRESS | I2: Leghorn | J2: 07.05.2024 | K2: Spolidoro | L2: 0WCH0N1MA | M2: Falta AoR, Booking, stuffing, origin, DUS, IVV, SR | N2: Temperature | O2: Pears | P2: 29.03.2024 | Q2: 07.05.2026
A3: 5683.82 | B3: SOLICITADO | C3: PRE-FIS-HLL-2024-05/26-3345 | D3: Thomas Chatterton | E3: CS-2024-04780 | F3: Magna | G3: Hapag Lloyd | H3: SANTOS EXPRESS | I3: Rotterdam | J3: 14.05.2024 | K3: Fruit Inspection & Consultancy BV | L3: 4210N | M3: Falta Payment letter (Adjunta), AoR (Adjunta), DUS, IVV | N3: Inspector indica no relacionado a tránsito/ temperatura irregular claramente en termos | O3: PEARS | P3: 17.04.2024 | Q3: 14.05.2026
A4: 5600 | B4: SOLICITADO / EME | C4: PRE-FIS-ONE-2025-05/26-3408 | D4: Emely Lambraño | E4: CS-2024-05427 | F4: Monteco / Sun Fresh | G4: ONE | H4: NYK ROMULUS | I4: Callao | J4: 18.05.2024 | M4: Falta Subro, AoR, Harvest | N4: Temperature | O4: Apples | P4: 20.04.2024 | Q4: 18.05.2026
B5: CALCULAR LOSS | C5: PRE-FIS-MSC-2025-05/26-3399 | D5: Emely Lambraño | E5: CS-2024-05844 | F5: Green Valley | G5: MSC | H5: MSC NITYA B | I5: Philadelphia | J5: 08.05.2024 | K5: PCCC | L5: NX414R | M5: Falta Subro, AoR, export Invoice, origin certificate, phyto, Harvest, SR, booking | N5: Delay | O5: Grapes | P5: 06.04.2024 | Q5: 08.05.2026
B6: SOLICITADO | C6: PRE-FIS-MAE-2024-05/26-3325 | D6: Emely Lambraño | E6: CS-2024-09639 | F6: Copefrut | G6: Maersk | H6: MAERSK BRANI | I6: Buenaventura | J6: 11.05.2024 | M6: Falta subro, SMV | N6: transportista despacha contenedor a destino distinto debiendo ser El Salvador | O6: Apples | P6: 25.04.2024 | Q6: 11.05.2026
B7: SOLICITADO | C7: PRE-FIS-HLL-2025-05/26-3442 | D7: Emely Lambraño | E7: CS-2024-07010 | F7: Polar Fruit Chile | G7: Hapag Lloyd | H7: AS CLAUDIA | I7: Manzanillo | J7: 07.05.2024 | K7: CSM | L7: 415N | M7: Falta Subro, Final report (No disponible), SMV | N7: Delay (10 días) | O7: Grapes | P7: 07.01.2024 | Q7: 07.05.2026

Sheet JUNIO
A1: Claim amount | B1: Id | C1: Reference No | D1: Claim Handler | E1: CS Claim No | F1: Assured | G1: Opponent | H1: Vessel | I1: Place of Discharge | J1: Date of Discharge | K1: Surveyorco | L1: Voyage | M1: Summary | N1: Commodity | O1: Date of Loading | P1: TB | Q1: Fecha de Orden | R1: Fecha Update | S1: Participation | T1: Comentarios Reunión
A2: 56238.52 | B2: PRESENTAR | C2: PRE-FIS-LAR-2025-06/26-4305 | D2: Thomas | E2: CS-2026-00840 | F2: Frusan | G2: Terrestre | H2: TH LARRAGUIBEL LTDA | I2: ROTTERDAM | K2: Crawford, CHL | N2: Blueberries | P2: 06.06.2026 | Q2: 30.12.2025 | T2: Caso terrestre, se debe reunir costos por contenedor con la naviera y la diferencia del valor de la fruta entre lo que fue y lo que podría haber sido
A3: 19302.31 | B3: SOLICITADO | C3: PRE-FIS-MSC-2025-06/26-3394 | D3: Thomas | E3: CS-2024-05102 | F3: Agrofruta Fresh | G3: MSC | H3: MSC SHREYA B | I3: Rotterdam | J3: 01.06.2024 | K3: Fruit Inspection & Consultancy BV | L3: NX418R | M3: Temperature | N3: Grapes | O3: 27.04.2024 | P3: 01.06.2026
A4: 58899.75 | B4: PRESENTAR | C4: PRE-FIS-ROS-2025-06/26-4304 | D4: Nicolás Núñez | E4: DIRECTO | F4: Exportadora Quelen | G4: Terrestre | H4: MSC LEIGH | I4: Shanghai | J4: 16.12.2025 | K4: Crawford, CHL | L4: 326 | M4: Volcamiento | N4: Cherries | O4: 16.12.2025 | P4: 16.06.2026 | Q4: 17.12.2025
A5: 13493.4 | B5: SOLICITADO | C5: PRE-FIS-MAE-2024-06/26-3349 | D5: Thomas | E5: CS-2024-05865 | F5: Magna | G5: Maersk | H5: MAERSK BOGOR | I5: Rotterdam | J5: 18.06.2024 | K5: Fruit Inspection & Consultancy BV | L5: 420N | M5: Inspector indica causa origen breve problema de temperatura/ termos muetsran problemas de temperatura con un incremento marcado durante un periodo y el resto erráticas. | N5: PEARS | O5: 23.05.2024 | P5: 18.06.2026 | T5: 19.12.2024 CASO SE ASIGNARÁ UNA VEZ LISTO A THOMAS PARA QUE EXHIBAN DATA NO SE USARÁ REPORTE
B6: SOLICITADO | C6: PRE-FIS-MAE-2024-06/26-3339 | D6: Emely Lambraño | E6: CS-2024-07044 | F6: Magna | G6: Maersk | H6: MAERSK BOGOR | I6: Rotterdam | J6: 18.06.2024 | K6: Fruit Inspection & Consultancy BV | L6: 420N | N6: Pears | O6: 22.05.2024 | P6: 18.06.2026
A7: 33383.55 | B7: SOLICITADO | C7: PRE-FIS-MAE-2024-06/26-3164 | D7: Emely Lambraño | E7: CS-2024-05425 | F7: FRUTAM | G7: Maersk Line | H7: JPO PISCES | I7: Buenaventura | J7: 01.06.2024 | K7: ACI | L7: 419N | M7: TEMPERATURE/TRASVASIJE | N7: Pears | O7: 16.05.2024 | P7: 01.06.2026
A8: 12665.93 | B8: SOLICITADO | C8: PRE-FIS-HLL-2024-06/26-3348 | D8: Thomas | E8: CS-2024-05099 | F8: Magna | G8: Hapag Lloyd | H8: GUAYAQUIL EXPRESS | I8: Rotterdam | J8: 01.06.2024 | K8: Fruit Inspection & Consultancy BV | L8: 4212N | M8: Inspector indica causa origen / termos se ven igual que los dos casos anteriores. | N8: PEARS | O8: 02.05.2024 | P8: 01.06.2026 | T8: 19.12.2024 CASO SE ASIGNARÁ UNA VEZ LISTO A THOMAS PARA QUE EXHIBAN DATA NO SE USARÁ REPORTE
A9: 33528.11 | B9: SOLICITADO | C9: PRE-FIS-CMA-2024-06/26-3286 | D9: Nicolás Núñez | E9: CS-2024-05857 | F9: FRUSAN | G9: CMA CGM | H9: COSCO SHIPPING VOLGA | I9: Rotterdam | J9: 21.06.2024 | K9: Fruit Inspection & Consultancy BV | L9: 0WCI0N1MA | M9: TEMPERATURE | N9: APPLES | O9: 24.05.2024 | P9: 21.06.2026 | R9: 20.02.2026
A10: 18163.89 | B10: SOLICITADO | C10: PRE-FIS-CMA-2024-06/26-3294 | D10: Nicolás Núñez | E10: CS-2024-05858 | F10: FRUSAN | G10: CMA CGM | H10: CMA CGM ESTELLE | I10: Rotterdam | J10: 26.06.2024 | K10: Fruit Inspection & Consultancy BV | L10: 0WCI2N1MA | M10: TEMPERATURE | N10: Kiwis | O10: 30.05.2024 | P10: 26.06.2026

Sheet JULIO
A1: Claim amount | B1: Id | C1: Reference No | D1: Claim Handler | E1: CS Claim No | F1: Assured | G1: Opponent | H1: Vessel | I1: Place of Discharge | J1: Date of Discharge | K1: Surveyorco | L1: Voyage | M1: Summary | N1: Commodity | O1: Date of Loading | P1: TB
A2: 20548.5 | B2: SOLICITADO | C2: PRE-FIS-MSC-2026-07/26-4340 | D2: Emely Lambraño | E2: CS-2025-08621 | F2: Itacu Corporation ltda. | G2: MSC | H2: MSC PASSION III | I2: Gioia Tauro | J2: 06.07.2025 | K2: Spolidoro | L2: PH522R | M2: Temperature (and 6 days of delay) | N2: Pineaples | O2: 07.06.2025 | P2: 06.07.2026
A3: 22390.51 | B3: PRESENTAR | C3: PRE-FIS-MSC-2024-07/26-3788 | D3: Nico Nuñez | E3: CS-2024-06993 | F3: Prize | G3: MSC | H3: MSC MAPUTO | I3: Fos-Sur-Mer | J3: 19.07.2024 | K3: McLeans | L3: NX422R | M3: TEMPERATURE | N3: Apples | O3: 02.06.2024 | P3: 19.07.2026
A4: 19358.47 | B4: PRESENTAR | C4: PRE-FIS-MSC-2024-07/26-3215 | D4: Eduardo Rojas | E4: CS-2024-07740 | F4: Lo Garces | G4: MSC | H4: MSC ELMA | I4: Sines | J4: 28.07.2024 | K4: Montalvao | L4: NX423R | M4: Delay 18 dias | N4: Kiwis | O4: 10.06.2024 | P4: 28.07.2026
A5: 24810.33 | B5: REVISAR | C5: PRE-FIS-PIL-2024-07/26-3238 | D5: Thomas | E5: CS-2024-07061 | F5: Rio Maipo | G5: PIL | H5: KOTA SEJARAH | I5: Nhava Sheva | J5: 06.07.2024 | K5: Intertek, IND | L5: 068W | M5: Temperature + DELAY 15 | N5: Apples | O5: 04.05.2024 | P5: 06.07.2026
B6: SOLICITADO | C6: PRE-FIS-MSC-2024-07/26-3327 | D6: Emely Lambraño | E6: CS-2024-07050 | F6: Copefrut | G6: MSC | H6: ANTHEA Y | I6: Port Everglades | J6: 02.07.2024 | K6: PCCC | L6: NX420R | M6: Temperatura y delay, durante transbordo se genera un alza considerable de varios dias | N6: Apples | O6: 18.05.2024 | P6: 02.07.2026

Sheet Solicitudes 
B1: Reference No | C1: Claim Handler | D1: Assured | E1: Solicitud | F1: Fecha de solicitud | G1: Update
B2: FIS-AFR-2025-10/26-3737 | C2: Thomas | D2: AMS EUROPEAN | E2: Claim notice | F2: 12.02.2026 | G2: Se insiste el 08.05.2026 // 28.05.2026 solicitado a inspector
B3: FIS-MAE-2025-03/27-4038 | C3: Thomas Chatterton | D3: Vidaurri el Salvador | E3: Harvest | F3: 18.05.2026 | G3: SOLICITADO nuevamente el 23.06.2026 / se insiste 13.07 / 17.07 envían subro, se insiste por harvest
B4: FIS-MSC-2025-01/27-3911 | C4: Nico Nuñez | D4: Prize | E4: Harvest, Stuffing | F4: 02.06.2026 | G4: SOLICITADO 23.06.2026 / se insiste 10.07
B5: FIS-MSC-2023-04/24-2302 | C5: Matias Farcuh | D5: Geofrut | E5: email claim notice | F5: 15.06.2026 | G5: Solicitada 15.06.2026
B6: FIS-PIL-2025-10/26-3808 | C6: Nico Nuñez | D6: Santa Azul | E6: Harvest, stuffing | F6: 15.06.2026 | G6: SOLICITADO 24.06 / 10.07 se insiste
B7: PRE-FIS-HLL-2026-10/26-4347 | C7: Nico Nuñez | D7: DUTOIT | E7: BL master y AOR | F7: 30.06.2026 | G7: Solicitado 06.07.2026
B8: FIS-CMA-2024-03/26-3109 | C8: Nico Nuñez | D8: Prize | E8: aclaración de la cantidad destruida | F8: 07.07.2026 | G8: Solicitado 10.07.2026
B9: FIS-HLL-2025-01/27-3836 | C9: Thomas Chatterton | D9: Agricom | E9: Reporte TH | F9: 10.07.2026 | G9: Solicitado 10.07.2026
B10: FIS-CMA-2026-11/26-4485 | C10: Nico Nuñez | D10: Tropicales del valle | E10: Staffin o QC en origen | F10: 20.07.2026 | G10: Solicitado 07.08.2026
B11: FIS-MAE-2025-01/27-4169 | C11: Nico Nuñez | D11: Frusan | E11: stuffing | F11: 27.07.2026 | G11: Solicitado 27.07.2026
B12: FIS-HLL-2026-02/28-4562 | C12: Thomas | D12: Quelen | E12: Reporte TH | F12: 24.07.2026 | G12: Solicitado 27.07.2026
... B17: FIS-MSC-2022-10/23-1627(EX) | C17: Edu | D17: Propal | E17: Claim Notice | F17: 13.08.2026 | G17: Por solicitar

Sheet General
A1: =-A1+'[1]2026'!$I$6 -> 0 | B1: Id | C1: Reference No | D1: Claim Handler | E1: CS Claim No | F1: Assured | G1: Opponent | H1: Vessel | I1: Place of Discharge | J1: Date of Discharge | K1: Surveyorco | L1: Voyage | M1: Status | N1: Summary | O1: Commodity | P1: Date of Loading | Q1: TB | R1: Fecha de Orden | S1: Fecha Update | T1: Participation | U1: Comentarios Reunión | V1: Itinerario MSC | W1: TT OFRECIDO | X1: TT REAL
A2: 117629.36 | B2: SOLICITADO | C2: PRE-FIS-ZIM-2025-01/27-3820 | D2: Emely Lambraño | E2: CS-2025-00865 | F2: Copefrut | G2: ZIM | H2: ZIM LUANDA | I2: Tianjin | J2: 03.01.2025 | K2: Teamhead | L2: 114W | M2: Falta Subro, AoR, harvest, survey report, liq. comparativa, DUS, IVV. | N2: temperatures | O2: Cherries | P2: 11.12.2024 | Q2: 04.01.2027
A3: 35760 | B3: 32547 | C3: PRE-FIS-YAN-2025-07/27-4117 | D3: Alejandra Peltier | E3: CS-2025-08640 | F3: Grin Export | G3: Yang Ming | H3: YM SUCCESS | I3: Jebel Ali | J3: 20.07.2025 | K3: Inchcape | L3: 182W | M3: Falta subro, AoR, harvest, DUS, IVV, Final report | N3: Delay | O3: Kiwis | P3: 16.05.2025 | Q3: 20.07.2027
B4: SOLICITADO | C4: PRE-FIS-WAN-2025-03/27-4029 | D4: Emely Lambraño | E4: CS-2025-02892 | F4: Agricom | G4: Wan Hai | H4: YM EXPRESS | I4: Busan | J4: 10.03.2025 | K4: Hyopsung | L4: 086W | M4: Falta Subro, AoR, harvest, Sales account, phyto, booking | N4: Delay & Inherent vice | O4: Blueberries | P4: 21.01.2025 | Q4: 10.03.2027
A5: 68928 | B5: SOLICITADO | C5: PRE-FIS-WAN-2025-03/27-3857 | D5: Emely Lambraño | E5: CS-2025-02939 | F5: RANCO | G5: Wan Hai | H5: YM EXPRESS | I5: Busan | J5: 09.03.2025 | K5: Hyopsung | L5: 086W | M5: Falta Subro, AoR | N5: Delay 16 DIAS / (Considerar ultimo reporte final subido a plataforma) | O5: Cherries | P5: 21.01.2025 | Q5: 10.03.2027 | R5: 10.07.2025
A6: 68928 | B6: SOLICITADO | C6: PRE-FIS-WAN-2025-03/27-3856 | D6: Emely Lambraño | E6: CS-2025-02934 | F6: RANCO | G6: Wan Hai | H6: YM EXPRESS | I6: Busan | J6: 09.03.2025 | K6: Hyopsung | L6: 086W | M6: Falta AoR | N6: Delay 16 DIAS / (considerar ultimo informe final cargado en plataforma) | O6: Cherries | P6: 21.01.2025 | Q6: 10.03.2027 | R6: 10.07.2025
A7: 43849.07 | B7: SOLICITADO | C7: PRE-FIS-COS-2025-01/27-3734 | D7: Alejandra Peltier | E7: CS-2025-04715 | F7: Prize | G7: Cosco | H7: YANTIAN | I7: Shanghai | J7: 03.01.2025 | K7: Teamhead | L7: 124W | M7: Falta AoR, harvest, origin, Invoice. Stuffing report, booking. | N7: temperature | O7: Cherries | P7: 09.12.2024 | Q7: 03.01.2027 | R7: 27.05.2025 | S7: 13.07.2026
B8: CALCULAR LOSS | C8: PRE-FIS-MAE-2025-07/27-4041 | D8: Emely Lambraño | E8: CS-2025-07601 | F8: Alempue | G8: Maersk | H8: SKAGEN MAERSK | I8: Cat Lai Port | J8: 06.07.2025 | K8: AIM Control | L8: 517W | M8: Falta subro, AoR, harvest, SMV O liqu. Comparativa. | N8: Delay | O8: Grapes | P8: 05.05.2025 | Q8: 06.07.2027 | R8: 17.09.2025
A9: 21357.05 | B9: SOLICITADO | C9: PRE-FIS-ONE-2025-04/27-3945 | D9: Alejandra Peltier | E9: CS-2025-04651 | F9: Prize | G9: ONE | H9: SEASPAN RAPTOR | I9: Keelung | J9: 21.04.2025 | K9: Teamhead | L9: 2501W | M9: Falta AoR, harvest | N9: Delay | O9: Plums | P9: 28.02.2025 | Q9: 21.04.2027 | R9: 18.07.2025 | S9: 13.07.2026
B10: SOLICITADO | C10: PRE-FIS-HLL-2025-03/27-3842 | D10: Emely Lambraño | E10: CS-2025-06244 | F10: Copefrut | G10: Hapag Lloyd | H10: SEASPAN BRIGHTNESS | I10: Hong Kong | J10: 13.03.2025 | K10: Teamhead | L10: 2451W | M10: Falta Subro, survey report, liquidación comparativa | N10: Delay | O10: Plums | P10: 14.02.2025 | Q10: 14.03.2027
A11: 12853 | B11: SOLICITADO | C11: PRE-FIS-MSC-2025-03/27-4286 | D11: Emely Lambraño | E11: CS-2025-03671 | F11: CFN | G11: MSC | H11: SEASPAN BRIGHTNESS | I11: Hong Kong | J11: 14.03.2025 | K11: Teamhead | L11: 2451W | M11: Falta subro, AoR, harvest, final report | N11: Temperature | O11: Grapes | P11: 14.02.2025 | Q11: 14.03.2027 | R11: 30.12.2025
A12: 41379.99 | B12: SOLICITADO | C12: PRE-FIS-HLL-2025-05/27-4100 | D12: Alejandra Peltier | E12: CS-2025-08603 | F12: Prize | G12: Hapag Lloyd | H12: SEASPAN BELIEF | I12: Mundra | J12: 27.06.2025 | K12: Zorro QC | L12: 2510W | M12: Falta subro, harvest, DUS, IVV, SR. | N12: Delay | O12: Walnut | P12: 27.04.2025 | Q12: 27.06.2027 | R12: 13.10.2025 | S12: 13.07.2026
B13: SOLICITADO | C13: PRE-FIS-SEA-2025-12/26-4064 | D13: Emely Lambraño | E13: CS-2025-09562 | F13: Family Farms | G13: Seaboard Marine | H13: SBD.GENESIS | I13: Philadelphia | J13: 21.12.2024 | K13: no surveyor involved | L13: SBD.GENESIS 16 | M13: Falta Subro, AoR, harvest certificate | N13: Delay (Allegedly 7 days of delay) | O13: Blueberries | P13: 03.12.2024 | Q13: 21.12.2026 | R13: 23.09.2025
A14: 10146.61 | B14: SOLICITADO | C14: PRE-FIS-HLL-2025-12/26-4068 | D14: Emely Lambraño | E14: CS-2025-00819 | F14: Jorge Schmidt | G14: Hapag Lloyd | H14: SANTOS EXPRESS | I14: London Gateway | J14: 22.12.2024 | K14: MMS | L14: 424N | M14: Falta subro, AoR, harvest certificate, final Report, destruction certificate and Invoice (If available) | N14: Delay (24 days) | O14: Avocados | P14: 14.11.2024 | Q14: 22.12.2026 | R14: 09.10.2025
A15: 5172.16 | B15: SOLICITADO | C15: PRE-FIS-CMA-2025-05/27-4005 | D15: Alejandra Peltier | E15: CS-2025-05381 | F15: FRUSAN | G15: CMA CGM | H15: SANTOS EXPRESS | I15: Rotterdam | J15: 08.05.2025 | K15: Fruit Inspection & Consultancy BV | L15: 0WCKIN1MA | M15: Falta AoR | N15: Temperature | O15: Pears | P15: 03.04.2025 | Q15: 08.05.2027 | S15: 08.04.2026
A16: 4445.98 | B16: SOLICITADO | C16: PRE-FIS-CMA-2025-05/27-4004 | D16: Alejandra Peltier | E16: CS-2025-05380 | F16: FRUSAN | G16: CMA CGM | H16: SANTOS EXPRESS | I16: Rotterdam | J16: 07.05.2025 | K16: Fruit Inspection & Consultancy BV | L16: 0WCKIN1MA | M16: Falta AoR | N16: Temperature | O16: Grapes | P16: 10.04.2025 | Q16: 06.05.2027 | S16: 08.04.2026
A17: 35560.58 | B17: SOLICITADO | C17: PRE-FIS-MAE-2025-05/27-4055 | D17: Emely Lambraño | E17: CS-2025-06247 | F17: Servicios Chilfresh | G17: Maersk | H17: SALLY MAERSK | I17: Cat Lai Port | J17: 31.05.2025 | K17: AIM Control | L17: 513W | M17: Falta subro, harvest, SMV | N17: Delay | O17: Grapes | P17: 08.04.2025 | Q17: 05.05.2027
A18: 12507.13 | B18: SOLICITADO | C18: PRE-FIS-MAE-2025-05/27-4142 | D18: Alejandra Peltier | E18: CS-2025-06883 | F18: Zepeda y Corral | G18: Maersk | H18: SALLY MAERSK | I18: Hong Kong | J18: 16.05.2025 | K18: Teamhead | L18: 513W | M18: Falta Final report, export Invoice, booking. | N18: Temperature | O18: Grapes | P18: 09.04.2025 | Q18: 16.05.2027 | R18: 11.11.2025 | S18: 22.07.2026
A19: 12016.96 | B19: SOLICITADO | C19: PRE-FIS-MAE-2025-05/27-4143 | D19: Alejandra Peltier | E19: CS-2025-06886 | F19: Zepeda y Corral | G19: Maersk | H19: SALLY MAERSK | I19: Hong Kong | J19: 16.05.2025 | K19: Teamhead | L19: 513W | M19: Falta Final report, export Invoice, booking. | N19: Temperature | O19: Grapes | P19: 09.04.2025 | Q19: 16.05.2027 | R19: 11.11.2025 | S19: 22.07.2026
A20: 13376.78 | B20: SOLICITADO | C20: PRE-FIS-MAE-2025-05/27-4144 | D20: Alejandra Peltier | E20: CS-2025-06884 | F20: Zepeda y Corral | G20: Maersk | H20: SALLY MAERSK | I20: Hong Kong | J20: 16.05.2025 | K20: Teamhead | L20: 513W | M20: Falta Final report, export Invoice, booking. | N20: Temperature | O20: Grapes | P20: 09.04.2025 | Q20: 16.05.2027 | R20: 11.11.2025 | S20: 22.07.2026
A21: 13440.03 | B21: SOLICITADO | C21: PRE-FIS-MAE-2025-05/27-4145 | D21: Alejandra Peltier | E21: CS-2025-06885 | F21: Zepeda y Corral | G21: Maersk | H21: SALLY MAERSK | I21: Hong Kong | J21: 16.05.2025 | K21: Teamhead | L21: 513W | M21: Falta Final report, export Invoice, booking. | N21: Temperature | O21: Grapes | P21: 09.04.2025 | Q21: 16.05.2027 | R21: 11.11.2025 | S21: 22.07.2026
A22: 56573.93 | B22: SOLICITADO | C22: PRE-FIS-MSC-2025-01/27-3998 | D22: Emely Lambraño | E22: CS-2025-02339 | F22: Duofrut | G22: MSC | H22: RIO DE JANEIRO EXPRESS | I22: Hong Kong | J22: 28.01.2025 | K22: Teamhead | L22: 2445W | M22: Falta subro, AoR, harvest, origin, SR, DUS, IVV. | N22: Closed Vent | O22: Cherries | P22: 06.01.2025 | Q22: 28.01.2027
B23: SOLICITADO | C23: PRE-FIS-HLL-2025-01/27-3834 | D23: Emely Lambraño | E23: CS-2025-01529 | F23: Magna | G23: Hapag Lloyd | H23: RIO DE JANEIRO EXPRESS | I23: Hong Kong | J23: 28.01.2025 | K23: Teamhead | L23: 2445W | M23: Falta Subro, AoR | N23: Temperature | O23: Cherries | P23: 05.01.2025 | Q23: 28.01.2027
A24: 45083.48 | B24: SOLICITADO | C24: PRE-FIS/FRU-ONE-2025-01/27-4108 | D24: Alejandra Peltier | E24: CS-2025-01422 | F24: FRUSAN | G24: ONE | H24: RIO DE JANEIRO EXPRESS | I24: Hong Kong | J24: 29.01.2025 | K24: Teamhead | L24: 2445W | M24: Falta AoR | N24: cut & run // pérdida de mercado delay 10 días, llega carta post año nuevo Chino | O24: Cherries | P24: 06.01.2025 | Q24: 29.01.2027 | S24: 08.04.2026 | U24: 06.08.2026 Según lo discutido, estos casos se manejarán por LWC, separados por naviera. Al momento de estar completos se traspasarían a Eduardo Rojas
A25: 50404.45 | B25: PRESENTAR | C25: PRE-FIS/FRU-HLL-2025-01/27-4109 | D25: Alejandra Peltier | E25: CS-2025-01423 | F25: FRUSAN | G25: Hapag Lloyd | H25: RIO DE JANEIRO EXPRESS | I25: Hong Kong | J25: 29.01.2025 | K25: Teamhead | L25: 2445W | M25: Ok | N25: cut & run // pérdida de mercado delay 10 días, llega carta post año nuevo Chino | O25: Cherries | P25: 06.01.2025 | Q25: 29.01.2027 | S25: 08.04.2026 | U25: 06.08.2026 Según lo discutido, estos casos se manejarán por LWC, separados por naviera. Al momento de estar completos se traspasarían a Eduardo Rojas
A26: 44186.92 | B26: PRESENTAR | C26: PRE-FIS/FRU-ONE-2025-01/27-4110 | D26: Alejandra Peltier | E26: CS-2025-01518 | F26: FRUSAN | G26: ONE | H26: RIO DE JANEIRO EXPRESS | I26: Hong Kong | J26: 28.01.2025 | K26: Teamhead | L26: 2445W | M26: Ok | N26: cut & run // pérdida de mercado delay 10 días, llega carta post año nuevo Chino | O26: Cherries | P26: 06.01.2025 | Q26: 29.01.2027 | S26: 08.04.2026 | U26: 06.08.2026 Según lo discutido, estos casos se manejarán por LWC, separados por naviera. Al momento de estar completos se traspasarían a Eduardo Rojas
A27: 24453.59 | B27: PRESENTAR | C27: PRE-FIS/FRU-HLL-2025-01/27-4111 | D27: Alejandra Peltier | E27: CS-2025-01519 | F27: FRUSAN | G27: Hapag Lloyd | H27: RIO DE JANEIRO EXPRESS | I27: Hong Kong | J27: 29.01.2025 | K27: Teamhead | L27: 2445W | M27: Falta stuffing, Fito. | N27: cut & run // pérdida de mercado delay 10 días, llega carta post año nuevo Chino | O27: Cherries | P27: 06.01.2025 | Q27: 29.01.2027 | S27: 08.04.2026 | U27: 06.08.2026 Según lo discutido, estos casos se manejarán por LWC, separados por naviera. Al momento de estar completos se traspasarían a Eduardo Rojas
A28: 59536.87 | B28: PRESENTAR | C28: PRE-FIS/FRU-HLL-2025-01/27-4112 | D28: Alejandra Peltier | E28: CS-2025-01520 | F28: FRUSAN | G28: Hapag LLoyd | H28: RIO DE JANEIRO EXPRESS | I28: Hong Kong | J28: 29.01.2025 | K28: Teamhead | L28: 2445W | M28: Ok | N28: cut & run // pérdida de mercado delay 10 días, llega carta post año nuevo Chino | O28: Cherries | P28: 06.01.2025 | Q28: 29.01.2027 | S28: 08.04.2026 | U28: 06.08.2026 Según lo discutido, estos casos se manejarán por LWC, separados por naviera. Al momento de estar completos se traspasarían a Eduardo Rojas
A29: 47094.15 | B29: SOLICITADO | C29: PRE-FIS/FRU-HLL-2025-01/27-4113 | D29: Alejandra Peltier | E29: CS-2025-01521 | F29: FRUSAN | G29: Hapag Lloyd | H29: RIO DE JANEIRO EXPRESS | I29: Hong Kong | J29: 28.01.2025 | K29: Teamhead | L29: 2445W | M29: Falta export Invoice, fito. | N29: cut & run // pérdida de mercado delay 10 días, llega carta post año nuevo Chino | O29: Cherries | P29: 06.01.2025 | Q29: 29.01.2027 | S29: 08.04.2026 | U29: 06.08.2026 Según lo discutido, estos casos se manejarán por LWC, separados por naviera. Al momento de estar completos se traspasarían a Eduardo Rojas
A30: 52091.22 | B30: PRESENTAR | C30: PRE-FIS/FRU-HLL-2025-01/27-4114 | D30: Alejandra Peltier | E30: CS-2025-01522 | F30: FRUSAN | G30: Hapag Lloyd | H30: RIO DE JANEIRO EXPRESS | I30: Hong Kong | J30: 28.01.2025 | K30: Teamhead | L30: 2445W | M30: Falta termógrafos. | N30: cut & run // pérdida de mercado delay 10 días, llega carta post año nuevo Chino | O30: Cherries | P30: 06.01.2025 | Q30: 28.01.2027 | S30: 08.04.2026 | U30: 06.08.2026 Según lo discutido, estos casos se manejarán por LWC, separados por naviera. Al momento de estar completos se traspasarían a Eduardo Rojas
A31: 362.04 | B31: SOLICITADO | C31: PRE-FIS/FRU-HLL-2025-01/27-4115 | D31: Alejandra Peltier | E31: CS-2025-01523 | F31: FRUSAN | G31: Hapag LLoyd | H31: RIO DE JANEIRO EXPRESS | I31: Hong Kong | J31: 29.01.2025 | K31: Teamhead | L31: 2445W | M31: Falta fito, export invoice. | N31: cut & run // pérdida de mercado delay 10 días, llega carta post año nuevo Chino | O31: Cherries | P31: 06.01.2025 | Q31: 29.01.2027 | S31: 08.04.2026 | U31: 06.08.2026 Según lo discutido, estos casos se manejarán por LWC, separados por naviera. Al momento de estar completos se traspasarían a Eduardo Rojas
A32: 35986.24 | B32: PRESENTAR | C32: PRE-FIS/FRU-HLL-2025-01/27-4116 | D32: Alejandra Peltier | E32: CS-2025-01524 | F32: FRUSAN | G32: Hapag Lloyd | H32: RIO DE JANEIRO EXPRESS | I32: Hong Kong | J32: 29.01.2025 | K32: Teamhead | L32: 2445W | M32: Falta export invoice, fito | N32: cut & run // pérdida de mercado delay 10 días, llega carta post año nuevo Chino | O32: Cherries | P32: 06.01.2025 | Q32: 29.01.2027 | S32: 08.04.2026 | U32: 06.08.2026 Según lo discutido, estos casos se manejarán por LWC, separados por naviera. Al momento de estar completos se traspasarían a Eduardo Rojas
B33: PRESENTAR | C33: PRE-FIS/FRU-HLL-2025-01/27-4139 | D33: Alejandra Peltier | E33: CS-2025-11038 | F33: FRUSAN | G33: Hapag LLoyd | H33: RIO DE JANEIRO EXPRESS | I33: Hong Kong | J33: 29.01.2025 | K33: no surveyor involved | L33: 2445W | M33: Ok | N33: cut & run // pérdida de mercado delay 10 días, llega carta post año nuevo Chino | O33: Cherries | P33: 06.01.2025 | Q33: 29.01.2027 | S33: 08.04.2026 | U33: 06.08.2026 Según lo discutido, estos casos se manejarán por LWC, separados por naviera. Al momento de estar completos se traspasarían a Eduardo Rojas
B34: SOLICITADO | C34: PRE-FIS/FRU-HLL-2025-01/27-4153 | D34: Alejandra Peltier | E34: CS-2025-11037 | F34: FRUSAN | G34: Hapag | H34: RIO DE JANEIRO EXPRESS | I34: Hong Kong | J34: 29.01.2025 | K34: no surveyor involved | L34: 2445W | M34: Falta AoR, tracking, QC o photos destino, termografos. | N34: cut & run // pérdida de mercado delay 10 días, llega carta post año nuevo Chino | O34: Cherries | P34: 06.01.2025 | Q34: 29.01.2027 | S34: 08.04.2026 | U34: 06.08.2026 Según lo discutido, estos casos se manejarán por LWC, separados por naviera. Al momento de estar completos se traspasarían a Eduardo Rojas
B35: SOLICITADO | C35: PRE-FIS-MAE-2025-11/26-4067 | D35: Emely Lambraño | E35: CS-2025-09564 | F35: Family Farms | G35: Maersk | H35: POLAR COLOMBIA | I35: Port Hueneme | J35: 08.11.2024 | K35: no surveyor involved | L35: 439N | M35: Falta subro, AoR, harvest certificate | N35: Delay (Allegedly 8 days of delay) | O35: Blueberries | P35: 12.10.2024 | Q35: 08.11.2026
B36: SOLICITADO | C36: PRE-FIS-MAE-2025-11/26-4063 | D36: Emely Lambraño | E36: CS-2025-09557 | F36: Family Farms | G36: Maersk | H36: POLAR COLOMBIA | I36: Philadelphia | J36: 05.11.2024 | K36: no surveyor involved | L36: 439N | M36: Falta subro, AoR, harvest certificate | N36: Delay (Allegedly 11 days of delay) | O36: Blueberries | P36: 12.10.2024 | Q36: 05.11.2026
B37: SOLICITADO | C37: PRE-FIS-MAE-2025-02/27-3462 | D37: Emely Lambraño | E37: CS-2025-02983 | F37: Propal | G37: Maersk | H37: POLAR COLOMBIA | I37: Sydney | J37: 13.02.2025 | K37: McLarens | L37: 451N | M37: Falta Subro, AoR, Destruction Certificate | N37: CA | O37: Avocados | Q37: 13.02.2027
B38: SOLICITADO | C38: PRE-FIS-MAE-2025-12/26-4049 | D38: Emely Lambraño | E38: CS-2025-00492 | F38: Family Farms | G38: Maersk | H38: POLAR ARGENTINA | I38: Philadelphia | J38: 02.12.2024 | K38: PCCC | L38: 441N | M38: Falta subro, AoR, harvest certificate | N38: Delay (Allegedly 21+ days of delay) | O38: Blueberries | P38: 26.10.2024 | Q38: 02.12.2026 | R38: 23.09.2025
B39: SOLICITADO | C39: PRE-FIS-MAE-2025-01/27-3376 | D39: Emely Lambraño | E39: CS-2025-09086 | F39: Family Farms | G39: Maersk | H39: POLAR ARGENTINA | I39: Algeciras | J39: 22.01.2025 | K39: Eurovet | L39: 449n | M39: Falta subro, AoR, harvest certificate, sales acc, SMV | N39: Delay (14 days) | O39: Blueberries | P39: 21.12.2024 | Q39: 22.01.2027
A40: 17723.99 | B40: SOLICITADO | C40: PRE-FIS-MAE-2025-01/27-3448 | D40: Emely Lambraño | E40: CS-2025-00900 | F40: Agualima | G40: Maersk | H40: POLAR ARGENTINA | I40: Philadelphia | J40: 13.01.2025 | K40: PCCC | L40: 445N | M40: Falta Subro, AoR, harvest cert. Origin certificate, phyto | N40: Delay 35 días | O40: Blueberries | P40: 23.11.2024 | Q40: 13.01.2027
B41: SOLICITADO | C41: PRE-FIS-ONE-2025-03/27-3963 | D41: Emely Lambraño | E41: CS-2025-03740 | F41: Dayka & Hackett | G41: ONE | H41: NYK SILVIA | I41: San Antonio | J41: 14.03.2025 | K41: Crawford, CHL | M41: Falta subro, AoR, harvest, origin, termógrafos (No disponibles), phyto, sales acc o cert destrucción, booking. | N41: Delay (23 days) | O41: Mandarines | P41: 22.01.2025 | Q41: 14.03.2027
A42: 40840.66 | B42: SOLICITADO | C42: PRE-FIS-ONE-2026-03/27-4318 | D42: Emely Lambraño | E42: CS-2025-03659 | F42: Sun Fresh USA | G42: ONE | H42: NYK ROMULUS | I42: San Antonio | J42: 13.03.2025 | K42: Crawford, CHL | L42: 072E | M42: Falta firma y stamp de Subro, AoR, / extra cost Invoices detailed in Final report | N42: Delay (35 days) | O42: Oranges | P42: 08.01.2025 | Q42: 13.03.2027 | R42: 23.01.2026
A43: 15959.29 | B43: SOLICITADO | C43: PRE-FIS-ONE-2026-03/27-4317 | D43: Emely Lambraño | E43: CS-2025-03661 | F43: Sun Fresh USA | G43: ONE | H43: NYK ROMULUS | I43: San Antonio | J43: 13.03.2025 | K43: Crawford, CHL | L43: 072E | M43: Falta AoR, Tracking details / Sales Invoices | N43: Delay (35 DAYS) | O43: Apples | P43: 08.01.2025 | Q43: 13.03.2027 | R43: 23.01.2026
B44: SOLICITADO | C44: PRE-FIS-ONE-2025-03/27-3958 | D44: Emely Lambraño | E44: CS-2025-03739 | F44: Dayka & Hackett | G44: ONE | H44: NYK REMUS | I44: San Antonio | J44: 20.03.2025 | K44: Crawford, CHL | L44: 077E | M44: Falta Firmas de cartas de subrogación de derechos, de AoR y de certificado de cosecha //, Certificado de Origen, registros de termógrafos, sales account y SMV. | N44: Delay & Temperature | O44: Mandarines | P44: 18.02.2025 | Q44: 21.03.2027
A45: 41200 | B45: SOLICITADO | C45: PRE-FIS-ONE-2025-03/27-3959 | D45: Emely Lambraño | E45: CS-2025-02933 | F45: Dayka & Hackett | G45: ONE | H45: NYK METEOR | I45: San Antonio | J45: 13.03.2025 | K45: Crawford, CHL | L45: 083E | M45: Falta subro, AoR, harvest, origin certificate, Registros de Termografos, Destruction certificate & Invoice | N45: Delay (41 days) | O45: Mandarines | P45: 15.01.2025 | Q45: 13.03.2027
A46: 5016.52 | B46: SOLICITADO | C46: PRE-FIS-ONE-2026-03/27-4319 | D46: Emely Lambraño | E46: CS-2025-03660 | F46: Sun Fresh USA | G46: ONE | H46: NYK METEOR | I46: San Antonio | J46: 13.03.2025 | K46: Crawford, CHL | L46: 083E | M46: Falta firma y stamp de Subro, AoR, Sales Invoices | N46: Delay (35 DAYS) | O46: Apples | P46: 17.01.2025 | Q46: 13.03.2027 | R46: 23.01.2026
A47: 16005.52 | B47: SOLICITADO | C47: PRE-FIS-ONE-2026-03/27-4333 | D47: Emely Lambraño | E47: CS-2025-03658 | F47: Sun Fresh USA | G47: ONE | H47: NYK METEOR | I47: San Antonio | J47: 13.03.2025 | K47: Crawford, CHL | L47: 083E | M47: Falta AoR, / sales Invoice | N47: Delay (35 days) | O47: Oranges | P47: 17.01.2025 | Q47: 13.03.2027 | R47: 23.01.2026
A48: 10606.06 | B48: SOLICITADO | C48: PRE-FIS-MSC-2025-06/27-4237 | D48: Alejandra Peltier | E48: CS-2025-07879 | F48: Agricola San Gallan S.A.C. | G48: MSC | H48: MSC VIDISHAR | I48: Jebel Ali | J48: 20.06.2025 | K48: Inchcape | L48: NN510A | M48: Falta subro, AoR, harvest, SR. | N48: Delay | O48: Pomegranades | P48: 16.04.2025 | Q48: 20.06.2027 | R48: 22.10.2025 | S48: 05.08.2026
A49: 10606.06 | B49: SOLICITADO | C49: PRE-FIS-MSC-2025-06/27-4239 | D49: Alejandra Peltier | E49: CS-2025-07878 | F49: Agricola San Gallan S.A.C. | G49: MSC | H49: MSC VIDISHAR | I49: Jebel Ali | J49: 20.06.2025 | K49: Inchcape | L49: NN510A | M49: Falta subro, AoR, harvest. | N49: Delay | O49: Pomegranades | P49: 17.04.2025 | Q49: 20.06.2027 | R49: 22.10.2025 | S49: 05.08.2026
B50: SOLICITADO | C50: PRE-FIS-MAE-2025-02/27-3769 | D50: Emely Lambraño | E50: CS-2025-03676 | F50: CFN | G50: ONE | H50: MSC TAYLOR | I50: Yokohama | J50: 23.03.2025 | K50: SCUA | L50: FA452R | M50: Falta subro, AoR, Harvest | N50: vicio inherente | O50: Grapes | P50: 26.01.2025 | Q50: 23.03.2027
A51: 34,335.17 | B51: SOLICITADO | C51: PRE-FIS-MSC-2025-02/27-3914 | D51: Alejandra Peltier | E51: CS-2025-02873 | F51: Prize | G51: MSC | H51: MSC SASHA | I51: Philadelphia | J51: 20.02.2025 | K51: PCCC | L51: NX503R | M51: Falta AoR, harvest | N51: Temperature | O51: Nectarines | P51: 20.01.2025 | Q51: 20.02.2027 | R51: 18.07.2025 | S51: 13.07.2026
A52: 26352.54 | B52: SOLICITADO | C52: PRE-FIS-MSC-2025-02/27-4188 | D52: Alejandra Peltier | E52: CS-2025-06227 | F52: Subsole | G52: MSC | H52: MSC SASHA | I52: Philadelphia | J52: 20.02.2025 | K52: PCCC | L52: NX503R | M52: Falta AoR, harvest cert. | N52: Delay | O52: Grapes | P52: 19.01.2025 | Q52: 20.02.2027 | R52: 17.12.2025 | S52: 08.04.2026
B53: SOLICITADO | C53: PRE-FIS-MSC-2025-07/27-4156 | D53: Emely Lambraño | E53: CS-2025-09043 | F53: A5 Export | G53: MSC | H53: MSC PANTERA | I53: Puerto Cortés | J53: 28.07.2025 | K53: Moller de Honduras | M53: Falta subro, AoR, harvest, tracking, sales acc. | N53: Temp + delay (9 days) | O53: Oranges | P53: 28.06.2025 | Q53: 28.07.2027
A54: 7865.03 | B54: SOLICITADO | C54: PRE-FIS-MSC-2025-01/27-3733 | D54: Alejandra Peltier | E54: CS-2025-04714 | F54: Prize | G54: MSC | H54: MSC ILENIA | I54: Nansha | J54: 23.01.2025 | K54: Teamhead | L54: UX440R | M54: Falta Subro, harvest, AoR, stuffing, origin, Exp Invoice, SR. | N54: temperature | O54: Cherries | P54: 30.12.2024 | Q54: 23.01.2027 | R54: 27.05.2025 | S54: 13.07.2026
A55: 26400 | B55: SOLICITADO | C55: PRE-FIS-ONE-2025-02/27-3550 | D55: Alejandra Peltier | E55: CS-2025-04497 | F55: FRUSAN | G55: ONE | H55: MSC CHIYO | I55: Manzanillo | J55: 01.02.2025 | L55: FA450R | M55: Falta AoR, tracking | N55: Temperature | O55: Plums | Q55: 01.02.2027 | S55: 08.04.2026
A56: 15991.36 | B56: SOLICITADO | C56: PRE-FIS-MSC-2025-05/27-4009 | D56: Alejandra Peltier | E56: CS-2025-05383 | F56: FRUSAN | G56: MSC | H56: MSC CASSANDRE | I56: Rotterdam | J56: 16.05.2025 | K56: Fruit Inspection & Consultancy BV | L56: NX515R | M56: Falta AoR | N56: Temperature | O56: Pears | P56: 12.04.2025 | Q56: 16.05.2027 | S56: 08.04.2026
A57: 16894.4 | B57: SOLICITADO | C57: PRE-FIS-MSC-2025-02/27-3928 | D57: Alejandra Peltier | E57: CS-2025-03789 | F57: Prize | G57: MSC | H57: MSC CASSANDRE | I57: Philadelphia | J57: 27.02.2025 | K57: PCCC | L57: NX505R | M57: Falta AoR, harvest | N57: Temperature & Delay | O57: Nectarines | P57: 01.02.2025 | Q57: 27.02.2027 | R57: 18.07.2025 | S57: 13.07.2026
A58: 13787.89 | B58: SOLICITADO | C58: PRE-FIS-MSC-2025-07/27-4242 | D58: Alejandra Peltier | E58: CS-2025-09088 | F58: Agricola San Gallan S.A.C. | G58: MSC | H58: MSC CAROLE | I58: Jebel Ali | J58: 11.07.2025 | K58: Inchcape | L58: NX517R | M58: Falta subro, AoR, harvest | N58: Delay | O58: Pomegranades | P58: 01.05.2025 | Q58: 11.07.2027 | R58: 22.10.2025 | S58: 05.08.2026
A59: 34337.79 | B59: SOLICITADO | C59: PRE-FIS-HLL-2025-01/27-3450 | D59: Emely Lambraño | E59: CS-2025-01086 | F59: Agualima | G59: Hapag lloyd | H59: MSC CANDIDA | I59: Yokohama | J59: 24.01.2025 | K59: SCUA | L59: FA442R | M59: Falta Subro, AoR, Harvest cert, phyto. | N59: Delay | O59: Asparagus | P59: 03.12.2024 | Q59: 24.01.2027
A60: 5400 | B60: PRESENTAR | C60: PRE-FIS-MSC-2025-02/27-4147 | D60: Alejandra Peltier | E60: CS-2025-11720 | F60: Lo Garces | G60: MSC | H60: MSC BRITTANY | I60: London Gateway | J60: 17.02.2025 | K60: no surveyor involved | L60: NX502R | M60: Ok (cliente no cuenta con termógrafos) | N60: Delay | O60: Nectarines | P60: 09.01.2025 | Q60: 17.02.2027 | R60: 23.03.2026 | S60: 07.04.2026
A61: 25708.07 | B61: SOLICITADO | C61: PRE-FIS-MSC-2025-03/27-3903 | D61: Emely Lambraño | E61: CS-2025-02898 | F61: Propal | G61: MSC | H61: MSC BIANCA | I61: Rotterdam | J61: 07.03.2025 | K61: Crawford, CHL | M61: Falta subro, AoR, harvest, local sales acc. | N61: Falla Ctr, carga no se puede exportar | O61: Avocados | P61: daño en puerto | Q61: 07.03.2027
B62: SOLICITADO | C62: PRE-FIS-MSC-2025-11/26-4062 | D62: Emely Lambraño | E62: CS-2025-09556 | F62: Family Farms | G62: MSC | H62: MSC ANTONELLA | I62: Los Angeles | J62: 05.11.2024 | K62: no surveyor involved | L62: NX440R | M62: Falta Subro, AoR, harvest certificate, SMV or comparative liquidation | N62: CT failure | O62: Blueberries | P62: 10.10.2024 | Q62: 05.11.2026
B63: SOLICITADO | C63: PRE-FIS-MSC-2025-11/26-4061 | D63: Emely Lambraño | E63: CS-2025-09554 | F63: Family Farms | G63: MSC | H63: MSC ANTONELLA | I63: Los Angeles | J63: 05.11.2024 | K63: no surveyor involved | L63: NX440R | M63: Falta subro, AoR, harvest certificate | N63: CT failure | O63: Blueberries | P63: 10.10.2024 | Q63: 05.11.2026
B64: SOLICITADO | C64: PRE-FIS-MSC-2025-11/26-4060 | D64: Emely Lambraño | E64: CS-2025-09552 | F64: Family Farms | G64: MSC | H64: MSC ANTONELLA | I64: Los Angeles | J64: 05.11.2024 | K64: no surveyor involved | L64: NX440R | M64: Falta subro, AoR, harvest certificate | N64: CT failure | O64: Blueberries | P64: 10.10.2024 | Q64: 05.11.2026
B65: SOLICITADO | C65: PRE-FIS-MSC-2025-11/26-4042 | D65: Emely Lambraño | E65: CS-2025-03319 | F65: Family Farms | G65: MSC | H65: MSC ANTONELLA | I65: Los Angeles | J65: 05.11.2024 | K65: PCCC | L65: NX440R | M65: Falta subro, AoR, harvest certificate | N65: CT failure | O65: Blueberries | P65: 10.10.2024 | Q65: 05.11.2026 | R65: 23.09.2025
A66: 32602.93 | B66: SOLICITADO | C66: PRE-FIS-ZIM-2025-01/27-3454 | D66: Alejandra Peltier | E66: CS-2025-02316 | F66: Xsur | G66: ZIM | H66: MONACO | I66: Da Chan Bay | J66: 16.01.2025 | K66: Teamhead | L66: 110W | M66: Falta AoR y Final report | N66: Temperature | O66: Cherries | Q66: 17.01.2027 | S66: 14.04.2026
A67: 11983.65 | B67: SOLICITADO | C67: PRE-FIS-CMA-2025-05/27-4011 | D67: Alejandra Peltier | E67: CS-2025-06233 | F67: FRUSAN | G67: CMA CGM | H67: MATTHEW SCHULTE | I67: Leghorn | J67: 13.05.2025 | K67: Spolidoro | L67: 041 | M67: Falta AoR | N67: Temperature | O67: Pears & grapes | P67: 13.04.2025 | Q67: 13.05.2027 | S67: 08.04.2026
A68: 40344.63 | B68: SOLICITADO | C68: PRE-FIS-OTC-2025-05/27-4033 | D68: Alejandra Peltier | E68: CS-2025-06872 | F68: FRUSAN | G68: CMA CGM | H68: MARTINIQUE | I68: Leghorn | J68: 26.05.2025 | K68: Spolidoro | L68: 0LIGVN1MA | M68: Falta AoR | N68: Temperature & Delay | O68: Pears | P68: 22.03.2025 | Q68: 26.05.2027 | S68: 08.04.2026
A69: 60338 | B69: SOLICITADO | C69: PRE-FIS-MSC-2025-02/27-3549 | D69: Alejandra Peltier | E69: CS-2025-02321 | F69: FRUSAN | G69: MSC | H69: MANZANILLO EXPRESS | I69: Laem Chabang | J69: 12.02.2025 | K69: Bangkok Average | L69: 2443W | M69: Falta AoR | N69: Temperature | O69: CHERRIES | Q69: 12.02.2027 | S69: 08.04.2026
B70: CALCULAR LOSS | C70: PRE-FIS-MAE-2025-05/27-4043 | D70: Emely Lambraño | E70: CS-2025-05426 | F70: Servicios Chilfresh | G70: Maersk | H70: MAERSK YUKON | I70: Cat Lai Port | J70: 06.05.2025 | K70: AIM Control | L70: 509W | M70: Falta subro, harvest, SMV ó comparativa, DUS, IVV. | N70: Delay | O70: Grapes | P70: 12.03.2025 | Q70: 06.05.2027
A71: 13195.56 | B71: SOLICITAR | C71: PRE-FIS-MAE-2025-03/27-3467 | D71: Emely Lambraño | E71: CS-2025-02865 | F71: A5 Export | G71: Maersk | H71: MAERSK LIMA | I71: Hong Kong | J71: 12.03.2025 | K71: Teamhead | M71: Falta Subro, AoR, Harvest. | N71: Temperature | Q71: 12.03.2027
A72: 53526.94 | B72: SOLICITADO | C72: PRE-FIS-MAE-2025-02/27-3853 | D72: Emely Lambraño | E72: CS-2025-02991 | F72: RANCO | G72: Maersk | H72: MAERSK LIMA | I72: Hong Kong | J72: 12.03.2025 | K72: Teamhead | L72: 505W | M72: Falta AoR, Survey report (solicitado) | N72: Temperature | O72: Plums | P72: 11.02.2025 | Q72: 12.03.2027 | R72: 10.07.2025
B73: CALCULAR LOSS | C73: PRE-FIS-MAE-2025-05/27-4048 | D73: Emely Lambraño | E73: CS-2025-05581 | F73: Servicios Chilfresh | G73: Maersk | H73: MAERSK LABERINTO | I73: Cat Lai Port | J73: 15.05.2025 | K73: AIM Control | L73: 510W | M73: Falta subro, harvest, SMV, DUS, IVV. | N73: Delay | O73: Grapes | P73: 18.03.2025 | Q73: 15.05.2027
B74: CALCULAR LOSS | C74: PRE-FIS-MAE-2025-05/27-4047 | D74: Emely Lambraño | E74: CS-2025-05582 | F74: Servicios Chilfresh | G74: Maersk | H74: MAERSK LABERINTO | I74: Cat Lai Port | J74: 15.05.2025 | K74: AIM Control | L74: 510W | M74: Falta subro, harvest, SMV, origin. | N74: Delay | O74: Grapes | P74: 19.03.2025 | Q74: 15.05.2027
A75: 5889.87 | B75: SOLICITAR | C75: PRE-FIS-MAE-2025-04/27-3906 | D75: Emely Lambraño | E75: CS-2025-05394 | F75: Magna | G75: Maersk | H75: MAERSK BULAN | I75: Barcelona | J75: 30.04.2025 | K75: Eurovet | L75: 509N | M75: Falta Subro, AoR, Origin certificate | N75: Delay(20 days) & Temperature | O75: Pears | P75: 06.03.2025 | Q75: 30.04.2027
A76: 39132.3 | B76: SOLICITADO | C76: PRE-FIS-MAE-2025-05/27-4050 | D76: Emely Lambraño | E76: CS-2025-05870 | F76: Servicios Chilfresh | G76: Maersk | H76: MAERSK BOGOR | I76: Philadelphia | J76: 26.05.2025 | K76: PCCC | L76: 517N | M76: Falta AoR, harvest, origin, Fito. | N76: Delay | O76: Grapes | P76: 01.05.2025 | Q76: 26.05.2027
A77: 14987.75 | B77: SOLICITADO | C77: PRE-FIS-MAE-2025-02/27-3922 | D77: Alejandra Peltier | E77: CS-2025-02313 | F77: Prize | G77: Maersk | H77: MAERSK BINTAN | I77: Vlissingen | J77: 16.02.2025 | K77: Fruit Inspection & Consultancy BV | L77: 503N | M77: Falta subro, AoR, harvest, SR | N77: Temperature | O77: Blueberries | P77: 11.01.2025 | Q77: 16.02.2027 | R77: 16.07.2025 | S77: 13.07.2026
A78: 54830.43 | B78: SOLICITADO | C78: PRE-FIS-MAE-2025-02/27-3921 | D78: Emely Lambraño | E78: CS-2025-02337 | F78: Servicios Chilfresh | G78: Maersk | H78: MAERSK BENGUELA | I78: Philadelphia | J78: 03.02.2025 | K78: PCCC | L78: 502N | M78: Falta Subro, AoR, harvest certificate, destruction certificate (solo está el invoice y detalle de carga destruida), Export Invoice | N78: delay | O78: Nectarines | P78: 16.01.2025 | Q78: 03.02.2027
A79: 4220.76 | B79: PRESENTAR | C79: PRE-FIS-MAE-2025-05/27-4148 | D79: Alejandra Peltier | E79: CS-2025-11723 | F79: Lo Garces | G79: Maersk | H79: MAERSK BENGUELA | I79: London Gateway | J79: 11.05.2025 | K79: no surveyor involved | L79: 511N | M79: Ok (cliente no cuenta con termógrafos) | O79: Plums | P79: 19.03.2025 | Q79: 11.05.2027 | R79: 23.03.2026 | S79: 07.04.2026
B80: CALCULAR LOSS | C80: PRE-FIS-MAE-2025-08/27-4176 | D80: Emely Lambraño | E80: CS-2025-08894 | F80: Magna | G80: Maersk | H80: MAERSK BENGUELA | I80: Rotterdam | J80: 18.08.2025 | K80: Fruit Inspection & Consultancy BV | L80: 529N | M80: Falta Subro, AoR, harvest, DUS, IVV, survey report, sales acc, staffing, origin. | N80: Temperature | O80: Apples | P80: 23.07.2025 | Q80: 18.08.2027 | R80: 04.12.2025
A81: 16079.9 | B81: SOLICITADO | C81: PRE-FIS-MAE-2025-03/27-4054 | D81: Emely Lambraño | E81: CS-2025-09269 | F81: FRUTAM | G81: Maersk | H81: MAERSK BAYETE | I81: Manzanillo | J81: 10.03.2025 | L81: 506N | M81: Falta subro, AoR, harvest, DUS, IVV, Sales Invoices | N81: Temperature | O81: Nectarines | P81: 13.20.2025 | Q81: 10.03.2027
A82: 59586.14 | B82: SOLICITADO | C82: PRE-FIS-MAE-2025-05/27-4164 | D82: Emely Lambraño | E82: CS-2025-06013 | F82: Propal | G82: Maersk | H82: MAERSK BAYETE | I82: London Gateway | J82: 29.05.2025 | K82: Fresh Produce | L82: 515N | M82: Falta subro | N82: Delay | O82: Avocados | P82: 17.04.2025 | Q82: 29.05.2027
A83: 59919.56 | B83: SOLICITADO | C83: PRE-FIS-MAE-2025-12/26-3459 | D83: Emely Lambraño | E83: CS-2025-00088 | F83: Propal | G83: Maersk | H83: MAERSK BATUR | I83: Rotterdam | J83: 30.12.2024 | K83: Fruit Inspection & Consultancy BV | M83: Falta Subro, AoR, Certificado of consigment processed in Oil | N83: CA Issues | O83: Avocados | P83: 04.12.2024 | Q83: 30.12.2026 | R83: 15.04.2025
A84: 40404 | B84: SOLICITADOS | C84: PRE-FIS-MAE-2025-05/27-4132 | D84: Alejandra Peltier | E84: CS-2025-05971 | F84: Lo Garces | G84: Maersk | H84: MAERSK BATUR | I84: London Gateway | J84: 14.05.2025 | K84: Fresh Produce | L84: 504N | M84: Falta destruction certificate and Invoice. | N84: Delay | O84: Nectarines | P84: 30.01.2025 | Q84: 14.05.2027 | R84: 23.03.2026 | S84: 07.04.2026
B85: CALCULAR LOSS | C85: PRE-FIS-MAE-2025-08/27-4177 | D85: Emely Lambraño | E85: CS-2025-08895 | F85: Magna | G85: Maersk | H85: MAERSK BATUR | I85: Philadelphia | J85: 25.08.2025 | K85: PCCC | L85: 531N | M85: Falta Subro, AoR, harvest, DUS, IVV, final report, sales acc, origin, phyto, booking, export Invoice. | N85: Temperature | O85: Apples | P85: 07.08.2025 | Q85: 25.08.2027 | R85: 04.12.2025
A86: 40684.32 | B86: SOLICITADOS | C86: PRE-FIS-MAE-2025-04/27-4135 | D86: Alejandra Peltier | E86: CS-2025-04262 | F86: Lo Garces | G86: Maersk | H86: MAERSK BATAM | I86: London | J86: 14.04.2025 | K86: Fresh Produce | L86: 505N | M86: Falta SR, destruction certificate and Invoice, SMV o liq. Comparativa, | N86: Delay | O86: Nectarines | P86: 06.02.2025 | Q86: 14.04.2027 | R86: 23.03.2026 | S86: 07.04.2026
A87: 12991.98 | B87: SOLICITADO | C87: PRE-FIS-COL-2025-02/27-3929 | D87: Alejandra Peltier | E87: CS-2025-02505 | F87: Prize | G87: Seatrade | H87: LADY ROSE | I87: Gloucester City | J87: 09.02.2025 | K87: PCCC | L87: EC060 | M87: Falta subro, harvest, tracking, booking | N87: Delay | O87: Blueberries | Q87: 09.02.2027 | R87: 16.07.2025 | S87: 13.07.2026
B88: CALCULAR LOSS | C88: PRE-FIS-MAE-2025-04/27-3994 | D88: Emely Lambraño | E88: CS-2025-04691 | F88: Magna | G88: Maersk | H88: JPO PISCES | I88: Barcelona | J88: 17.04.2025 | K88: Eurovet | L88: 507N | M88: Falta subro, AoR, DUS, IVV. | N88: Delay | O88: Pears | P88: 19.02.2025 | Q88: 17.04.2027
A89: 54403.31 | B89: SOLICITADO | C89: PRE-FIS-MAE-2025-04/27-4159 | D89: Emely Lambraño | E89: CS-2025-04689 | F89: Propal | G89: Maersk | H89: JPO LIBRA | I89: Southampton | J89: 23.04.2025 | K89: Fresh Produce | L89: 510N | M89: Falta subro, harvest | N89: Delay (Total de notas de crédito se pasan de Libras a USD - currency rate de fecha de arribo) | O89: Avocados | P89: 14.03.2025 | Q89: 23.04.2027
A90: 45803.79 | B90: SOLICITADO | C90: PRE-FIS-MAE-2025-04/27-4160 | D90: Emely Lambraño | E90: CS-2025-04690 | F90: Propal | G90: Maersk | H90: JPO LIBRA | I90: Southampton | J90: 23.04.2025 | K90: Fresh Produce | L90: 510N | M90: Falta subro, AoR, harvest | N90: Delay (Total de notas de crédito se pasan de Libras a USD - currency rate de fecha de arribo) | O90: Avocados | P90: 14.03.2025 | Q90: 23.04.2027
A91: 41354.97 | B91: SOLICITADO | C91: PRE-FIS-MAE-2025-04/27-4161 | D91: Emely Lambraño | E91: CS-2025-05389 | F91: Propal | G91: Maersk | H91: JPO LIBRA | I91: Southampton | J91: 23.04.2025 | K91: Fresh Produce | L91: 510N | M91: Falta subro | N91: Delay (Total de notas de crédito se pasan de Libras a USD - currency rate de fecha de arribo) | O91: Avocados | P91: 14.03.2025 | Q91: 23.04.2027
A92: 44418.08 | B92: SOLICITADO | C92: PRE-FIS-MAE-2025-04/27-4162 | D92: Emely Lambraño | E92: CS-2025-05390 | F92: Propal | G92: Maersk | H92: JPO LIBRA | I92: Southampton | J92: 23.04.2025 | K92: Fresh Produce | L92: 510N | M92: Falta subro | N92: Delay (Total de notas de crédito se pasan de Libras a USD - currency rate de fecha de arribo) | O92: Avocados | P92: 14.03.2025 | Q92: 23.04.2027
A93: 23634.97 | B93: SOLICITADO | C93: PRE-FIS-HLL-2025-01/27-3920 | D93: Alejandra Peltier | E93: CS-2025-00925 | F93: Prize | G93: Hapag Lloyd | H93: ITAJAI EXPRESS | I93: Hong Kong | J93: 20.01.2025 | K93: Teamhead | L93: 2444W | M93: Falta AoR, Harvest certificate | N93: Temperature | O93: Nectarines | P93: 29.12.2024 | Q93: 21.01.2027 | R93: 18.07.2025 | S93: 13.07.2026
A94: 36100 | B94: SOLICITADO | C94: PRE-FIS-HLL-2025-05/27-4006 | D94: Alejandra Peltier | E94: CS-2025-05573 | F94: GLS | G94: Hapag Lloyd | H94: ISTANBUL EXPRESS | I94: London Gateway | J94: 18.05.2025 | K94: MMS | L94: 5208N | M94: Falta AoR, origin, Booking | N94: Temperature & Delay | O94: Grapes | P94: 04.04.2025 | Q94: 18.05.2027 | S94: 14.07.2026
A95: 22900.26 | B95: SOLICITADO | C95: PRE-FIS-HMM-2025-02/27-3924 | D95: Alejandra Peltier | E95: CS-2025-02506 | F95: Prize | G95: HMM | H95: HUMBOLDT EXPRESS | I95: Hong Kong | J95: 19.02.2025 | K95: Teamhead | L95: 0004W | M95: Falta AoR, harvest, stuffing | N95: Temperature | O95: Plums | P95: 24.01.2025 | Q95: 19.02.2027 | R95: 18.07.2025 | S95: 13.07.2026
A96: 7028.99 | B96: SOLICITADO | C96: PRE-FIS-HLL-2025-01/27-4093 | D96: Alejandra Peltier | E96: CS-2025-00508 | F96: GLS | G96: Hapag Lloyd | H96: GUAYAQUIL EXPRESS | I96: London Gateway | J96: 09.01.2025 | K96: MMS | L96: 4242N | M96: Falta AoR, origin, SR, stuffing. | N96: Delay 14 días | O96: Avocados | P96: 28.11.2024 | Q96: 09.01.2027 | S96: 14.07.2026
B97: SOLICITADO | C97: PRE-FIS-HLL-2025-01/27-4094 | D97: Emely Lambraño | E97: CS-2025-00428 | F97: Jorge Schmidt | G97: Hapag Lloyd | H97: GUAYAQUIL EXPRESS | I97: London Gateway | J97: 09.01.2025 | K97: MMS | L97: 4242N | M97: Falta subro, AoR, harvest certificate | N97: Delay (12 days) | O97: Avocados | P97: 28.11.2024 | Q97: 09.01.2027
B98: SOLICITADO | C98: PRE-FIS-EVE-2025-01/27-3907 | D98: Emely Lambraño | E98: CS-2025-11834 | F98: Aqu Anqa ll | G98: Evergreen | H98: EVER LUCKY | I98: Kaoshiung | J98: 02.01.2025 | K98: Intertek, SGP | L98: 075W | M98: Falta Subro, AoR, origin, harvest certificate, export Invoice, Sales acc and Invoices | N98: Investigar mayor profundidad, inland incluido en BL demora casi 2 meses en total | O98: Blueberries | P98: 28.11.2024 | Q98: 30.01.2027
B99: SOLICITADO | C99: PRE-FIS-CC-2025-03/27-3847 | D99: Emely Lambraño | E99: CS-2025-03717 | F99: Copefrut | G99: Cool Carriers | H99: CS STRATOS | I99: Gloucester City | J99: 12.03.2025 | K99: PCCC | M99: Falta Subro, Survey report, SMV. | N99: Temperature | O99: Plums | P99: 21.02.2025 | Q99: 12.03.2027
A100: 188912 | B100: SOLICITADO | C100: PRE-FIS-CC-2025-02/27-3855 | D100: Emely Lambraño | E100: CS-2025-02538 | F100: RANCO | G100: Cool Carriers | H100: CS STRATOS | I100: Gloucester City | J100: 06.02.2025 | K100: PCCC | L100: EC050 | M100: Falta Subro, Tracking | N100: CT failure | O100: Cherries | P100: 25.01.2025 | Q100: 06.02.2027 | R100: 10.07.2025
...

Sheet Revisar
A1: 0 | B1: Id | C1: Reference No | D1: Claim Handler | E1: CS Claim No | F1: Assured | G1: Opponent | H1: Vessel | I1: Place of Discharge | J1: Date of Discharge | K1: Surveyorco | L1: Voyage | M1: Status | N1: Summary | O1: Commodity | P1: Date of Loading | Q1: TB | R1: Fecha de Orden

Sheet Presentar
A1: Claim amount | B1: Fecha de Traspaso | C1: Reference No | D1: Claim Handler | E1: CS Claim No | F1: Assured | G1: Opponent | H1: Vessel | I1: Place of Discharge | J1: Date of Discharge | K1: Surveyorco | L1: Voyage | M1: Status | N1: Summary | O1: Commodity | P1: Date of Loading | Q1: TB | R1: Comments
A2: 4220.76 | B2: 20.08.2026 | C2: PRE-FIS-MAE-2025-05/27-4148 | D2: Alejandra Peltier | E2: CS-2025-11723 | F2: Lo Garces | G2: Maersk | H2: MAERSK BENGUELA | I2: London Gateway | J2: 11.05.2025 | K2: no surveyor involved | L2: 511N | M2: Ok (cliente no cuenta con termógrafos) | O2: Plums | P2: 19.03.2025 | Q2: 11.05.2027 | R2: 23.03.2026 | S2: 07.04.2026
A3: 5400 | B3: 20.08.2026 | C3: PRE-FIS-MSC-2025-02/27-4147 | D3: Alejandra Peltier | E3: CS-2025-11720 | F3: Lo Garces | G3: MSC | H3: MSC BRITTANY | I3: London Gateway | J3: 17.02.2025 | K3: no surveyor involved | L3: NX502R | M3: Ok (cliente no cuenta con termógrafos) | N3: Delay | O3: Nectarines | P3: 09.01.2025 | Q3: 17.02.2027 | R3: 23.03.2026 | S3: 07.04.2026
A4: 52883.43 | B4: 20.08.2026 | C4: PRE-FIS-MSC-2026-01/28-4458 | D4: Alejandra Peltier | E4: CS-2026-01462 | F4: FRUSAN | G4: MSC | H4: MSC LEIGH | I4: Shanghai | J4: 14.01.2026 | K4: Teamhead | L4: XA549A | M4: Falta Harvest, SR | N4: Temperature | O4: Cherries | P4: 19.12.2025 | Q4: 14.01.2028 | R4: 15.04.2026
A5: 37076.48 | B5: 20.08.2026 | C5: PRE-FIS-ONE-2026-02/28-4571 | D5: Alejandra Peltier | E5: CS-2026-02369 | F5: FRUSAN | G5: ONE | H5: BUENOS AIRES EXPRESS | I5: Shanghai | J5: 19.02.2026 | K5: Teamhead | L5: 2545W | M5: Falta harvest certificate, survey report, claim notice. | N5: Delay (16 days) | O5: Blueberries | P5: 28.12.2025 | Q5: 19.02.2028 | R5: 29.04.2026 | S5: 06.07.2026
A6: 53664.68 | B6: 20.08.2026 | C6: PRE-FIS/AGR-MSC-2026-03/27-4731 | D6: Emely Lambraño | E6: DIRECTO | F6: Agricom | G6: MSC | H6: MSC CASSANDRE | I6: Los Angeles | J6: 11.03.2026 | K6: PCCC | L6: NX607R | M6: Falta LoA, AoR, harvest certificate. (en gestión) | N6: Temperature | O6: Plums | P6: 15.02.2026 | Q6: 11.03.2028 | R6: 10.08.2026

Sheet Traspasados
C1: Reference No | D1: Claim Handler | E1: CS Claim No | F1: Assured | G1: Opponent | H1: Vessel | I1: Place of Discharge | J1: Date of Discharge | K1: Surveyorcomp | L1: Voyage | M1: Status | N1: Summary | O1: Commodity | P1: Date of Loading | Q1: TB | R1: Participation | S1: Reunión comentarios
A2: 35131 | B2: TRASPASADO | C2: PRE-FIS-TKS-2023-01/24-2580 | D2: Camila Sanhueza | E2: CS-2022-12584 | F2: Gidding Cerasus S.A. | G2: Turkish Airlines | I2: Phnom Penh | J2: 02.01.2022 | K2: Other | L2: TK0900/21 TK0778/23 | M2: Falta claim notice | N2: DELAY 11 DIAS + TEMPS | O2: Cherries | P2: 20.12.2021 | Q2: 02.01.2024
A3: 29557.86 | B3: TRASPASADO | C3: PRE-FIS-YAN-2023-03/25-2667 | D3: Nicolas Aravena | E3: CS-2023-04197 | F3: FRUSAN | G3: Yang Ming | H3: (NOT IN LIST) | I3: Shanghai | J3: 05.03.2023 | K3: Teamhead | L3: W013 | M3: Falta Harvest, DUS, IVV, STUFFING, PHYTO, ORIGIN, BOOKING | N3: CA | O3: PLUMS | P3: 04.02.2023 | Q3: 05.03.2025
A4: 50927.79 | B4: TRASPASADO/SR | C4: PRE-FIS-COS-2023-01/25-2562 | D4: Victor Vilches | E4: CS-2023-04357 | F4: Copefrut | G4: COSCO | H4: (NOT IN LIST) | I4: Shanghai | J4: 14.01.2023 | K4: Teamhead | L4: 049W | M4: Falta , claim notice, , harvest, SR | N4: VENTILATION | O4: Cherries | P4: 18.12.2022 | Q4: 14.01.2025
A5: 43143.51 | B5: TRASPASADO | C5: PRE-FIS-COS-2023-01/25-2563 | D5: Victor Vilches | E5: CS-2023-04359 | F5: Copefrut | G5: COSCO | H5: (NOT IN LIST) | I5: Shanghai | J5: 14.01.2023 | K5: Teamhead | L5: 049W | M5: Falta , claim notice harvest, | N5: TEMPERATURE | O5: Cherries | P5: 17.12.2022 | Q5: 14.01.2025 | S5: 15.06.2023 Preguntarle a Kelly comentarios. Si es origen, se cierra
A6: 3360 | B6: TRASPASADO | C6: PRE-FIS-CC-2023-03/25-2729 | D6: Camila Sanhueza | E6: CS-2023-04250 | F6: Agricom | G6: Cool Carriers | H6: (NOT IN LIST) | I6: Gloucester City | J6: 05.03.2023 | K6: PCCC | L6: EC140 | M6: ok | N6: CONTAMINATION | O6: Grapes | P6: 20.02.2023 | Q6: 05.03.2025
A7: 12181.25 | B7: PRESENTAR | C7: PRE-FIS-AFR-2024-12/25-3133 | D7: Isidora Martinez | E7: CS-2024-02031 | F7: AMS EUROPEAN | G7: Air France | H7: AIRFREIGHT | I7: Charles de Gaulle Airport | J7: 09.12.2023 | K7: Other | L7: AF0401 | M7: Falta harvest, stuffing, booking | N7: Delay 2 dias | O7: CHERRIES | P7: 08.12.2023 | Q7: 09.12.2025
A8: 25340.46 | B8: PRESENTAR | C8: PRE-FIS-QAW-2024-11/25-3042 | D8: Thomas Chatterton | E8: CS-2024-01396 | F8: Agricom | G8: Qatar Airways | H8: AIRFREIGHT | I8: Mumbai | J8: 30.11.2023 | K8: Intertek, IND | L8: QR8307 | M8: ok | N8: Variaciones de temperatura durante tránsito y al embarque. | O8: Cherries | P8: 25.11.2023 | Q8: 30.11.2025
A9: 273127 | B9: TRASPASADO | C9: PRE-FIS-ONE-2023-02/25-2717 | D9: Isidora Martinez | E9: CS-2023-04245 | F9: Agricom | G9: ONE | H9: AKADIMOS | I9: Hong Kong | J9: 19.02.2023 | K9: Teamhead | L9: 2250W | M9: Falta Harvest, DUS, IVV | N9: TEMPERATURA | O9: Cherries | P9: 25.01.2023 | Q9: 19.02.2025
A10: 3254.75 | B10: TRASPASADO | C10: PRE-FIS-CMA-2023-01/24-2861 | D10: Camila Sanhueza | E10: CS-2023-08134 | F10: Itacu Corporation ltda. | G10: CMA CGM | H10: ALEXIS | I10: Catania | J10: 17.01.2023 | K10: Spolidoro | L10: 0DVEEN1MA | M10: ok | N10: Temperature. Dos interrupciones importantes de temperatura | O10: BANANAS | P10: 29.12.2022 | Q10: 17.01.2024
A11: 12697.73 | B11: TRASPASADO | C11: PRE-FIS-CMA-2023-03/24-2749 | D11: Isidora Martinez | E11: CS-2023-04345 | F11: Itacu Corporation ltda. | G11: CMA CGM | H11: ALEXIS | I11: Catania | J11: 13.03.2023 | K11: Spolidoro | L11: 0DVEUN1MA | M11: ok | N11: TEMPERATURE | O11: BANANAS | P11: 23.02.2023 | Q11: 13.03.2024
A12: 38660.49 | B12: TRASPASADO | C12: PRE-FIS-CMA-2024-01/24-2884 | D12: Camila Sanhueza | E12: CS-2023-08133 | F12: Itacu Corporation ltda. | G12: CMA CGM | H12: ALEXIS | I12: Catania | J12: 17.01.2023 | K12: Spolidoro | L12: 0DVEEN1MA | M12: ok | N12: Temperature issues | O12: Bananas | P12: 29.12.2022 | Q12: 17.01.2024
A13: 6407.8 | B13: PRESENTAR | C13: PRE-FIS-ONE-2024-01/26-2963 | D13: Thomas Chatterton | E13: CS-2024-01483 | F13: Agricola Rapel | G13: ONE | H13: ALGOL | I13: Kaohsiung | J13: 04.01.2024 | K13: Teamhead | L13: 23023N | M13: OK | N13: DELAY 14 DIAS | O13: GRAPES | P13: 14.11.2023 | Q13: 04.01.2026
A14: 54886.53 | B14: TRASPASADO | C14: PRE-FIS-HLL-2023-01/25-2663 | D14: Barbara Choque | E14: CS-2023-04186 | F14: FRUSAN | G14: Hapag Lloyd | H14: AMALTHEA | I14: Nansha | J14: 09.01.2023 | K14: Teamhead | L14: 0001W | M14: Falta factura exportación, DUS, IVV, Booking, Stuffing Report | N14: Temperature issues | O14: Cherries | P14: 17.12.2022 | Q14: 09.01.2025
A15: 100556.87 | B15: TRASPASADO | C15: PRE-FIS-EVG-2023-01/25-2507(EX) | D15: Barbara Choque | E15: CS-2023-04664 | F15: Prize | G15: Evergreen | H15: ANTHEA Y | I15: Keelung | J15: 20.01.2023 | K15: Teamhead | M15: ok | N15: TEMPERATURA | O15: Cherries | P15: 21.12.2022 | Q15: 20.01.2025
A16: 26020.99 | B16: TRASPASADO | C16: FIS-HAM-2022-01/23-1370 | D16: Isidora Martinez | E16: CS-2021-50556 | F16: Copefrut | G16: Hamburg Süd | H16: AOTEA MAERSK | I16: Hong Kong | J16: 07.01.2021 | K16: Teamhead | L16: 049W | M16: Falta HC. | N16: TEMP ( Se sugiere exhibición) | O16: Cherries | P16: 16.12.2020 | Q16: 44933
A17: 64755.59 | B17: TRASPASADO | C17: PRE-FIS-COS-2022-10/23-2246 | D17: Isidora Martinez | E17: CS-2022-12238 | F17: Jealous Fruits | G17: COSCO | H17: APL LE HAVRE | I17: Vancouver/Shanghai | J17: 04.10.2022 | K17: Teamhead | L17: 0TN7CN1MA | M17: Falta reporte de calidad | N17: Delay 11 days, as per BL -0,5°C and thermograph shows 2,1°C and 3,1°C | O17: Cherries | P17: 10.09.2022 | Q17: 45203
A18: 46276.19 | B18: TRASPASADO | C18: PRE-FIS-COS-2022-10/23-2245 | D18: Isidora Martinez | E18: CS-2022-12237 | F18: Jealous Fruits | G18: COSCO | H18: APL LE HAVRE | I18: Vancouver/Shanghai | J18: 04.10.2022 | K18: Teamhead | L18: OTN7CN1MA | M18: Falta reporte de calidad | N18: Delay 11 days | O18: Cherries | P18: 10.09.2022 | Q18: 45203
A19: 101131.87 | B19: TRASPASADO | C19: FIS-HLL-2022-01/23-2004 | D19: Isidora Martinez | E19: CS-2022-02353 | F19: Asica Farms SAC | G19: Hapag Lloyd | H19: AS PATRIA | I19: Malaga | J19: 13.01.2022 | K19: Eurovet | L19: 2139W | M19: Falta BL Máster | N19: TEMPERATURA | O19: Blueberries | P19: 16.12.2021 | Q19: 44939 | S19: Se continua con solicitud de documentos. Se traspasa a Isi para avance.
A20: 87181.04 | B20: TRASPASADO | C20: PRE-FIS-CMA-2022-02/23-2018 | D20: Isidora Martinez | E20: CS-2022-05388 | F20: Asica Farms SAC | G20: CMA CGM | H20: AS PATRIA | I20: Paita / | J20: 16.02.2022 | K20: Eurovet | L20: 0VF7CN1MA | M20: ok | N20: Delay 15 días | O20: Mangoes | P20: 12.01.2022 | Q20: 44973
A21: 23940 | B21: TRASPASADO | C21: PRE-FIS-CMA-2022-03/23-2149 | D21: Isidora Martinez | E21: CS-2022-05302 | F21: Frusan Agro | G21: CMA CGM | H21: AS PATRIA | I21: Paita-Hai Phòng | J21: 16.03.2022 | L21: 0VF7CN1MA | M21: Factura comercial, packing list, notificación naviera, reporte consolidado con temperaturas | N21: Delay TT 68 días. | O21: Grapes | P21: 12.01.2022 | Q21: 45001 | S21: 02-02-2023 - Para solicitud de TE, a medida que lleguen docus se irán proporcionando
A22: 65365.5 | B22: TRASPASADO | C22: PRE-FIS-STD-2023-11/24-2366 | D22: Camila Sanhueza | E22: CS-2022-12648 | F22: Agualima | G22: Seatrade | H22: ATLANTIC REEFER | I22: Vlissingen | J22: 01.11.2022 | K22: Fruit Inspection & Consultancy BV | L22: CS | M22: ok | N22: Alza de temperatura | O22: Blueberries | P22: 16.10.2022 | Q22: 01.11.2024
A23: 41367.75 | B23: PRESENTAR | C23: PRE-FIS-TRS-2024-02/25-2918 | D23: Nicolás Aravena | E23: CS-2023-04154 | F23: Geofrut | G23: Trans Global | H23: AUTUMN STREAM | I23: Wilmington | J23: 14.02.2023 | K23: PCCC | L23: USEC-04 | M23: ok | N23: Temperature | O23: Grapes | P23: 26.01.2023 | Q23: 14.02.2025 | R23: Innspector indica que necesitan de otros antecedentes para continuar con el caso, de lo contrario no pueden emitir reporte. Hemos focalizado solicitud con Susane.- Inspector responde que aun clarificando la venta (por la cantidad de cajas del embarque y clarificando los termógrafos correspondientes al caso, no se justificaría el daño encontrado en la carga (más bien de origen).- | S23: Se traspasa a Judicial pq no se consigue TE
A24: 17802.23 | B24: TRASPASADO | C24: PRE-FIS-CMA-2023-04/25-2658 | D24: Nicolas Aravena | E24: CS-2023-05904 | F24: David del Curto | G24: CMA CGM | H24: BALLENITA | I24: Leghorn | J24: 11.04.2023 | K24: Spolidoro | M24: Falta DUS, IVV | N24: TEMPERATURAS | O24: Pears | P24: 25.02.2023 | Q24: 11.04.2025
A25: 58288.15 | B25: TRASPASADO | C25: PRE-FIS-CMA-2023-05/25-2788 | D25: Isidora Martinez | E25: CS-2023-10246 | F25: FRUSAN | G25: CMA CGM | H25: BALLENITA | I25: Leghorn | J25: 21.05.2023 | K25: Spolidoro | L25: 0LI0WN1MA | M25: Falta Harvest, Booking (todos los contenedores), Origen (todos los contenedores) DUS, IVV (todos los contenedores) | N25: Temperature issues | O25: PEARS | P25: 07.04.2023 | Q25: 21.05.2025
A26: 16084.04 | B26: TRASPASADO | C26: FIS-HLL-2022-03/23-1465(EX) | D26: Nicolas Aravena | E26: cs2021-58170 | F26: Subsole | G26: Hapag Lloyd | H26: BOMAR JULIANA | I26: London Gateway | J26: 02.03.2021 | K26: Fresh Produce | L26: 0053N | M26: Falta liquidación 1. 27.05.2022 (LB) 596 boxes were dumped (11.324 GBP), DUS | N26: Low temperature abuse resulting in chill damage to the grapes | O26: Grapes | P26: 28.01.2021 | Q26: 44987
A27: 20631.45 | B27: TRASPASADO | C27: FIS-CMA-2022-02/23-1405(EX) | D27: Nicolas Aravena | E27: CS-2021-51124 | F27: ROVEG | G27: CMA CGM | H27: BOMAR JULIANA | I27: Rotterdam | J27: 25.02.2021 | K27: Fruit Inspection & Consultancy BV | L27: Falta SR. | M27: Temperatura anormal | O27: 25.02.2023
A28: 176594.68 | B28: TRASPASADO | C28: PRE-FIS-UCC-2023-03/25-2727 | D28: Barbara Choque | E28: CS-2023-05449 | F28: Verfrut | H28: BOMAR PRAIA | I28: Algeciras | K28: Eurovet | L28: 0LI0GN1MA | M28: Falta Tracking, DUS IVV | N28: TEMPERATURA | O28: PEARS | P28: 11.02.2023 | Q28: 07.03.2023
A29: 71025.24 | B29: PRESENTAR | C29: PRE-FIS-MSC-2024-02/26-3077 | D29: Nicolas Aravena | E29: CS-2024-02433 | F29: Verfrut | G29: MSC | H29: BUENAVENTURA EXPRESS | I29: Hong Kong | J29: 21.02.2024 | K29: Teamhead | L29: 2349W | M29: Falta SR. | N29: Temperature | O29: Nectarines | P29: 27.01.2024 | Q29: 21.02.2026
A30: 76377.6 | B30: PRESENTAR | C30: PRE-FIS-HLL-2024-03/26-3093 | D30: Barbara Choque | E30: CS-2024-02452 | F30: RANCO | G30: Hapag Lloyd | H30: BUENAVENTURA EXPRESS | I30: Busan | J30: 01.03.2024 | K30: Hyopsung | L30: 2349W | M30: ok | N30: Condicion de origen exacerbada por temperatura | O30: Cherries | P30: 28.01.2024 | Q30: 01.03.2026 | S30: 19.06.2024 (LB) EX una vez listo, sin presentar reporte
A31: 69147.6 | B31: PRESENTAR | C31: PRE-FIS-HLL-2024-03/26-3094 | D31: Barbara Choque | E31: CS-2024-02424 | F31: RANCO | G31: Hapag Lloyd | H31: BUENAVENTURA EXPRESS | I31: Busan | J31: 01.03.2024 | K31: Hyopsung | L31: 2349W | M31: ok | N31: Condicion de origen exacerbada por temperatura | O31: Cherries | P31: 28.01.2024 | Q31: 01.03.2026 | S31: 19.06.2024 (LB) EX una vez listo, sin presentar reporte
A32: 66000 | B32: PRESENTAR | C32: PRE-FIS-MSC-2024-06/26-3192 | D32: Barbara Choque | E32: CS-2024-07006 | F32: Verfrut | G32: MSC | H32: BUENAVENTURA EXPRESS | I32: Surabaya | J32: 28.06.2024 | K32: Carsurin | L32: 2410W | M32: Falta AoR | N32: DELAY 22 DIAS // falla cold treatment | O32: GRAPES | P32: 24.04.2024 | Q32: 28.06.2026
A33: 23716.14 | B33: PRESENTAR | C33: PRE-FIS-CMA-2023-05/25-2829 | D33: Barbara Choque | E33: CS-2023-07076 | F33: FRUSAN | G33: CMA CGM | H33: BUENOS AIRES EXPRESS | I33: Rotterdam | J33: 24.05.2023 | K33: Fruit Inspection & Consultancy BV | L33: 0WCEKN1MA | M33: Falta Origen, Booking, DUS, IVV, Stuffing, SR. | N33: Inspecto indica 10% relacionado a transporte y el resto origen. Evidente problema de temperatura en viaje. | O33: Apples | P33: 27.04.2023 | Q33: 24.05.2025 | S33: 26.09.2024 NO USAR REPORTE
A34: 35543.75 | B34: PRESENTAR | C34: PRE-FIS-HLL-2024-03/26-3284 | D34: Victor Vilches | E34: CS-2024-08131 | F34: FRUSAN | G34: Hapag Lloyd | H34: BUENOS AIRES EXPRESS | I34: Hong Kong | J34: 14.03.2024 | K34: no surveyor involved | L34: 2352W | M34: Falta Claim notice, DUS, IVV | N34: DELAY 6 DIAS POL/ pérdida de mercado | O34: Plums | P34: 21.02.2024 | Q34: 14.03.2026
A35: 37008 | B35: PRESENTAR | C35: PRE-FIS-HLL-2024-03/26-3206 | D35: Victor Vilches | E35: CS-2024-07080 | F35: FRUSAN | G35: Hapag Lloyd | H35: BUENOS AIRES EXPRESS | I35: Hong Kong | J35: 14.03.2024 | K35: no surveyor involved | L35: 2352W | M35: Falta sales account, claim notice, DUS IVV | N35: Loss in Market / delay // 6 dias de demora // Frusan indica que son 76 contenedores los involucrados,con una pérdida de 350.000USD | O35: Plums | P35: 21.02.2024 | Q35: 14.03.2026 | S35: 26.09.2024 Se tiene que conseguir la notificación, sin notificacion se debe volver a revisarse.
A36: 24150.86 | B36: PRESENTAR | C36: PRE-FIS-HLL-2024-03/26-3282 | D36: Victor Vilches | E36: CS-2024-08129 | F36: FRUSAN | G36: Hapag Lloyd | H36: BUENOS AIRES EXPRESS | I36: Hong Kong | J36: 14.03.2024 | K36: no surveyor involved | L36: 2352W | M36: Falta AoR, Booking, Claim notice, DUS, IVV | N36: DELAY 6 DIAS POL/ pérdida de mercado | O36: Plums | P36: 21.02.2024 | Q36: 14.03.2026
A37: 35994.11 | B37: PRESENTAR | C37: PRE-FIS-HLL-2024-03/26-3283 | D37: Victor Vilches | E37: CS-2024-08130 | F37: FRUSAN | G37: Hapag Lloyd | H37: BUENOS AIRES EXPRESS | I37: Hong Kong | J37: 24.03.2024 | K37: no surveyor involved | L37: 2352W | M37: Falta AoR, Booking, Claim notice, Packing, DUS, IVV, | N37: DELAY 6 DIAS POL/ pérdida de mercado | O37: Plums | P37: 21.02.2024 | Q37: 14.03.2026
A38: 39970.97 | B38: PRESENTAR | C38: PRE-FIS-HLL-2024-03/26-3285 | D38: Victor Vilches | E38: CS-2024-08132 | F38: FRUSAN | G38: Hapag Lloyd | H38: BUENOS AIRES EXPRESS | I38: Hong Kong | J38: 14.03.2024 | K38: no surveyor involved | L38: 2352W | M38: Falta AoR, Booking, Claim notice, DUS, IVV, SR (no surveyor involved) | N38: DELAY 6 DIAS POL/ pérdida de mercado | O38: Plums | P38: 21.02.2024 | Q38: 14.03.2026
A39: 30639.19 | B39: PRESENTAR | C39: PRE-FIS-HLL-2024-03/26-3287 | D39: Victor Vilches | E39: CS-2024-08133 | F39: FRUSAN | G39: Hapag Lloyd | H39: BUENOS AIRES EXPRESS | I39: Hong Kong | J39: 28.03.2024 | K39: no surveyor involved | L39: 2352W | M39: Falta Booking, Claim notice, Packing, DUS, IVV | N39: DELAY 6 DIAS POL/ pérdida de mercado | O39: Plums | P39: 21.02.2024 | Q39: 14.03.2026
A40: 36715.66 | B40: PRESENTAR | C40: PRE-FIS-HLL-2024-03/26-3289 | D40: Victor Vilches | E40: CS-2024-08134 | F40: FRUSAN | G40: Hapag Lloyd | H40: BUENOS AIRES EXPRESS | I40: Hong Kong | J40: 14.03.2024 | K40: no surveyor involved | L40: 2352W | M40: Falta AoR, Claim notice, DUS, IVV, | N40: DELAY 6 DIAS POL/ pérdida de mercado | O40: Plums | P40: 21.02.2024 | Q40: 14.03.2026
A41: 33715.66 | B41: PRESENTAR | C41: PRE-FIS-HLL-2024-03/26-3290 | D41: Victor Vilches | E41: CS-2024-08135 | F41: FRUSAN | G41: Hapag Lloyd | H41: BUENOS AIRES EXPRESS | I41: Shenzen | J41: 14.03.2024 | K41: no surveyor involved | L41: 2352W | M41: Falta AoR, Claim notice, Booking, Packing, Booking, DUS, IVV | N41: DELAY 6 DIAS POL/ pérdida de mercado | O41: Plums | P41: 21.02.2024 | Q41: 14.03.2026
A42: 49842.33 | B42: PRESENTAR | C42: PRE-FIS-MSC-2024-03/26-3210 | D42: Barbara Choque | E42: CS-2024-03091 | F42: FRUSAN | G42: MSC | H42: BUENOS AIRES EXPRESS | I42: Hong Kong | J42: 14.03.2024 | K42: Teamhead | L42: 2352W | M42: Falta AoR, Export invoice, Claim notice, phyto, origen, DUS, IVV, SR | N42: Ventilation / DELAY 6 DIAS POL | O42: Plums | P42: 20.02.2024 | Q42: 14.03.2026 | S42: Acuerdo comercial entre shipper y cnee, modalidad de venta, compromisos de llegada de la carga, programa de venta con el recibidor, información si se junto con otra nave. Correo del routing original de MSC a SPL sold transit time.
A43: 39876.93 | B43: PRESENTAR | C43: PRE-FIS-MSC-2024-03/26-3291 | D43: Matias Farcuh | E43: CS-2024-08326 | F43: FRUSAN | G43: MSC | H43: BUENOS AIRES EXPRESS | I43: Hong Kong | J43: 14.03.2024 | K43: no surveyor involved | L43: 2352W | M43: Falta AoR, Packing, Booking, Claim notice, DUS, IVV | N43: DELAY 6 DIAS POL/ pérdida de mercado | O43: Plums | P43: 21.02.2024 | Q43: 14.03.2026
A44: 44630.19 | B44: PRESENTAR | C44: PRE-FIS-MSC-2024-03/26-3207 | D44: Matias Farcuh | E44: CS-2024-03090 | F44: FRUSAN | G44: MSC | H44: BUENOS AIRES EXPRESS | I44: Hong Kong | J44: 14.03.2024 | K44: Teamhead | L44: 2352W | M44: Falta AoR (firmada por frusan), SR, DUS, IVV | N44: DELAY 6 DIAS POL/ pérdida de mercado | O44: Plums | P44: 21.02.2024 | Q44: 14.03.2026 | S44: 02.12.2024 (LB) Case willbe handler with all container from the same vessel/voyage.12.09.2024 (LB) Case not recoverable, it is clear that quest system was activated during voyage, the temperature was maintain in range during transit. Regarding transit time, this was okay without delays.
A45: 30743.09 | B45: PRESENTAR | C45: PRE-FIS-ONE-2024-03/26-3288 | D45: Thomas Chatterton | E45: CS-2024-08157 | F45: FRUSAN | G45: ONE | H45: BUENOS AIRES EXPRESS | I45: Hong Kong | J45: 14.03.2024 | K45: no surveyor involved | L45: 2352W | M45: Falta Claim notice, Packing, DUS, IVV | N45: DELAY 6 DIAS POL/ pérdida de mercado | O45: Plums | P45: 21.02.2024 | Q45: 14.03.2026
A46: 14466.49 | B46: TRASPASADO | C46: PRE-FIS-COS-2021-03/22-0703 | D46: Nicolas Aravena | E46: cs2020-04553 | F46: freshgbv | G46: COSCO | H46: CALLAO EXPRESS | I46: St. Petersburg | J46: 43908 | M46: Falta SA,SMV / reporte débil. No hay SA propiamente, solo desglose de reclamo | N46: Caso general. DELAY 9 días. ETA04.03.2020. TT 13.03.2020 | O46: 18.03.2022 | P46: NA
A47: 31076.07 | B47: TRASPASADO | C47: PRE-FIS-COS-2021-03/22-0704 | D47: Nicolas Aravena | E47: cs2020-04552 | F47: freshgbv | G47: COSCO | H47: CALLAO EXPRESS | I47: St. Petersburg | J47: 43908 | M47: Falta SMV. Reporte useless. | N47: Caso general. DELAY 9 días. ETA 04.03.20. Arribó el 13.03.2020 unidad perdió conexión en Rotterdam. | O47: 18.03.2022 | P47: NA
A48: 13535.87 | B48: TRASPASADO | C48: PRE-FIS-CMA-2021-03/23-1032(EX) | D48: Matias Farcuh | E48: CS-2021-53370 | F48: FRUSAN | G48: CMA CGM | H48: CALLAO EXPRESS | I48: Rotterdam | J48: 17.03.2021 | K48: Spolidoro | M48: ok | N48: TE . enorme alza de te durante viaje. CN tardía. | O48: 17.03.2023
A49: 15497 | B49: TRASPASADO | C49: PRE-FIS-CMA-2023-05/25-2731 | D49: Camila Sanhueza | E49: CS-2023-05348 | F49: Subsole | G49: CMA CGM | H49: CALLAO EXPRESS | I49: Algeciras | J49: 01.05.2023 | K49: Eurovet | L49: 0WCE8N1MA | M49: ok | N49: DELAY | O49: Grapes | P49: 15.03.2023 | Q49: 01.05.2025
A50: 163689.75 | B50: PRESENTAR | C50: PRE-FIS-CMA-2024-01/26-3208 | D50: Isidora Martinez | E50: CS-2024-01356 | F50: Greenvic | G50: CMA CGM | H50: CALLAO EXPRESS | I50: Manzanillo | J50: 29.01.2024 | K50: CSM | L50: 0WCGON1MA | M50: Falta SR | N50: Delay 14 dias | O50: Peaches Plums Nectarines | P50: 30.12.2023 | Q50: 29.01.2026
A51: 26793 | B51: PRESENTAR | C51: PRE-FIS-CMA-2024-05/24-2955 | D51: Isidora Martinez | E51: NA | F51: Ship4Link | G51: CMA CGM | H51: CAP SAN MALEAS | I51: ROTTERDAM | J51: 26.05.2023 | L51: 0EWEMN1MA | M51: Falta stuffing | N51: CLOSE VENTILATION + HIGH TEMP. | O51: Limes | P51: 07.05.2023 | Q51: 26.05.2024 | R51: DIRECTO
A52: 22792.75 | B52: TRASPASADO/SR | C52: PRE-FIS-MSC-2022-04/24-2008 | D52: Barbara Choque | E52: CS-2022-04955 | F52: El Parque Chile | G52: MSC | H52: CAPE AKRITAS | I52: Valparaiso- Rotterdam | J52: 01.04.2022 | K52: Fruit Inspection & Consultancy BV | L52: NX206R | M52: SR | N52: TEMPERATURA | O52: Avocados | P52: 16.02.2022 | Q52: 45383 | S52: 02-02-2023- EXTRAJUDICIAL
A53: 46526.4 | B53: TRASPASADO | C53: PRE-FIS-MSC-2022-07/24-2136 | D53: Barbara Choque | E53: CS-2022-08576 | F53: FRUSAN | G53: MSC | H53: CAPE AKRITAS | I53: Savannah | J53: 10.07.2022 | K53: PCCC | L53: NX219R | M53: Falta reserva naviera, reporte consolidado con temperaturas, termografos | N53: Delay 40 d+ias | O53: Clementines | P53: 14.05.2022 | Q53: 45483
A54: 29181.38 | B54: TRASPASADO | C54: PRE-FIS-MSC-2023-12/24-2503 | D54: Barbara Choque | E54: CS-2023-04648 | F54: Prize | G54: MSC | H54: CAPE AKRITAS | I54: Rotterdam | J54: 28.12.2022 | K54: Fruit Inspection & Consultancy BV | L54: NX248R | M54: Falta stuffing report | N54: not transit related acorde a inspector, evidente alza de temp. | O54: Blueberries | P54: 04.12.2022 | Q54: 28.12.2024
A55: 12491 | B55: TRASPASADO | C55: PRE-FIS-CMA-2024-05/25-2950 | D55: Isidora Martinez | E55: CS-2023-05795 | F55: Itacu Corporation ltda. | G55: CMA CGM | H55: CAPE CITIUS | I55: Aqaba | J55: 13.05.2023 | K55: Seaman | L55: 0DVGYN1MA | M55: OK | N55: Delay 1 semana | O55: PINEAPPLES | P55: 06.04.2023 | Q55: 13.05.2025
A56: 10931.17 | B56: TRASPASADO | C56: FIS-MSC-2022-03/24-1855 | D56: Victor Vilches | E56: Isidora Martinez | F56: Rucaray | G56: MSC | H56: CAPE KORTIA | I56: Rotterdam | J56: 22.03.2022 | K56: Spolidoro | L56: NX204B | M56: ok | N56: Origin nature / Inherent vices - Delay 25 days / reporte modificado enfoque delay | O56: Nectarines-Pears | P56: 31.01.2022 | Q56: 45373
A57: 15981.43 | B57: TRASPASADO | C57: PRE-FIS-MSC-2022-05/24-2117 | D57: Barbara Choque | E57: CS-2022-07295 | F57: David del Curto | G57: MSC | H57: CAPE KORTIA | I57: Valparaíso/Hamad | J57: 04.05.2022 | K57: ACE Qatar | L57: NX204B | M57: Falta notificación naviera, certificado de cosecha | N57: Delay - Transit Period of 103 Days | O57: Pears | P57: 01.02.2022 | Q57: 45416
A58: 34242 | B58: TRASPASADO | C58: PRE-FIS-MSC-2022-03/24-2118 | D58: Barbara Choque | E58: CS-2022-05237 | F58: David del Curto | G58: MSC | H58: CAPE KORTIA | I58: Valparaíso- London Gateway | J58: 24.03.2022 | K58: MMS | L58: NX204B | M58: Falta certificado de cosecha | N58: See SR. Delay in transit. Issued of waste, shrive, dehydration. Limited shelf-life. | O58: Grapes | P58: 01.02.2022 | Q58: 45375
A59: 8904.8 | B59: TRASPASADO | C59: FIS-MSC-2022-03/24-2288 SDA | D59: Victor Vilches | E59: CS-2022-04868 | F59: Verfrut | G59: MSC | H59: CAPE KORTIA | I59: Philadelphia | J59: 10.03.2022 | K59: PCCC | L59: NX204B | M59: notificación naviera | N59: Delay 22 días / COVID and Quarantine | O59: Nectarines-Peaches | P59: 28.01.2022 | Q59: 45361
A60: 156355.2 | B60: TRASPASADO | C60: FIS-MSC-2022-04/24-2259 SDA | D60: Victor Vilches | E60: CS-2022-04880 | F60: Verfrut | G60: MSC | H60: CAPE KORTIA | I60: Valparaíso / Rotterdam | J60: 20.04.2022 | K60: Fruit Inspection & Consultancy BV | L60: NX204B | M60: ok. Asegurado indica no tiene factura de destrucciòn. | N60: Delay / PERDIDA TOTAL / COVID and Quarantine | O60: Nectarines | P60: 31.01.2022 | Q60: 20.04.2024 | S60: Ver estado judicial de los otro del CAPE KORTIA para ver si presentar conjuntamente en el caso de que no esté ingresado judicialmente.
A61: 107067.6 | B61: TRASPASADO | C61: PRE-FIS-MSC-2022-03/24-2125(EX) | D61: Victor Vilches | E61: CS-2022-04979 | F61: FRUSAN | G61: MSC | H61: CAPE KORTIA | I61: Philadelphia | J61: 10.03.2022 | K61: PCCC | L61: NX204B | M61: Falta certificado de cosecha | N61: Delay 20 days, extended time in transit with irregular temperatures / COVID and Quarantine | O61: Blueberries | P61: 01.02.2022 | Q61: 45361
A62: 60367.09 | B62: TRASPASADO | C62: PRE-FIS-MSC-2022-03/24-2137 SDA | D62: Victor Vilches | E62: CS-2022-09019 | F62: David del Curto | G62: MSC | H62: CAPE KORTIA | I62: Sines | J62: 29.03.2022 | K62: Montalvao | L62: NX204B | M62: ok | N62: Delay 22 DIAS / COVID and Quarantine | O62: Nectarines | P62: 31.01.2022 | Q62: 45380
A63: 35700 | B63: TRASPASADO | C63: PRE-FIS-MSC-2023-07/24-2333(EX) | D63: Barbara Choque | E63: CS-2022-08965 | F63: Santa Cruz | G63: MSC | H63: CAPE KORTIA | I63: Valparaiso-Jebel Ali | J63: 02.07.2022 | K63: Inchcape | L63: NX217R | M63: Falta AoR, reporte consolidado con temperaturas, certificado de cosecha, reporte de calidad, DUS, IVV | N63: Temperature issues y demora de 18 días | O63: Kiwis | P63: 04.05.2022 | Q63: 45475
A64: 43447.97 | B64: TRASPASADO | C64: PRE-FIS-MSC-2023-03/24-2320 SDA(EX) | D64: Victor Vilches | E64: CS-2022-05018 | F64: Los Lirios | G64: MSC | H64: CAPE KORTIA | I64: Valparaiso/Rotterdam | J64: 21.03.2022 | K64: Fruit Inspection & Consultancy BV | L64: NX204B | M64: Falta certificado de destrucción y factura de destrucción, fotos | N64: Delay 25 days / COVID and Quarantine | O64: Nectarines | P64: 28.01.2022 | Q64: 45372
A65: 47022.41 | B65: TRASPASADO | C65: PRE-FIS-MSC-2022-03/24-2143 SDA | D65: Victor Vilches | E65: CS-2022-05027 | F65: Magna | G65: MSC | H65: CAPE KORTIA | I65: Rotterdam | J65: 21.03.2022 | K65: Fruit Inspection & Consultancy BV | L65: NX204B | M65: OK | N65: Delay /COVID and Quarantine | O65: Nectarines | P65: 31.01.2022 | Q65: 45372
A66: 31183.2 | B66: TRASPASADO | C66: PRE-FIS-MSC-2023-03/24-2772 | D66: Victor Vilches | E66: CS-2022-08916 | F66: Patagonian Fruits Trade | G66: MSC | H66: CAPE KORTIA | I66: Philadelphia | J66: 10.03.2022 | K66: PCCC | L66: NX204R | M66: Falta stuffing, harvest | N66: DELAY | O66: PEARS | P66: 28.01.2022 | Q66: 10.03.2024
A67: 39870.14 | B67: TRASPASADO | C67: PRE-FIS-MSC-2023-07/24-2615 | D67: Barbara Choque | E67: CS-2022-09010 | F67: Copefrut | G67: MSC | H67: CAPE KORTIA | I67: Hamad | J67: 11.07.2022 | K67: ACE Qatar | L67: NX217R | M67: ok | N67: TEMPERATURA + DELAY | O67: Kiwis | P67: 03.05.2022 | Q67: 11.07.2024
A68: 33548.43 | B68: TRASPASADO | C68: PRE-FIS-MSC-2022-03/24-2083 SDA | D68: Victor Vilches | E68: CS-2022-05229 | F68: David del Curto | G68: MSC | H68: CAPE KORTIA | I68: Valparaiso/Rotterdam | J68: 22.03.2022 | K68: Fruit Inspection & Consultancy BV | L68: NX204B | M68: ok no existe reporte, cargo no se inspeccionó | N68: Delay /COVID and Quarantine | O68: Grapes | P68: 31.01.2022 | Q68: 45373
A69: 45574.85 | B69: TRASPASADO | C69: PRE-FIS-MSC-2022-03/24-2145 SDA | D69: Victor Vilches | E69: CS-2022-05228 | F69: David del Curto | G69: MSC | H69: CAPE KORTIA | I69: Rotterdam | J69: 22.03.2022 | K69: Fruit Inspection & Consultancy BV | L69: NX204B | M69: ok | N69: Delay / COVID and Quarantine | O69: Nectarines | P69: 01.02.2022 | Q69: 44642
A70: 22377.73 | B70: TRASPASADO | C70: PRE-FIS-MSC-2022-03/24-2235 SDA | D70: Victor Vilches | E70: CS-2022-04855 | F70: Greenvic | G70: MSC | H70: CAPE KORTIA | I70: Valparaiso/Philadelphia | J70: 10.03.2022 | K70: PCCC | L70: NX204B | M70: Falta reporte consolidado con temperaturas | N70: extended time in transit / COVID and Quarantine | O70: Blueberries | P70: 31.01.2022 | Q70: 45361
A71: 40088.88 | B71: TRASPASADO | C71: PRE-FIS-MSC-2022-03/24-2085 SDA | D71: Victor Vilches | E71: CS-2022-05028 | F71: Magna | G71: MSC | H71: CAPE KORTIA | I71: Rotterdam | J71: 22.03.2022 | K71: Fruit Inspection & Consultancy BV | L71: NX204B | M71: ok | N71: Delay / COVID and Quarantine | O71: Nectarines | P71: 31.01.2022 | Q71: 45373 | R71: con participacion
A72: 36577.32 | B72: TRASPASADO | C72: PRE-FIS-MSC-2022-03/24-2106 SDA | D72: Victor Vilches | E72: CS-2022-05039 | F72: Magna | G72: MSC | H72: CAPE KORTIA | I72: Rotterdam | J72: 22.03.2022 | K72: Fruit Inspection & Consultancy BV | L72: NX204B | M72: ok(booking no disponible) | N72: Delay / COVID and Quarantine | O72: Nectarines | P72: 31.01.2022 | Q72: 45373 | R72: con participacion
A73: 90537.51 | B73: TRASPASADO | C73: PRE-FIS-MSC-2022-03/24-2127 SDA | D73: Victor Vilches | E73: CS-2022-05038 | F73: Magna | G73: MSC | H73: CAPE KORTIA | I73: Rotterdam | J73: 22.03.2022 | K73: Fruit Inspection & Consultancy BV | L73: NX204B | M73: ok | N73: Delay/ COVID and Quarantine | O73: Nectarines | P73: 01.02.2022 | Q73: 45373 | R73: con participacion
A74: 41911.98 | B74: TRASPASADO | C74: PRE-FIS-MSC-2023-03/24-2334 SDA | D74: Victor Vilches | E74: CS-2022-04940 | F74: Valle Maule | G74: MSC | H74: CAPE KORTIA | I74: valparaiso-Rotterdam | J74: 21.03.2022 | K74: Fruit Inspection & Consultancy BV | L74: NX204B | M74: OK | N74: Delay 15 días / COVID and Quarantine | O74: Blueberries | P74: 31.07.2022 | Q74: 45372
A75: 41911.98 | B75: TRASPASADO/SR | C75: PRE-FIS-MSC-2023-03/24-2335 SDA | D75: Victor Vilches | E75: CS-2022-04934 | F75: Valle Maule | G75: MSC | H75: CAPE KORTIA | I75: Valparaiso-Rotterdam | J75: 21.03.2022 | K75: Fruit Inspection & Consultancy BV | L75: NX204B | M75: Falta SR | N75: Delay 15 días / COVID and Quarantine | O75: Blueberries | P75: 01.02.2022 | Q75: 45372 | S75: 10.11.2022- una vez caso completo se pasa a extrajudicial.
A76: 36693.69 | B76: TRASPASADO | C76: PRE-FIS-MSC-2023-03/24-2336 SDA | D76: Victor Vilches | E76: CS-2022-04935 | F76: Valle Maule | G76: MSC | H76: CAPE KORTIA | I76: Valparaiso-Rotterdam | J76: 21.03.2022 | K76: Fruit Inspection & Consultancy BV | L76: NX204B | M76: ok | N76: Delay 15 días / COVID and Quarantine | O76: Blueberries | P76: 01.02.2022 | Q76: 45372 | S76: 10.11.2022- una vez caso completo se pasa a extrajudicial.
A77: 25775.19 | B77: TRASPASADO | C77: PRE-FIS-MSC-2023-03/24-2337 SDA | D77: Victor Vilches | E77: CS-2022-04936 | F77: Valle Maule | G77: MSC | H77: CAPE KORTIA | I77: Valparaiso-Rotterdam | J77: 21.03.2022 | K77: Fruit Inspection & Consultancy BV | L77: NX204B | M77: OK | N77: Delay 15 días / COVID and Quarantine | O77: Blueberries | P77: 01.02.2022 | Q77: 45372 | S77: caso está siendo manejado de forma directa por Francisco.
A78: 41908.1 | B78: TRASPASADO | C78: PRE-FIS-MSC-2022-03/24-2279 SDA | D78: Victor Vilches | E78: CS-2022-04882 | F78: Verfrut | G78: MSC | H78: CAPE KORTIA | I78: Rotterdam | J78: 22.03.2022 | K78: Fruit Inspection & Consultancy BV | L78: NX204B | M78: ok | N78: Delay 24 aprox / COVID and Quarantine | O78: Nectarines | P78: 31.01.2022 | Q78: 45373
A79: 42456.59 | B79: TRASPASADO | C79: PRE-FIS-MSC-2022-03/24-2280 SDA | D79: Victor Vilches | E79: CS-2022-04883 | F79: Verfrut | G79: MSC | H79: CAPE KORTIA | I79: Rotterdam | J79: 22.03.2022 | K79: Fruit Inspection & Consultancy BV | L79: NX204B | M79: ok | N79: Delay 24 aprox / COVID and Quarantine | O79: Nectarines | P79: 31.01.2022 | Q79: 45373
A80: 48619.27 | B80: TRASPASADO | C80: PRE-FIS-COS-2023-01/25-2451 | D80: Barbara Choque | E80: CS-2023-04149 | F80: Geofrut | G80: COSCO | H80: CAPE PIONEER | I80: Rotterdam | J80: A | K80: Fruit Inspection & Consultancy BV | L80: 0001N | M80: ok | N80: delay // INSPECTOR INDICA NO RELACIONADO A TRÀNSITO | O80: Cherries | P80: 24.12.2022 | Q80: 45688 | S80: Presentar Tratar de llevar en rebeldía lo más rápido posible. Si se requiere, contactar a un experto.
A81: 39316.15 | B81: PRESENTAR | C81: PRE-FIS-CMA-2024-02/26-3031 | D81: Isidora Martinez | E81: CS-2024-02435 | F81: Verfrut | G81: CMA CGM | H81: CAPE QUEST | I81: Philadelphia | J81: 13.02.2024 | K81: PCCC | L81: 0LID7N1MA | M81: ok | N81: problemas de temperatura, leves acorde a termo- aun falta reporte para ver comentarios de inspector | O81: Cherries | P81: 22.01.2024 | Q81: 13.02.2026
A82: 15484.84 | B82: PRESENTAR | C82: PRE-FIS-CMA-2024-03/26-3047 | D82: Barbara Choque | E82: CS-2024-04613 | F82: Lo Garces | G82: CMA CGM | H82: CAPE QUEST | I82: Algeciras | J82: 26.03.2024 | K82: Eurovet | L82: 0LIDJN1MA | M82: Falta IVV, Stuffing Report, Booking | N82: Inspector indica daño de origen, hubo un evento puntual de temperatura que generó un aumento de 4° en la carga. | O82: Nectarines | P82: 02.03.2024 | Q82: 26.03.2026 | S82: 06.06.2024: Una vez completo, EX para negociar sin que el caso avance y no mostrar reporte
A83: 22952.09 | B83: PRESENTAR | C83: PRE-FIS-ONE-2024-07/26-3311 | D83: Thomas Chatterton | E83: CS-2024-07027 | F83: FRUSAN | G83: ONE | H83: CAPE QUEST | I83: Philadelphia | J83: 24.07.2024 | K83: PCCC | L83: 0LIEVN1MA | M83: Falta AoR | N83: falla en CT, tuvieron que reiniciar el proceso en Destino// solicitar correo en que naviera informó que el protocolo falló | O83: Apples | P83: 06.07.2024 | Q83: 24.07.2026
A84: 20139.93 | B84: 29633 | C84: PRE-FIS-CMA-2024-03/26-3176 | D84: Thomas Chatterton | E84: CS-2024-02439 | F84: FRUSAN | G84: CMA CGM | H84: CAPE SCOTT | I84: Leghorn | J84: 05.03.2024 | K84: Spolidoro | L84: 0LIDBN1MA | M84: Subro | N84: Temperature | O84: Pears | P84: 02.02.2024 | Q84: 05.03.2026
A85: 40156.59 | B85: TRASPASADO | C85: PRE-FIS-MSC-2022-03/24-2285 | D85: Matias Farcuh | E85: CS-2022-04872 | F85: Verfrut | G85: MSC | H85: CAPE TAINARO | I85: Rotterdam | J85: 26.03.2022 | K85: Fruit Inspection & Consultancy BV | L85: NX205R | M85: AoR | N85: Delay Intended ETA according to the booking: Booking not received Real ETA: 26.03.2022 "T | O85: Nectarines | P85: 09.02.2022 | Q85: 45377
A86: 29774.08 | B86: TRASPASADO | C86: PRE-FIS-MSC-2022-04/24-2263 | D86: Barbara Choque | E86: CS-2022-04874 | F86: Verfrut | G86: MSC | H86: CAPE TAINARO | I86: Hamburg | J86: 05.04.2022 | K86: Berner | L86: MSC Anchorage, MSC Caterina | M86: ok | N86: Delay 29 days (1) 07.02.2023 (CA) Assured indicates no SMV is available. ) | O86: Nectarines | P86: 09.02.2022 | Q86: 45387
A87: 49565.47 | B87: TRASPASADO | C87: FIS-MSC-2022-03/24-2027 | D87: Victor Vilches | E87: CS-2022-04828 | F87: Jorge Schmidt | G87: MSC | H87: CAPE TAINARO | I87: Valparaíso / Rotterdam | J87: 21.03.2022 | K87: Fruit Inspection & Consultancy BV | L87: NX205R | M87: ok | N87: Malfuncionamiento del contenedor: se tuvo que abrir ventilación, ya que sistema Controlled Atmosphere no estaba funcionando (accident) / Controlled Atmosphere and Delay | O87: Avocados | P87: 09.02.2022 | Q87: 21.03.2024
A88: 36534.05 | B88: TRASPASADO | C88: PRE-FIS-MSC-2022-01/24-2327 | D88: Barbara Choque | E88: CS-2023-00243 | F88: El Parque | G88: MSC | H88: CAPE TAINARO | I88: Valparaiso-Rotterdam | J88: 25.01.2022 | K88: no surveyor involved | L88: NX148R | M88: Falta Tracking, Certificado de destrucción (622 cajas), liquidación comparativa de mismos tamaños (14 y 16) la proporcionada es de otros tamaños. | N88: Delay 21 días - Posible pérdida de mercado porque no hubo inspección | O88: Avocados | P88: 19.12.2021 | Q88: 45316
A89: 261282.52 | B89: TRASPASADO | C89: PRE-FIS-MSC-2023-01/24-2322 | D89: Victor Vilches | E89: CS-2022-02289 | F89: Newdayfruits | G89: MSC | H89: CAPE TAINARO | I89: Coronel/Philadelphia | J89: 16.01.2022 | K89: PCCC | L89: NX148R | M89: Falta fotos falta MEDU9744829 | N89: extended time in transit - Delay 21 días | O89: Blueberries | P89: 03.12.2021 | Q89: 45307
A90: 33439.43 | B90: TRASPASADO | C90: PRE-FIS-MSC-2023-07/25-2748 | D90: Eduardo Rojas | E90: CS-2023-07051 | F90: Subsole | G90: MSC | H90: CAPE TAINARO | I90: Jebel Ali | J90: 02.07.2023 | K90: Inchcape | L90: NX317R | M90: ok | N90: DELAY | O90: Kiwis | P90: 29.04.2023 | Q90: 02.07.2025
A91: 50100.13 | B91: TRASPASADO | C91: PRE-FIS-OCL-2022-01/24-1703 | D91: Yasna Rodríguez | E91: CS-2022-07458 | F91: Santa Cruz | G91: MSC | H91: CAPE TAINARO | I91: Rotterdam | J91: 20.01.2022 | K91: Fruit Inspection & Consultancy BV | L91: NX148R | M91: Falta AoR | N91: Delay | O91: Avocados | P91: 07.12.2021 | Q91: 45311
A92: 54443.4 | B92: TRASPASADO | C92: PRE-FIS-MSC-2022-01/24-1706 | D92: Yasna Rodríguez | E92: CS-2022-07459 | F92: Santa Cruz | G92: MSC | H92: CAPE TAINARO | I92: Rotterdam | J92: 20.01.2022 | K92: no surveyor involved | L92: NX148R | M92: Falta nottificación naviera, certificado de cosecha, DUS, IVV | N92: Delay | O92: Avocados | P92: 07.12.2021 | Q92: 45311 | S92: Se revisan en reunion del 14.02.2024 y se determinara que Jan evaluará pasos a seguir considerando el monto de los reclamos
A93: 8906.79 | B93: PRESENTAR | C93: PRE-FIS-MSC-2023-05/25-2828 | D93: Nicolas Aravena | E93: CS-2023-07068 | F93: Quintay | G93: MSC | H93: CAPE TAINARO | I93: Rotterdam | J93: 24.05.2023 | K93: Fruit Inspection & Consultancy BV | L93: NX317R | M93: OK | N93: No se hizo inspección // termos muestran temp irregulares (rear temp. recorder too high, but front ok) | O93: Grapes | P93: 28.04.2023 | Q93: 24.05.2025 | R93: DIRECTO (No habrá reporte, confirmado por Sonja, "No survey was done, as the fruit was already loaded/distributed one days after claimed." | S93: Caso revisado 07.12.2023: Dependienteo del monto (sobre $10.000), dejarlo para EX.
A94: 24210.17 | B94: TRASPASADO | C94: FIS-MSC/PGR-2022-02/24-1939 | D94: Victor Vilches | E94: N/A | F94: Priagro | G94: MSC | H94: CAROLE | I94: VALPARAISO / RÓTERDAM | J94: 19.02.2022 | L94: NX202R | M94: Falta Termografos | N94: Demora de 6 días/Acorde a reporte reporte en origen de 13 días (POL) | O94: Blueberries | Q94: 19.02.2024
A95: 22895.5 | B95: TRASPASADO | C95: FIS-MSC/PGR-2022-02/24-1941 | D95: Victor Vilches | E95: N/A | F95: Priagro | G95: MSC | H95: CAROLE | I95: VALPARAISO / RÓTERDAM | J95: 18.02.2022 | L95: NX202R | M95: Falta AoR, survey report, Tracking, Falta Sales account ya que documento proporcionado no indica precio por caja que es lo que necesitamos proporcionar a la naviera, debe ser simil a los entregados por Triple Fruit | N95: Demora de 6 días | O95: Blueberries | Q95: 18.02.2024
A96: 6186.3 | B96: TRASPASADO | C96: FIS-MSC/PGR-2022-02/24-1942 | D96: Barbara Choque | E96: N/A | F96: Priagro | G96: MSC | H96: CAROLE | I96: VALPARAISO / RÓTERDAM | J96: 23.02.2022 | L96: NX202R | M96: FaltaSurvey Report, | N96: Demora de 6 días | O96: Blueberries | Q96: 23.02.2024
A97: 14083.62 | B97: TRASPASADO | C97: FIS-MSC/PGR-2022-03/24-1944 | D97: Victor Vilches | E97: N/A | F97: Priagro | G97: MSC | H97: CAROLE | I97: VALPARAISO / RÓTERDAM | J97: 27.03.2022 | L97: 2201W | M97: OK | N97: Delay 13 días (POL) | O97: Blueberries | Q97: 27.03.2024
A98: 26830.46 | B98: TRASPASADO | C98: PRE-FIS-MAE-2021-07/23-1278 | D98: Matias Farcuh | E98: CS-2021-56222 | F98: Los Lirios | G98: Maersk Line | H98: CAROLINE MAERSK | I98: Wladiwostok | J98: 17.07.2021 | K98: Other | M98: Falta SA,SMV. | N98: Asegurado confirmo no hay tracking disponible / delay 40 días. TT 80 DÍAS | O98: Pears | P98: 28.04.2021 | Q98: 45124
A99: 29990.22 | B99: TRASPASADO | C99: FIS-CMA-2021-06/22-0823 | D99: Matias Farcuh | E99: cs2020-05403 | F99: David del Curto | G99: CMA CGM | H99: CARTAGENA EXPRESS | I99: Rotterdam | J99: 09.06.2020 | K99: Fruit Inspection & Consultancy BV | M99: ok | N99: Fuego en el contenedor. Al parecer llegó 1 pallet quemado (carga destruida). Falta SR. | O99: 09.06.2022
A100: 781.75 | B100: TRASPASADO | C100: PRE-FIS-HLL-2024-10/24-2887 | D100: Camila Sanhueza | E100: CS-2023-11798 | F100: Itacu Corporation ltda. | G100: Hapag Lloyd | H100: CAUCEDO EXPRESS | I100: Helsingborg | J100: 22.10.2023 | K100: no surveyor involved | L100: 339N | M100: Falta stuffing | N100: falla del contenedor en origen por lo que se procedió con trasvasije | O100: Bananas | P100: 25.09.2023 | Q100: 22.10.2024
...

Sheet Revision Ale
A1: Claim amount | B1: Id | C1: Reference No | D1: Claim Handler | E1: CS Claim No | F1: Assured | G1: Opponent | H1: Vessel | I1: Place of Discharge | J1: Date of Discharge | K1: Surveyorco | L1: Voyage | M1: Status | N1: Summary | O1: Commodity | P1: Date of Loading | Q1: TB | R1: Comentario revisión
A2: $ 8.021,47 | B2: SOLICITADO | C2: PRE-FIS-MSC-2024-03/26-3103 | D2: Eduardo Rojas | E2: CS-2024-03074 | F2: Prize | G2: MSC | H2: BUENOS AIRES EXPRESS | I2: Hong Kong | J2: 15.03.2024 | K2: Teamhead | L2: 2352W | M2: Falta harvest, stuffing, origen, fito, DUS, IVV | N2: Temperatura / DELAY 6 DIAS POL/ | O2: Nectarines | P2: 20.02.2024 | Q2: 15.03.2026 | R2: Seguir insistiendo con clientes para obtener la documentación que se encunetre pendiente
A3: $ 39.654,56 | B3: SOLICITADO | C3: PRE-FIS-MSC-2024-03/26-3100 | D3: Matias Farcuh | E3: CS-2024-02429 | F3: Prize | G3: MSC | H3: CAUTIN | I3: Hong Kong | J3: 02.03.2024 | K3: Teamhead | L3: 2351W | M3: falta AoR (adjunta), FITO, ORIGE, harvest certificate (adjunto), reporte de consolidado en origen, booking naviera, DUS, IVV | N3: Temperatura | O3: Plums | P3: 06.02.2024 | Q3: 02.03.2026 | R3: Seguir insistiendo con clientes para obtener la documentación que se encunetre pendiente
A4: $ 33.164,07 | B4: SOLICITADO | C4: PRE-FIS-CMA-2024-03/26-3109 | D4: Nicolás Nuñez | E4: CS-2024-03072 | F4: Prize | G4: CMA CGM | H4: CMA CGM BEIRA | I4: Algeciras | J4: 13.03.2024 | K4: Montalvao | L4: 0LIGFN1MA | M4: Falta sales account, booking, stuffing, harvest, SR, DUS, IVV | N4: Temperatura | O4: Nectarines | P4: 16.02.2024 | Q4: 13.03.2026 | R4: Seguir insistiendo a través de Montalvao para recibir las liquidaciones pendientes
A5: $ 31.600,18 | B5: SOLICITADO | C5: PRE-FIS-MAE-2024-03/26-3293 | D5: Thomas Chatterton | E5: CS-2024-03103 | F5: FRUSAN | G5: Maersk | H5: MAERSK LABERINTO | I5: Hong Kong | J5: 31.03.2024 | K5: Teamhead | L5: 4058W | M5: Falta AoR, export invoice, sales | N5: TEMPERATURE | O5: Plums | P5: 05.03.2024 | Q5: 31.03.2026 | R5: Seguir insistiendo con clientes para obtener la documentación que se encunetre pendiente
A6: $ 21.718,49 | B6: SOLICITADO | C6: PRE-FIS-MSC-2024-03/26-3115 | D6: Matias Farcuh | E6: CS-2024-03089 | F6: FRUSAN | G6: MSC | H6: MSC AVNI | I6: Rotterdam | J6: 17.03.2024 | K6: Fruit Inspection & Consultancy BV | L6: NX407R | M6: Falta AoR | N6: Temperature | O6: Plums | P6: 17.02.2024 | Q6: 17.03.2026 | R6: Seguir insistiendo con clientes para obtener la documentación que se encunetre pendiente
A7: $ 40.000,00 | B7: SOLICITADO | C7: PRE-FIS-MSC-2024-03/26-3068 | D7: Matias Farcuh | E7: CS-2024-03076 | F7: Prize | G7: MSC | H7: MSC YASHI B | I7: Philadelphia | J7: 13.03.2024 | K7: PCCC | L7: NX408R | M7: Falta Subro, AoR, Harvest, Phyto, Origen, Sales account, Booking, Stuffing, SR. | N7: Registro de gases disponible no concuerda con solicitado. Se indica posible problema de temp, pero no figuran los termos disponibles. | O7: Blueberries | P7: 25.02.2024 | Q7: 13.03.2026 | R7: Seguir insistiendo con clientes para obtener la documentación que se encunetre pendiente
A8: $ 5.137,33 | B8: SOLICITAR | C8: PRE-FIS-MSC-2024-03/26-3056 | D8: Matias Farcuh | E8: CS-2024-03095 | F8: FRUSAN | G8: MSC | H8: MSC YASHI B | I8: London Gateway | J8: 22.03.2024 | K8: MMS | L8: NX408R | M8: Falta AoR | N8: TEMPERATURA, daños por frío, igual daños de origen encontrados.- | O8: Plums | P8: 25.02.2024 | Q8: 22.03.2026 | R8: Seguir insistiendo con clientes para obtener la documentación que se encunetre pendiente
A9: $ 20.290,82 | B9: SOLICITAR | C9: PRE-FIS-MSC-2024-03/26-3292 | D9: Eduardo Rojas | E9: CS-2024-03102 | F9: FRUSAN | G9: MSC | H9: SEASPAN BRIGHTNESS | I9: Hong Kong | J9: 26.03.2024 | K9: Teamhead | L9: 2402W | M9: Falta AoR | N9: TEMPERATURE | O9: Plums | P9: 22.02.2024 | Q9: 26.03.2026 | R9: Seguir insistiendo con clientes para obtener la documentación que se encunetre pendiente
A10: $ 9.027,83 | B10: SOLICITAR | C10: PRE-FIS-MSC-2024-03/26-3280 | D10: Alejandra Peltier | E10: CS-2024-03100 | F10: FRUSAN | G10: MSC | H10: SEASPAN BRIGHTNESS | I10: Hong Kong | J10: 26.03.2024 | K10: Teamhead | M10: Falta AoR | N10: Temperatura | O10: Plums | P10: 22.02.2024 | Q10: 26.03.2026 | R10: Seguir insistiendo con clientes para obtener la documentación que se encunetre pendiente
A13: Claim amount | B13: Id | C13: Reference No | D13: Claim Handler | E13: CS Claim No | F13: Assured | G13: Opponent | H13: Vessel | I13: Place of Discharge | J13: Date of Discharge | K13: Surveyorco | L13: Voyage | M13: Status | N13: Summary | O13: Commodity | P13: Date of Loading | Q13: TB | R13: Comentario revisión
A14: $ 17.219,43 | B14: SOLICITADO | C14: PRE-FIS-MSC-2024-02/26-3110 | D14: Nicolás Nuñez | E14: CS-2024-02186 | F14: Prize | G14: MSC | H14: LIMA EXPRESS | I14: Hong Kong | J14: 23.02.2024 | K14: Teamhead | L14: 2350W | M14: Falta AoR, booking, stuffing, harvest, fito, origen, DUS, IVV | N14: Inspector indica condicion de origen, pero termo muestra temp más baja de lo solicitada y retorno en alza. | O14: Plums | P14: 31.01.2024 | Q14: 23.02.2026 | R14: Seguir insistiendo con clientes para obtener la documentación que se encunetre pendiente
A15: $ 25.482,31 | B15: SOLICITADO | C15: PRE-FIS-MSC-2024-02/26-3108 | D15: Nicolás Nuñez | E15: CS-2024-01868 | F15: Prize | G15: MSC | H15: BUENAVENTURA EXPRESS | I15: Hong Kong | J15: 20.02.2024 | K15: Teamhead | L15: 2349W | M15: Falta AoR, booking, stuffing, harvest, DUS, IVV | N15: Temperatura | O15: Plums | P15: 20.01.2024 | Q15: 20.02.2026 | R15: Seguir insistiendo con clientes para obtener la documentación que se encunetre pendiente
A16: $ 27.690,00 | B16: SOLICITADO | C16: PRE-FIS-CMA-2024-02/26-3063 | D16: Matias Farcuh | E16: CS-2024-03628 | F16: Prize | G16: CMA CGM | H16: COSCO SHIPPING BRAZIL | I16: Busan | J16: 16.02.2024 | K16: Other | L16: 0HCGKW1MA | M16: Falta AoR, Harvest, DUS, IVV, Stuffing Report, Phyto, Origen, Booking | N16: Inspector indica no relacionado a transporte.pero está informe de gases que se ven con alzas durante viaje. registro de gases disponible no concuerdqa con solicitado. | O16: Blueberries | P16: 09.01.2024 | Q16: 16.02.2026 | R16: Seguir insistiendo con clientes para obtener la documentación que se encunetre pendiente
A20: Claim amount | B20: Id | C20: Reference No | D20: Claim Handler | E20: CS Claim No | F20: Assured | G20: Opponent | H20: Vessel | I20: Place of Discharge | J20: Date of Discharge | K20: Surveyorco | L20: Voyage | M20: Status | N20: Summary | O20: Commodity | P20: Date of Loading | Q20: TB | R20: Comentario revisión
A21: $ 18.657,13 | B21: 29973 | C21: PRE-FIS-CMA-2024-05/26-3179 | D21: Thomas Chatterton | E21: CS-2024-04777 | F21: FRUSAN | G21: CMA CGM | H21: VALPARAISO EXPRESS | I21: Leghorn | J21: 07.05.2024 | K21: Spolidoro | L21: 0WCH0N1MA | M21: Falta AoR | N21: Temperature | O21: Pears | P21: 29.03.2024 | Q21: 07.05.2026 | R21: Seguir insistiendo con clientes para obtener la documentación que se encunetre pendiente
A22: $ 147.457,02 | B22: 30507 | C22: PRE-FIS-MSC-2024-06/26-3308 | D22: Yasna Rodriguez | E22: CS-2024-09630 | F22: FRUSAN | G22: MSC | H22: MANZANILLO EXPRESS | I22: Nhava Sheva | J22: 13.06.2024 | K22: not necessary | L22: 2406W | M22: Falta AoR | N22: Delay 23 días /ETA 21.05.2024 // loss in market | O22: Apples | P22: 26.03.2024 | Q22: 11.06.2026 | R22: Seguir insistiendo con clientes para obtener la documentación que se encunetre pendiente
A25: Claim amount | B25: Id | C25: Reference No | D25: Claim Handler | E25: CS Claim No | F25: Assured | G25: Opponent | H25: Vessel | I25: Place of Discharge | J25: Date of Discharge | K25: Surveyorco | L25: Voyage | M25: Status | N25: Summary | O25: Commodity | P25: Date of Loading | Q25: TB | R25: Comentario revisión
A26: $ 22.390,51 | B26: SOLICITADO | C26: PRE-FIS-MSC-2024-07/26-3788 | D26: Alejandra Peltier | E26: CS-2024-06993 | F26: Prize | G26: MSC | H26: MSC MAPUTO | I26: Fos-Sur-Mer | J26: 19.07.2024 | K26: McLeans | L26: NX422R | M26: Falta AoR, harvest, credit notes, booking | N26: TEMPERATURE | O26: Apples | P26: 02.06.2024 | Q26: 19.07.2026 | R26: Traspasar este jueves 9 de abril.- Seguir insistiendo docs pendientes
A27: $ 19.358,47 | B27: SOLICITADO | C27: PRE-FIS-MSC-2024-07/26-3215 | D27: Alejandra Peltier | E27: CS-2024-07740 | F27: Lo Garces | G27: MSC | H27: MSC ELMA | I27: Sines | J27: 28.07.2024 | K27: Montalvao | L27: NX423R | M27: Falta subro, AoR, nota de crédito, Booking, SR | N27: Delay 18 dias | O27: Kiwis | P27: 10.06.2024 | Q27: 28.07.2026 | R27: Solicitar a Jan intervenga considerando conversación que sostuvo con Lo Garces respecto a la documentación de casos. Seguir isnistiendo con GH y directamente con Lo Garces. Traspasar a finales de abril
A28: $ 24.810,33 | B28: SOLICITADOS | C28: PRE-FIS-PIL-2024-07/26-3238 | D28: Alejandra Peltier | E28: CS-2024-07061 | F28: Rio Maipo | G28: PIL | H28: KOTA SEJARAH | I28: Nhava Sheva | J28: 06.07.2024 | K28: Intertek, IND | L28: 068W | M28: Falta AoR, Sales Invoice, Claim Notice, Stuffing, Tracking | N28: Temperature + DELAY 15 | O28: Apples | P28: 04.05.2024 | Q28: 06.07.2026 | R28: Enviaron documentación, se debe seguir insistiendo. Traspasar jueves 16 de abril.
A31: Claim amount | B31: Id | C31: Reference No | D31: Claim Handler | E31: CS Claim No | F31: Assured | G31: Opponent | H31: Vessel | I31: Place of Discharge | J31: Date of Discharge | K31: Surveyorco | L31: Voyage | M31: Status | N31: Summary | O31: Commodity | P31: Date of Loading | Q31: TB | R31: Comentario revisión
A32: 12291.53 | B32: SOLICITADO | C32: PRE-FIS-MSC-2024-08/26-3276 | D32: Alejandra Peltier | E32: CS-2024-07755 | F32: Los Lirios | G32: MSC | H32: MSC PALAK | I32: Philadelphia | J32: 20.08.2024 | K32: PCCC | L32: NX430R | M32: Falta Subro, AoR, Harvest, Extra costs invoices | N32: TEMPERATURE | O32: Kiwis | P32: 27.07.2024 | Q32: 20.08.2026 | R32: Deben estar solicitadas las cartas y la documentación pendinete para que puedan ser traspasados a mediados de mayo
A33: 17663.2 | B33: SOLICITADO | C33: PRE-FIS-MSC-2024-08/26-3279 | D33: Alejandra Peltier | E33: CS-2024-07757 | F33: Los Lirios | G33: MSC | H33: MSC LAGOS | I33: San Juan | J33: 06.08.2024 | K33: Other | L33: NX425R | M33: Falta subro, AoR, harvest, DUS, IVV, | N33: Delay + Temp | O33: Apple | P33: 25.06.2024 | Q33: 05.08.2026 | R33: Deben estar solicitadas las cartas y la documentación pendinete para que puedan ser traspasados a mediados de mayo
A34: 20928 | B34: SOLICITADO | C34: PRE-FIS-MSC-2024-08/26-3278 | D34: Alejandra Peltier | E34: CS-2024-07756 | F34: Los Lirios | G34: MSC | H34: MSC LAGOS | I34: San Juan | J34: 06.08.2024 | K34: BSR | L34: NX425R | M34: Falta subro, AoR, harvest, DUS, IVV. | N34: Delay + Temp | O34: Apple | P34: 25.06.2024 | Q34: 06.08.2026 | R34: Deben estar solicitadas las cartas y la documentación pendinete para que puedan ser traspasados a mediados de mayo
A35: 29032.28 | B35: SOLICITADO | C35: PRE-FIS-MSC-2025-08/26-3380 | D35: Alejandra Peltier | E35: CS-2024-07949 | F35: Subsole | G35: MSC | H35: MSC ALICANTE | I35: Sines | J35: 12.08.2024 | K35: Montalvao | L35: NX426R | M35: Falta Credit Note, SR, AoR, IVV, Inv. Extra costs | N35: Delay 12 días + Temp + preshipment (2 meses de almacenaje post harvest) | O35: Kiwis | P35: 29.06.2024 | Q35: 12.08.2026 | R35: Deben estar solicitadas las cartas y la documentación pendinete para que puedan ser traspasados a mediados de mayo
A36: 30812.52 | B36: SOLICITADO | C36: PRE-FIS-CMA-2024-08/26-3274 | D36: Alejandra Peltier | E36: CS-2024-07025 | F36: FRUSAN | G36: CMA CGM | H36: GUAYAQUIL EXPRESS | I36: Rotterdam | J36: 09.08.2024 | K36: Fruit Inspection & Consultancy BV | L36: 0WCIEN1MA | M36: Falta AoR, DUS, IVV, stuffing, Origin certificate, SR | N36: TEMPERATURE | O36: Kiwis | P36: 11.07.2024 | Q36: 09.08.2026 | R36: Deben estar solicitadas las cartas y la documentación pendinete para que puedan ser traspasados a mediados de mayo
A37: 7800.58 | B37: SOLICITADO | C37: PRE-FIS-FTR-2025-08/26-4074 | D37: Alejandra Peltier | E37: CS-2025-08602 | F37: ROVEG | G37: MSC | H37: BREMERHAVEN EXPRESS | I37: Rotterdam | J37: 10.08.2025 | K37: Fruit Inspection & Consultancy BV | R37: Deben estar solicitadas las cartas y la documentación pendinete para que puedan ser traspasados a mediados de mayo
A40: Claim amount | B40: Id | C40: Reference No | D40: Claim Handler | E40: CS Claim No | F40: Assured | G40: Opponent | H40: Vessel | I40: Place of Discharge | J40: Date of Discharge | K40: Surveyorco | L40: Voyage | M40: Status | N40: Summary | O40: Commodity | P40: Date of Loading | Q40: TB | R40: Comentario revisión
A41: 56878.29 | B41: SOLICITADO | C41: PRE-FIS-MSC-2024-09/26-3314 | D41: Alejandra Peltier | E41: CS-2024-08595 | F41: FRUSAN | G41: MSC | H41: MSC PALAK | I41: La Guaira | J41: 04.09.2024 | K41: Frank B. Hill | L41: NX430R | M41: Falta AoR 2 Cnee, Harvest Certificate, Packing List, SMV, | N41: TEMPERATURE | O41: Apples | P41: 25.07.2024 | Q41: 04.09.2026 | R41: Deben estar solicitadas las cartas y la documentación pendinete para que puedan ser traspasados a mediados de mayo
A42: 24177.84 | B42: SOLICITADO | C42: PRE-FIS-MSC-2024-09/26-3310 | D42: Alejandra Peltier | E42: CS-2024-08139 | F42: FRUSAN | G42: MSC | H42: MSC PALAK | I42: London Gateway | J42: 10.09.2024 | K42: MMS | L42: NX430R | M42: Falta AoR, SMV por lo 22,50libras por caja. | N42: Delay. TT 46 días siendo actualmente de 24 dias // INPECTOR MENCIONA TB CONDICION PRESHIPMENT Y EL HARVEST | O42: Kiwis | P42: 27.07.2024 | Q42: 10.09.2026 | R42: Deben estar solicitadas las cartas y la documentación pendinete para que puedan ser traspasados a mediados de mayo
A43: 48045 | B43: SOLICITADOS | C43: PRE-FIS-ONE-2024-09/26-3350 | D43: Alejandra Peltier | E43: CS-2024-08338 | F43: San Osvaldo | G43: ONE | H43: CAPE SCOTT | I43: Philadelphia | J43: 18.09.2024 | K43: PCCC | L43: 0LIFBN1MA | M43: Falta Subro, Aor (falta timbre asegurado) | N43: TEMPERATURA, PÉRDIDA TOTAL | O43: Oranges | P43: 31.08.2024 | Q43: 18.09.2026 | R43: Deben estar solicitadas las cartas y la documentación pendinete para que puedan ser traspasados a mediados de mayo
B44: SOLICITADO | C44: PRE-FIS-HLL-2026-09/26-4354 | D44: Alejandra Peltier | E44: CS-2025-11027 | F44: Eosta | G44: Customs | H44: GSL MARIA | I44: Antwerpen | J44: 22.09.2025 | K44: Fruit Inspection & Consultancy BV | L44: 538W | M44: Falta subro, harvest, SR, sales acc and comparative sales | N44: Delay por error de aduanas | O44: Avocados | P44: 29.08.2025 | Q44: 22.09.2026 | R44: Deben estar solicitadas las cartas y la documentación pendinete para que puedan ser traspasados a mediados de mayo
A47: *próxima revisión lunes 22 de junio.

Sheet Descartados
B1: Id | C1: Reference No | D1: Claim Handler | E1: CS Claim No | F1: Assured | G1: Opponent | H1: Vessel | I1: Place of Discharge | J1: Date of Discharge | K1: Surveyorcomp | L1: Status | M1: Summary | N1: TB | R1: Participation
B2: Descartado | C2: PRE-FIS-PLA-2021-12/22-0940 | D2: Ljubinka Basic | E2: CS-2020-50348 | F2: Verfrut | G2: Polar Air | H2: AIRFREIGHT | I2: Hong Kong | J2: 01.12.2020 | K2: Teamhead | L2: Falta CN,subro,AoR(incompleta),SR. | M2: Pérdida de mercado. Se indica daño físico en damage ratio.(caso debil ETA 29.11 y llegó el 01.12) | N2: 01.12.2022
B3: Descartado | C3: PRE-FIS-ONE-2021-02/22-1039 | D3: Ljubinka Basic | E3: CS-2021-51309 | F3: Frusan Agro | G3: ONE | H3: ALIOTH | I3: Los Angeles | J3: 09.02.2021 | K3: PCCC | L3: Falta subro y AoR | M3: DELAY 11 días ETA 29.01 descarga 09.02. inspector indica condición no relacionada a tránsito | N3: 09.02.2022
B4: Descartado | C4: PRE-FIS-EGR-2021-12/21-0908 | D4: Ljubinka Basic | E4: CS-2021-50665 | F4: Agricola Rapel | G4: Evergreen | H4: CAP ANDREAS | I4: Shanghai | J4: 06.12.2020 | K4: Teamhead | L4: Falta subro,AoR,SR,SA,HC,SMV. | M4: Inspector indica condición de origen. No hay termógrafo disponible | N4: 06.12.2021
B5: Descartado | C5: PRE-FIS-CMA-2021-06/22-0824 | D5: Ljubinka Basic | E5: cs2020-05395 | F5: Verfrut | G5: CMA CGM | H5: CARTAGENA EXPRESS | I5: Rotterdam | J5: 09.06.2020 | K5: Fruit Inspection & Consultancy BV | L5: Falta subro,AoR,SR,TR,SA,HC,SMV | M5: Baja T° Inspeccion conjunta. Se indica posible sistema Quest. | N5: 09.06.2022
B6: Descartado | C6: PRE-FIS-CMA-2021-02/23-0966 | D6: Ljubinka Basic | E6: CS-2021-51187 | F6: FRUSAN | G6: CMA CGM | H6: CARTAGENA EXPRESS | I6: London Gateway | J6: 17.02.2021 | K6: MMS | M6: Inspector indica causa origen. packing entre el 11 y 16 de enero . inspector indica que ademas pueden haber dejado fruta más del tiempo debido en los arboles dado la falta de trabajadores. | N6: 17.02.2023
B7: Descartado | C7: PRE-FIS-HLL-2021-03/23-1037 | D7: Ljubinka Basic | E7: CS-2021-51171 | F7: Valle Maule | G7: Hapag Lloyd | H7: CAUQUENES | I7: Singapore | J7: 05.03.2021 | K7: Intertek, SGP | L7: Falta subro,AoR | M7: Delay 5 días. SR indica vicio inherente carga. credit note USD16,125.00. tiempo en unidad aumentó condición | N7: 05.03.2023
B8: Descartado | C8: PRE-FIS-ONE-2021-01/23-0951 | D8: Ljubinka Basic | E8: CS-2021-50412 | F8: Verfrut | G8: ONE | H8: CAUTIN | I8: Hong Kong | J8: 16.01.2021 | K8: Teamhead | L8: Falta subro,SR,SMV. Pendiente para solic subro. | M8: Plataforma indica origen, pero 1 termografo muestra temp anormal durante viaje. | N8: 16.01.2023
B9: Descartado | C9: PRE-FIS-HLL-2021-01/23-0923 | D9: Ljubinka Basic | E9: CS-2021-51357 | F9: Utilitas | G9: Hapag Lloyd | H9: CAUTIN | I9: Hong Kong | J9: 16.01.2021 | K9: Teamhead | L9: Falta subro,AoR,HC,SMV. | M9: termografo indica alza de temperatura durante vijae. Inspector indica problema de origen. | N9: 16.01.2023
B10: Descartado | C10: PRE-FIS-MSC-2021-03/22-0678 | D10: Ljubinka Basic | E10: cs2020-02985 | F10: geofrut | G10: MSC | H10: CAUTIN | I10: Hong Kong | J10: 43898 | K10: Fruit Inspection & Consultancy BV | L10: Falta PC, OC, HC, SMV | M10: Caso debil. Daño producto de calidad de origen. SR a modificar | N10: 08.03.2022
B11: Descartado | C11: PRE-FIS-CMA-2021-01/22-0980 | D11: Ljubinka Basic | E11: cs2020-10457 | F11: Propal | G11: CMA CGM | H11: CMA CGM NIAGARA | I11: Algeciras | J11: 01.12.2020 | K11: Eurovet | N11: 01.12.2022
B12: DESCARTADO | C12: PRE-FIS-HBS-2021-01/22-0599 | D12: Ljubinka Basic | E12: cs2020-08103 | F12: Lo Garces | G12: Hamburg Süd | H12: CORNELIUS MAERSK | I12: Shanghai | J12: 07.01.2020 | L12: Faltan documentos | M12: Se indica daño de origen/ caso descartable | N12: 07.01.2022
B13: DESCARTADO | C13: PRE-FIS-HBS-2021-01/22-0602 | D13: Ljubinka Basic | E13: cs2020-08105 | F13: Lo Garces | G13: Hamburg Süd | H13: CORNELIUS MAERSK | I13: Hong Kong | J13: 01.01.2020 | L13: Falta documentación/SR/INV. | M13: Se indica daño de origen. T° ok durante viaje | N13: 01.01.2022
B14: DESCARTADO | C14: PRE-FIS-EGR-2021-07/22-0828 | D14: Ljubinka Basic | E14: cs2020-06922 | F14: Copefrut | G14: Evergreen | H14: COSCO PRINCE RUPERT | I14: Kaohsiung | J14: 25.07.2020 | K14: Teamhead | L14: Falta subro,AoR,SR,SA,CI,HC,PC,OC,SMV. | M14: DELAY 15 días, acorde a carta cliente. Inpector indica en plataforma que daño es de orige | N14: 25.07.2022
B15: DESCARTADO | C15: PRE-FIS-EGR-2021-07/22-0829 | D15: Ljubinka Basic | E15: cs2020-06388 | F15: Copefrut | G15: Evergreen | H15: COSCO PRINCE RUPERT | I15: Kaohsiung | J15: 25.07.2020 | K15: Teamhead | L15: Falta subro,AoR,SR,SA,HC,PC,OC,SMV. | M15: DELAY 15 días, acorde a carta cliente. Inpector indica en plataforma que daño es de orige | N15: 25.07.2022
B16: DESCARTADO | C16: PRE-FIS-EGR-2021-07/22-0830 | D16: Ljubinka Basic | E16: cs2020-06383 | F16: Copefrut | G16: Evergreen | H16: COSCO PRINCE RUPERT | I16: Kaohsiung | J16: 25.07.2020 | K16: Teamhead | L16: Falta subro,AoR,CI,SR,SA,HC,PC,OC,SMV. | M16: DELAY 15 días, acorde a carta cliente. Inpector indica en plataforma que daño es de orige | N16: 25.07.2022
B17: DESCARTADO | C17: PRE-FIS-EGR-2021-07/22-0831 | D17: Ljubinka Basic | E17: cs2020-06375 | F17: Copefrut | G17: Evergreen | H17: COSCO PRINCE RUPERT | I17: Kaohsiung | J17: 25.07.2020 | K17: Teamhead | L17: Falta subro,AoR,CI,SR,SA,HC,PC,OC,SMV. | M17: DELAY 15 días, acorde a carta cliente. Inpector indica en plataforma que daño es de orige | N17: 25.07.2022
B18: DESCARTADO | C18: PRE-FIS-WAN-2021-02/22-0665 | D18: Ljubinka Basic | E18: cs2020-09370 | F18: frucentr | G18: Wan Hai | H18: COSCO YANTIAN | I18: Manzanillo | J18: 43889 | K18: no surveyor involved | L18: Falta CN,Subro,AoR,TR,SMV. | M18: No hay info. Solo contenedores rechazados por autoridad mexicana (solic. Fumigar de nuevo). | N18: 28.02.2022
B19: DESCARTADO | C19: PRE-FIS-ONE-2021-04/22-0882 | D19: NOT RECOVERABLE | E19: cs2020-03241 | F19: Quintay | G19: ONE | H19: COYHAIQUE | I19: Busan | J19: 11.04.2020 | K19: Hyopsung | L19: Falta subro,AoR,SA,HC,SMV. | M19: iNSPECTOR INDICA 10% ATRIBUIBLE A DELAY 90% A ORIGEN. No se indica cantidad de días delay. | N19: 11.04.2022
B20: DESCARTADO | C20: PRE-FIS-HLL-2021-02/22-0932 | D20: Ljubinka Basic | E20: CS-2021-52659 | F20: Frutas Finas de Valles de Michoacan | G20: Hapag Lloyd | H20: CROATIA | I20: Busan | J20: 13.02.2021 | K20: Hyopsung | L20: Falta subro,AoR,PL,SA,PC,OC,HC,SMV. | M20: DELAY 16 DÍAS. INSPECTOR INDICA CONDICIÓN ORIGEN. | N20: 13.02.2022
B21: DESCARTADO | C21: PRE-FIS-WAN-2021-01/22-0603 | D21: Ljubinka Basic | E21: cs2020-09368 | F21: Frucentro | G21: Wan Hai | H21: CSCL WINTER | I21: Manzanillo | J21: 29.01.2020 | L21: Falta Ph | M21: Baja temepratura, se debe determinar bajo custodia de quien. | N21: 29.01.2022
B22: DESCARTADO | C22: PRE-FIS-HLL-2021-10/21-0958 | D22: NOT RECOVERABLE | E22: cs2021-01698 | F22: Amefruit | H22: GLASGOW EXPRESS | I22: Montreal | J22: 30.10.2020 | L22: Falta CN, fotos, informe QC. ( SE RECLAMA COSTO "EXTRA") | M22: Unidad no embarcada en POL en nave provista. No hay info del motivo ni cuando se embarcó. Se está reclamando penalización por entrega fuera de plazo + fruta descarte, no hay informe de calidad ni nada de respaldo. | N22: 30.10.2021
B23: DESCARTADO | C23: PRE-FIS-MSC-2021-03/22-0671 | D23: Ljubinka Basic | E23: cs2020-02979 | F23: geofrut | G23: MSC | H23: HMM BLESSING | I23: Hong Kong | J23: 43891 | K23: no surveyor involved | L23: Falta CN, Subro, AoR, SR, HC, SMV | M23: VICIO INHERENTE/ ORIGEN. En termografo se ven algunas alzas en el viaje. Caso debil | N23: 01.03.2022
B24: DESCARTADO | C24: PRE- | D24: Ljubinka Basic | E24: CS-2021-50914 | F24: Intermodal Transporte y Logistica S.A. | G24: MSC | H24: ITAL UNIVERSO | I24: Kaoshiung | L24: NO HAY | M24: carga rechazada en destino por problemas con empaque de la carga
B25: DESCARTADO | C25: PRE-FIS-ONE-2021-02/22-1040 | D25: Ljubinka Basic | E25: CS-2021-51310 | F25: Frusan Agro | G25: ONE | H25: JULIANA | I25: Los Angeles | J25: 09.02.2021 | K25: PCCC | L25: Falta subro,AoR. | M25: Delay 18 días. ETA22.01 descargó 09.02, inspector indica daño no relacionado delay. | N25: 09.02.2022
B26: DESCARTADO | C26: PRE-FIS-MAE-2021-07/21-0576 | D26: Ljubinka Basic | E26: cs2019-06252 | F26: Copefrut | G26: Maersk Line | H26: MAERSK NIAMEY | I26: St. Petersburg | J26: 13.07.2019 | L26: Falta CN,AoR | M26: Alza enorme temperatura durante transporte/ Posible malfuncionamiento | N26: 13.07.2021
B27: DESCARTADO | C27: PRE-FIS-MAE-2021-06/21-0575 | D27: Ljubinka Basic | E27: cs2019-06055 | F27: Verfrut | G27: Maersk Line | H27: MARINER | I27: St. Petersburg | J27: 23.06.2019 | L27: Faltan pocos documentos | M27: Alza temperatura durante transporte/posible malfuncionamiento
B28: DESCARTADO | C28: PRE-FIS-CMA-2021-06/21-0586 | D28: Ljubinka Basic | E28: cs2020-05375 | F28: Itacu Corporation ltda. | G28: CMA CGM | H28: MARY | I28: Leghorn | J28: 29.06.2020 | L28: Faltan pocos documentos | M28: Caso debil por falta de evidencia de preenfriado/
B29: DESCARTADO | C29: PRE-FIS-ONE-2021-04/22-0897 | D29: Ljubinka Basic | E29: cs2020-03924 | F29: Verfrut | G29: ONE | H29: MAULLIN | I29: Laem Chabang | J29: 29.04.2020 | K29: Other | L29: Falta subro,AoR,HC,SMV. | M29: Alza de temp durante viaje. / NO LOSS | N29: 29.04.2022
B30: DESCARTADO | C30: PRE-FIS-MSC-2021-01/23-0767 | D30: Ljubinka Basic | E30: CS-2021-51111 | F30: Subsole | G30: MSC | H30: MOL BEACON | I30: Hong Kong | J30: 23.01.2021 | K30: Teamhead | L30: Falta subro, AoR,SR,SMV. | M30: Nunca estuvo a la Temp seteada. inspector indica temp normal. | N30: 23.01.2023
B31: DESCARTADO | C31: PRE-FIS-MSC-2021-01/23-0948 | D31: Ljubinka Basic | E31: CS-2021-50402 | F31: Verfrut | G31: MSC | H31: MOL BENEFACTOR | I31: Hong Kong | J31: 02.01.2021 | K31: Teamhead | L31: Falta subro,AoR,HC,SMV. | M31: > | N31: 02.01.2023
B32: DESCARTADO | C32: PRE-FIS-HMM-2021-01/23-0928 | D32: Ljubinka Basic | F32: Utilitas | G32: HMM | H32: MOL BENEFACTOR | I32: Hong Kong | J32: 02.01.2021 | L32: Falta CN,subro,AoR,PH,HC,SMV. No se realizó inspección. | M32: No hay info, no hubo delay. no hay termografos. | N32: 02.01.2023
B33: DESCARTADO | C33: FIS-MSC-2021-02/22-0661 | D33: Jan Klempau | E33: cs2020-02766 | F33: geofrut | G33: MSC | H33: MOL BENEFACTOR | I33: Hong Kong | J33: 43883 | K33: Fruit Inspection & Consultancy BV | L33: Falta HC. Ok | M33: REPORTE INDICA CAUSA DEBIDO AL LA CALIDAD DE ORIGEN DE LA FRUTA. Termografo se ve durante todo el viaje con T° sobre setting.CN indica problema Tº | N33: 22.02.2022
B34: DESCARTADO | C34: PRE-FIS-HMM-2021-12/22-0930 | D34: Ljubinka Basic | F34: Utilitas | G34: HMM | H34: MOL BEYOND | I34: Hong Kong | J34: 26.12.2020 | L34: Falta CN,subro,AoR,HC,SMV.NO SE HIZO INSPECCIÓN | M34: uno de los termografos muestra alza de temp. no hay mayor info del daño. | N34: 26.12.2022
B35: DESCARTADO | C35: PRE-FIS-HMM-2021-12/22-0931 | D35: Ljubinka Basic | F35: Utilitas | G35: HMM | H35: MOL BEYOND | I35: Hong Kong | J35: 26.12.2020 | L35: Falta CN,subro,AoR,HC,SMV. No hay inspección. Se requiere liq. Comparativa | M35: no se indica razón del daño. un solo termografo con temp un poco elevada | N35: 26.12.2022
B36: DESCARTADO | C36: PRE-FIS-ONE-2021-12/22-0810 | D36: Ljubinka Basic | E36: CS-2021-50545 | F36: Copefrut | H36: MOL BEYOND | I36: Shenzen | J36: 03.12.2020 | K36: Crawford, CHL | L36: Falta todo, solo disponible SR. | M36: No se entiende reclamación si en inspección en POL carga fue encontrada en buenas condiciones para exportar. Se indica pago de la compañía de seguro de transportista terrestre.. | N36: 03.12.2022
B37: DESCARTADO | C37: PRE-FIS-MSC-2021-03/23-0991 | D37: standby | E37: cs-2021-53293 | F37: Verfrut | G37: MSC | H37: MSC ABIDJAN | I37: Rotterdam | J37: 18.03.2021 | K37: Fruit Inspection & Consultancy BV | L37: Falta subro,AoR,SR,SMV. Sin SMV disponible | M37: DELAY 9 DÍAS. Se indica condición de origen. el delay puede haber sumado al daño, pero habría llegado carga con misma condición sin delay. ETA:10.03 DISCHAR 19.03 | N37: 18.03.2023
B38: DESCARTADO | C38: PRE-FIS-MSC-2021-10/21-0825 | D38: Ljubinka Basic | E38: cs2020-05725 | F38: El Parque | G38: MSC | H38: MSC AINO | I38: London Gateway | L38: Falta CN,Subro,AoR,PH,TR,SA,HC,SMV. No se hizo inspección. | M38: FECHA BL/se solicita info GH, roleo nave // delay | N38: 26.10.2021
B39: DESCARTADO | C39: PRE-FIS-MSC-2021-10/21-0826 | D39: Ljubinka Basic | E39: cs2020-05724 | F39: El Parque | G39: MSC | H39: MSC AINO | I39: London Gateway | L39: Falta CN,Subro,AoR,CI,PH,TR,SA,HC,SMV. | M39: FECHA BL/se solicita info GH, roleo nave // delay | N39: 26.10.2021
B40: DESCARTADO | C40: PRE-FIS-MSC-2021-10/21-0827 | D40: Ljubinka Basic | E40: cs2020-05722 | F40: El Parque | G40: MSC | H40: MSC AINO | I40: London Gateway | L40: Falta todo, solo hay CNy SMV | M40: FECHA BL/se solicita info GH, roleo nave // delay | N40: 26.10.2021
B41: DESCARTADO | C41: PRE-FIS-MSC-2021-10/21-0855 | D41: Ljubinka Basic | E41: cs2020-05723 | F41: El parque | G41: MSC | H41: MSC AINO | I41: London Gateway | L41: Falta todo. Solo hay CN | M41: Fecha de los demás embarques /se solicita info GH, roleo nave // delay | N41: 26.10.2021
B42: DESCARTADO | C42: PRE-FIS-MSC-2021-01/23-0763 | D42: Ljubinka Basic | E42: CS-2021-50550 | F42: Copefrut | G42: MSC | H42: MSC ALESSIA | I42: Shanghai | J42: 02.01.2021 | K42: Teamhead | L42: Falta subro,AoR,SR,SA,HC,PC,OC,SMV. SE HIZO JS | M42: Inspector indica causa de origen, pero termógrafos se ven con temp anormal (posible sistema Quest). | N42: 02.01.2023
B43: DESCARTADO | C43: PRE-FIS-MSC-2021-02/22-0636 | D43: Ljubinka Basic | E43: cs2020-06644 | F43: Organic Time | G43: MSC | H43: MSC ANCHORAGE | I43: Philadelphia | J43: 43864 | L43: Falta export invoice, subro, cert destru, AoR | M43: Caso debil, contaminación de carga durante desconsolidado. | N43: 03.02.2022
B44: DESCARTADO | C44: PRE-FIS-MSC-2021-03/23-0987 | D44: standby | E44: CS-2021-53288 | F44: Verfrut | G44: MSC | H44: MSC ATLANTIC | I44: Rotterdam | J44: 18.03.2021 | K44: Fruit Inspection & Consultancy BV | L44: Falta subro,AoR,PL,SR,HC. | M44: ELAY 8 DÍAS. Se indica condición de origen. el delay puede haberr sumado al daño, pero habría llegado carga con misma condición sin delay. ETA:10.03 DISCHAR 18.03 | N44: 18.03.2023
B45: DESCARTADO | C45: PRE-FIS-MSC-2021-03/23-0988 | D45: standby | E45: CS-2021-53287 | F45: Verfrut | G45: MSC | H45: MSC ATLANTIC | I45: Rotterdam | J45: 18.03.2021 | K45: Fruit Inspection & Consultancy BV | N45: 18.03.2023
B46: DESCARTADO | C46: PRE-FIS-MSC-2021-03/22-0939 | D46: Ljubinka Basic | E46: CS-2021-52661 | F46: Frutura | G46: MSC | H46: MSC ATLANTIC | I46: Rotterdam | J46: 18.03.2021 | K46: Fruit Inspection & Consultancy BV | L46: Falta subro,SR,SA,HC,SMV. no existe origen o euro 1. | M46: Delay de 9 días. iNSPECTOR CREE QUE CONDICIÓN ES DE ORIGEN INCLUSO SI CARGA HUBIESE LLEGADO UNA SEMANA ANTES HABRÍA PRESENTADO MISMO DAÑO. | N46: 18.03.2022
B47: DESCARTADO | C47: PRE-FIS-MSC-2021-03/23-1022 | D47: Ljubinka Basic | E47: CS-2021-53447 | F47: CYD | G47: MSC | H47: MSC ATLANTIC | I47: Rotterdam | J47: 19.03.2021 | K47: Fruit Inspection & Consultancy BV | N47: 19.03.2023
B48: DESCARTADO | C48: PRE-FIS-MSC-2021-07/22-0894 | D48: NOT RECOVERABLE | E48: cs2020-06378 | F48: Utilitas | G48: MSC | H48: MSC CHLOE | I48: Philadelphia | J48: 20.07.2020 | K48: PCCC | L48: Falta subro,AoR,SMV. | M48: Alza de temperatura durante viaje. | N48: 20.07.2022
B49: DESCARTADO | C49: PRE-FIS-MSC-2021-02/22-0659 | D49: Ljubinka Basic | E49: cs2020-01678 | F49: vallemau | G49: MSC | H49: MSC EARTH | I49: Rotterdam | J49: 43882 | K49: Teamhead | L49: Falta SR, Subro, AoR, HC, DC, SMV | M49: CA PROBLEMAS. Leves diferencias de T°/ inspector indica daño no relacionado al transporte. | N49: 21.02.2022
B50: DESCARTADO | C50: PRE-FIS-MSC-2021-02/22-0660 | D50: Ljubinka Basic | E50: cs2020-01677 | F50: vallemau | G50: MSC | H50: MSC EARTH | I50: Rotterdam | J50: 43882 | K50: Teamhead | L50: Falta SR, Subro, AoR, HC, DC, SMV | M50: Posible filtración de CA, sin determinar Surveyor no inspecciona unidad, al igual que en los otros casos. No rel. Transp | N50: 21.02.2022
B51: DESCARTADO | C51: PRE-FIS-MSC-2021-10/21-0933 | D51: Ljubinka Basic | E51: CS-2020-50276 | F51: Frutas Finas de Valles de Michoacan | G51: MSC | H51: MSC ELISA | I51: Singapore | J51: 10.10.2020 | K51: Intertek, SGP | L51: Falta CN,subro,AoR,SA,HC,PC,OC,SMV. | M51: Se indica vicio inherente agravado por delay. | N51: 10.10.2021
B52: DESCARTADO | C52: PRE-FIS-ONE-2021-09/22-0852 | D52: Ljubinka Basic | E52: cs2020-08110 | F52: Copefrut | G52: ONE | H52: MSC ELISA | I52: Yokohama | J52: 19.09.2020 | K52: SCUA | L52: Falta subro,AoR,HC,PC,OC,SMV. Liquidación poco formal. | M52: teMP. SET -0.5°c. TERMOGRAFO SE VE | N52: 19.09.2022
B53: DESCARTADO | C53: PRE-FIS-MSC-2021-09/21-0712 | D53: Ljubinka Basic | E53: cs2019-08388 | F53: El Parque | G53: MSC | H53: MSC GAYANE | I53: London Gateway | J53: 29.09.2019 | K53: MMS | L53: Falta subro insured,HC | M53: Temp, seteo 5°C, estuvo a 1.5°C | N53: 29.09.2021
B54: DESCARTADO | C54: PRE-FIS-MSC-2021-03/23-0993 | D54: Ljubinka Basic | E54: CS-2021-53285 | F54: Verfrut | G54: MSC | H54: MSC NITYA B | I54: Algeciras | J54: 16.03.2021 | K54: Eurovet | L54: Falta CN,subro,AoR,PH,SR,SA. | M54: Se indica condición de origen temp ok y TT ok. | N54: 16.03.2023
B55: DESCARTADO | C55: PRE-FIS-MSC-2021-03/23-1026 | D55: Ljubinka Basic | E55: CS-2021-53225 | F55: Prize | G55: MSC | H55: MSC SHUBA B | I55: Philadelphia | J55: 15.03.2021 | K55: PCCC | L55: Falta subro,AoR. | M55: Se indica causa no relacionada a transporte. Pérdida $22,318.24 | N55: 15.03.2023
B56: DESCARTADO | C56: PRE-FIS-HBS-2021-10/21-0776 | E56: cs2020-09347 | F56: Eosta | G56: Hamburg Süd | H56: MSC SORAYA | I56: Antwerpen | J56: 08.10.2020 | L56: Falta Subro,PH,SR,HC. | M56: Carga pérdida total. Falta SR para más antecedentes. | N56: 08.10.2021
B57: DESCARTADO | C57: PRE-FIS-MSC-2021-02/23-0803 | D57: NOT RECOVERABLE | E57: CS-2021-52320 | F57: Copefrut | G57: MSC | H57: MSC YASHI B | I57: Jeddah | J57: 18.02.2021 | K57: AIS | L57: Falta subro,AoR,PL,SR,SA. | M57: Temp anormal. Inspector indica tema calidad.B305:I305 | N57: 18.02.2023
B58: DESCARTADO | C58: PRE-FIS-MSC-2021-12/22-0802 | D58: NOT RECOVERABLE | E58: CS-2020-50344 | F58: A5 Export | G58: MSC | H58: MSC YASHI B | I58: Rotterdam | J58: 01.12.2020 | K58: Fruit Inspection & Consultancy BV | L58: Falta subro, AoR,SR. | M58: Inspector indica no relacionado a transporte, termo se ve bien. Se embarcó el 31.10 y descargó el 01.12. | N58: 01.12.2022
B59: DESCARTADO/PRESENTADO | C59: FIS-CMA-2021-11/21-0593 | D59: Ljubinka Basic | E59: cs2020-10437 | F59: Itacu Corporation ltda. | G59: CMA CGM | H59: PHILEMON | I59: Rotterdam | J59: 01.11.2020 | L59: REMINDER 10.06 | M59: Alza temperatura durante transporte. | N59: 01.11.2021
B60: DESCARTADO | C60: PRE-FIS-MAE-2021-02/22-0648 | D60: Ljubinka Basic | E60: cs2020-04176 | F60: vallemau | G60: MAERSK | H60: RHINE MAERSK | I60: Antwerpen | J60: 43876 | K60: Fruit Inspection & Consultancy BV | L60: Falta GR, SR, HC, Subro, AoR, SMV | M60: Caso debil, condición previo embarque. Posible filtración CA (drenaje o pcortina), mal consolidado- | N60: 15.02.2022
B61: DESCARTADO | C61: PRE-FIS-MSC-2021-03/23-0613 | D61: Ljubinka Basic | E61: CS-2021-50915 | F61: Intermodal Transporte y Logistica S.A. | G61: MSC | H61: SEASPAN BELIEF | I61: Kaohsiung | J61: 05.03.2021 | L61: NO HAY | M61: carga rechazada en destino por problemas con empaque de la carga | N61: 05.03.2023
B62: DESCARTADO | C62: PRE-FIS-MSC-2021-04/22-0870 | D62: Ljubinka Basic | E62: cs2020-03549 | F62: Organic Time | G62: MSC | H62: SKYROS | I62: Hong Kong | J62: 12.04.2020 | K62: Teamhead | L62: Falta subro,AoR,HC,PC,OC,SMV. | M62: SR indica condición de origen. Termografo muestra termeratura normal. | N62: 12.04.2022
B63: DESCARTADO | C63: FIS-HBS-2021-10/21-0577 | D63: Ljubinka Basic | E63: cs2019-08389 | F63: El Parque | G63: Hamburg Süd | H63: SOVEREIGN MAERSK | J63: 15.10.2019 | L63: YA HABÍA SIDO PRESENTADO POR ASEGURADO | M63: Delay/ 14 días / indica además daño de origen
B64: DESCARTADO | C64: PRE-FIS-CC-2021-03/22-0696 | D64: Ljubinka Basic | E64: cs2020-04545 | F64: Agrofruta S.A. | G64: COOL CARRIERS | H64: STAR BEST | I64: Gloucester City | J64: 43903 | L64: Falta subro,AoR,TR,HC,SMV | M64: Alzas de temperatura durante viaje. Falta tracking para revisar fechas Thermo si son post salida Terminal | N64: 13.03.2022
B65: DESCARTADO | C65: PRE-FIS-EGR-2021-01/22-0622 | D65: Ljubinka Basic | E65: cs2020-01206 | F65: Verfrut | G65: Evergreen | H65: VALUE | I65: Hong Kong | J65: 22.01.2020 | L65: Falta documentación | M65: Baja T° menor de -1.5 (set -1) caso debill/revisar reu Rafa exhibición data(posible sistema Quest) | N65: 22.01.2022
B66: DESCARTADO | C66: PRE-FIS-WAN-2021-04/22-0857 | D66: Ljubinka Basic | E66: cs2020-09369 | F66: Frucentro | G66: Wan Hai | H66: XIN OU ZHOU | I66: Manzanillo | J66: 04.04.2020 | L66: Falta todo. disponible subro cnee.No se hizo inspección | M66: Unidades rechazadas por autoridad mexicana, se solicita refumigar. | N66: 04.04.2022
B67: DESCARTADO | C67: NOT RECOVERABLE | D67: Ljubinka Basic | E67: cs2020-03544 | F67: rucaray | G67: trans y log san esteban | J67: 43910 | M67: No figura fecha descargaT transporte terrestre, precrito 2020, carga congelada. | N67: 20.03.2022
B68: DESCARTADO | C68: NOT RECOVERABLE | D68: Ljubinka Basic | E68: cs2020-03198 | F68: nicofrut | G68: Marvel | J68: 43908 | M68: Caso prescrito marzo2021
B69: DESCARTADO | C69: PRE-FIS-MSC-2021-03/22-0710 | D69: Ljubinka Basic | E69: cs2020-03560 | F69: geofrut | G69: MSC | J69: 43920 | L69: Falta HC. | M69: Delay 8días . Surveyor indica daño producto de condición de origen. | N69: 30.03.2022
B70: DESCARTADO | C70: PRE-FIS-COS-2021-01/23-1076 | D70: NOT RECOVERABLE | E70: CS-2021-51360 | F70: Greenex SpA | G70: COSCO | H70: XIN YA ZHOU | I70: Hong Kong | J70: 29.01.2021 | K70: Teamhead | L70: Falta subro, AoR,SR. | M70: Se indica reclamo fue por temperatura, pero thermo se ve ok. Inspector indica problema de origen. | N70: 29.01.2023
B71: DESCARTADO | C71: PRE-FIS-MSC-2021-01/23-1081 | D71: NOT RECOVERABLE | F71: Greenvic | G71: MSC | H71: MSC BIANCA | I71: Long Beach | J71: 14.01.2021 | L71: Falta CN,subro,AoR,Booking,SMV,HC. | M71: Delay, perdida de mercado. No se hizo inspección. Casi 1 mes de tránsito. | N71: 14.01.2023
B72: DESCARTADO | C72: FIS-MAE-2021-05/21-0585 | D72: NOT RECOVERABLE | E72: cs2020-07818 | F72: Sunshine Peru | G72: Maersk Line | H72: MINSTREL | I72: Rotterdam | J72: 19.05.2020 | L72: 3 REMINDER MAERSK 02.06 | M72: Buque con retraso por tripulante con COVID | N72: 18.10.2021 | O72: 8.786,56USD | P72: 18.10.2021
B73: DESCARTADO | C73: FIS-CMA-2021-12/21-0609 | D73: Ljubinka Basic | E73: cs2020-10475 | F73: Delot d.o.o | G73: CMA CGM | H73: MARY | I73: Koper | J73: 22.12.2020 | L73: Falta PL,HC | M73: SE PRESENTÓ Y DATA ESTABA LIMPIO | N73: 22.12.2021 | O73: 18.334,51EUR | P73: SMV
B74: PRESCRITO | C74: FIS-AEL-2021-05/21-0587 | D74: Ljubinka Basic | E74: cs2020-04571 | F74: Eosta | G74: African Express Line | H74: COSTA RICAN STAR | I74: Antwerpen | J74: 04.05.2020 | L74: Falta documentación relevante. | M74: Transporte terrestre apagado origen. Se presenta a FFW | O74: NA /47.600 EUR | P74: SE SOLICITA
B75: DESCARTADO | C75: PRE-FIS-MSC-2021-11/21-0934 | D75: Ljubinka Basic | E75: CS-2020-50278 | F75: Frutas Finas de Valles de Michoacan | G75: MSC | H75: MSC VEGA | I75: Singapore | J75: 04.11.2020 | K75: Intertek, SGP | L75: Falta CN,subro,AoR,SA,HC,PC,OC,SMV. | M75: INSPECTOR INDICA VICIO INHERENTE AGRAVADO POR DELAR. | N75: 04.11.2021
B76: DESCARTADO | C76: PRE-FIS-ONE-2021-02/23-1096 | D76: NOT RECOVERABLE | E76: CS-2021-51152 | F76: Greenvic | G76: ONE | H76: CAUQUENES | I76: Hong Kong | J76: 22.02.2021 | K76: Teamhead | L76: Falta subrogación,AoR,CI,SR,SMV. | M76: Inspector indica causa de origen. | N76: 22.02.2023
B77: DESCARTADO | C77: FIS-ONE-2021-02/23-0794 | D77: Ljubinka Basic | E77: CS-2021-50376 | F77: Gravo | G77: ONE | H77: COCHRANE | I77: Busan | J77: 14.02.2021 | K77: Hyopsung | L77: Credit note disponible. Falta SA. | M77: Baja Temp y vicio inherente/ PRESENTADO NAVIERA MUESTRA DATA LIMPIO | N77: 14.02.2023 | O77: 15.428,93USD
B78: DESCARTADO | C78: PRE-FIS-EGR-2021-12/21-1128 | D78: NOT RECOVERABLE | E78: CS-2021-50312 | F78: Agrovision | G78: Evergreen | H78: JULIANA | I78: Shanghai | J78: 12.12.2020 | K78: Teamhead | L78: Falta CN,subro,AoR,CI,SR,HC,PC,OC. | M78: Inspector indica vicio inherente. Carga tuvo un delay de 6 días. Se indica que el TT fue de 38 días.
B79: DESCARTADO | C79: PRE-FIS-EGR-2021-01/22-1139 | D79: NOT RECOVERABLE | E79: CS-2021-50338 | F79: Agrovision | G79: Evergreen | H79: KOTA CANTIK | I79: Shanghai | J79: 20.01.2021 | K79: Teamhead | M79: Inspector indica daño de origen.
B80: DESCARTADO | C80: PRE-FIS-MSC-2021-12/21-1051 | D80: Ljubinka Basic | E80: cs2020-06353 | F80: BB Trading | G80: MSC | H80: CORCOVADO | I80: Hong Kong | L80: Falta CN,Subro,TR,SMV | M80: No hay informaciòn | N80: 30.12.2021 | O80: NA | P80: 21.01.2019
B81: DESCARTADO | C81: PRE-FIS-MSC-2021-12/21-1050 | D81: Ljubinka Basic | E81: cs2020-06344 | F81: BB Trading | G81: MSC | H81: Corcovado | I81: Hong Kong | L81: Falta CN,Subro,TR,SMV | M81: No hay informaciòn | N81: 30.12.2021 | O81: NA | P81: 22.01.2019
B82: DESCARTADO | C82: PRE-FIS-MSC-2021-12/21-1049 | D82: Ljubinka Basic | E82: cs2020-06343 | F82: BB Trading | G82: MSC | H82: Corcovado | I82: Hong Kong | L82: Falta CN,Subro,TR,SMV | M82: No hay informaciòn | N82: 30.12.2021 | O82: NA | P82: 22.01.2019
B83: DESCARTADO | C83: PRE-FIS-ONE-2021-12/21-1048 | D83: Ljubinka Basic | E83: cs2020-06342 | F83: BB Trading | G83: ONE | H83: Corcovado | I83: Hong Kong | L83: Falta CN,Subro,TR,SMV | M83: No hay informaciòn | N83: 30.12.2021 | O83: NA | P83: 22.01.2019
B84: DESCARTADO | C84: PRE-FIS-EGR-2021-12/21-1058 | D84: Ljubinka Basic | E84: cs2020-06352 | F84: BB Trading | G84: Evergreen | H84: VALUE | I84: =Descartados!$I$910 -> Hong Kong | L84: Falta CN,Subro,TR,SMV | M84: No hay informaciòn | N84: NA | O84: NA | P84: 21.01.2019
B85: DESCARTADO | C85: PRE-FIS-EGR-2021-12/21-1057 | D85: Ljubinka Basic | E85: cs2020-06351 | F85: BB Trading | G85: Evergreen | H85: VALUE | I85: =Descartados!$I$910 -> Hong Kong | L85: Falta CN,Subro,TR,SMV | M85: No hay informaciòn | N85: NA | O85: NA | P85: 21.01.2019
B86: DESCARTADO | C86: PRE-FIS-EGR-2021-12/21-1056 | D86: Ljubinka Basic | E86: cs2020-06349 | F86: BB Trading | G86: Evergreen | H86: VALUE | I86: =Descartados!$I$910 -> Hong Kong | L86: Falta CN,Subro,TR,SMV | M86: No hay informaciòn | N86: NA | O86: NA | P86: 21.01.2019
B87: DESCARTADO | C87: PRE-FIS-EGR-2021-1221-1055 | D87: Ljubinka Basic | E87: cs2020-06348 | F87: BB Trading | G87: Evergreen | H87: VALUE | I87: =Descartados!$I$910 -> Hong Kong | L87: Falta CN,Subro,TR,SMV | M87: No hay informaciòn | N87: NA | O87: NA | P87: 21.01.2019
B88: DESCARTADO | C88: PRE-FIS-EGR-2021-01/22-0627(C19) | D88: Ljubinka Basic | E88: cs2020-06350 | F88: BB Trading | G88: Evergreen | H88: VALUE | I88: Hong Kong | J88: 21.01.2020 | L88: Falta CN. No se hizo inspección | M88: PLATAFORMA INDICA DESCARGA 21.01, MISMA FECHA QUE BOOKING ETA. SA indica 27.01 | N88: 21.01.2022 | O88: NA
B89: DESCARTADO | C89: PRE-FIS-EGR-2021-01/22-0628(C19) | D89: Ljubinka Basic | E89: cs2020-06354 | F89: BB Trading | G89: Evergreen | H89: VALUE | I89: Hong Kong | J89: 21.01.2020 | L89: Falta CN,Subro,PH,HC,SMV(AOR). Aún no es posible determinar monto sin liqui. Compara | M89: No hay info/ no hay inspección. | N89: 21.01.2022 | O89: NA
B90: DESCARTADO | C90: PRE-FIS-ONE-2021-01/22-1131 | D90: NOT RECOVERABLE | E90: CS-2021-50318 | F90: Agrovision | G90: ONE | H90: MSC ELISA | I90: Shanghai | J90: 08.01.2021 | K90: Teamhead | L90: Falta subro,AoR,SR,PC,OC. | M90: Delay 16 días. Inspector indica vicio inherente.JS | N90: 08.01.2022
B91: DESCARTADO | C91: PRE-FIS-EGR-2021-03/23-1070 | D91: NOT RECOVERABLE | E91: CS-2021-53451 | F91: Rio Blanco SpA | G91: Evergreen | H91: ITAL USODIMARE | I91: Busan | J91: 24.03.2021 | K91: Hyopsung | L91: Falta subro,AoR,SA. Disponible credit note. Se hizo JS. | M91: Delay 16 días. Inspector indica vicio inherente. | N91: 24.03.2023
B92: DESCARTADO | C92: PRE-FIS-MSC-2021-02/22-0640 | D92: Ljubinka Basic | E92: cs2020-02548 | F92: Collipulli Red Soil S.A. | G92: MSC | H92: COPIAPO | I92: Hong Kong | J92: 43870 | K92: Sadaoui | L92: Falta SR, CN, CI,SA, SMV,PC, OC, HC, subro, AoR | M92: Caso general.- Se indica vicio inherente/15 días demora cnee en retirar/ Thermo muestra alza de t° | N92: 09.02.2022 | O92: NA
B93: DESCARTADO | C93: PRE-FIS-ONE-2021-02/22-0638 | D93: Ljubinka Basic | E93: cs2020-02547 | F93: Collipulli Red Soil S.A. | G93: ONE | H93: COPIAPO | I93: Hong Kong | J93: 43869 | K93: Eurovet | L93: Falta CN, fact. SA, SR,Subro, HC, PC,OC, AoR | M93: Caso general. Caso débil. Se indica vicio inherente/ 15 días demora entre descarga y retiro/ Thermo muestra T° sobre set app 1° | N93: 08.02.2022 | O93: NA
B94: DESCARTADO | C94: PRE-FIS-ONE-2021-02/22-0641 | D94: Ljubinka Basic | E94: cs2020-02193 | F94: Collipulli Red Soil S.A. | G94: ONE | H94: COPIAPO | I94: Hong Kong | J94: 43870 | K94: Hyopsung | L94: Falta SR, CN, CI,SA, SMV,PC, OC, HC, subro, AoR | M94: Caso general. Se indica vicio inherente/ T° en rango | N94: 09.02.2022 | O94: NA
B95: DESCARTADO | C95: PRE-FIS-MSC-2021-05/23-1086 | D95: Ljubinka Basic | E95: CS-2021-53269 | F95: Greenvic | G95: MSC | H95: MSC BIANCA | I95: Buenaventura | J95: 10.05.2021 | K95: ACI | L95: Falta subro,AoR,SR | M95: MANZANAS CON DAÑO DE ORIGEN Y PERAS CON DAÑO ATRIBUIBLE A DELAY. CLIENTE DEMORA EN RETIRAR UNIDAD. | N95: 10.05.2023
B96: DESCARTADO | C96: PRE-FIS-MSC-2021-05/23-1087 | D96: Ljubinka Basic | E96: CS-2021-53270 | F96: Greenvic | G96: MSC | H96: MSC BIANCA | I96: Buenaventura | J96: 10.05.2021 | K96: ACI | L96: Falta subro,AoR,SR | M96: Inspector indica daño de origen y demora. Se hizo JS. La demora se genera en el retiro de la unidad por parte del cnee. | N96: 10.05.2023
B97: DESCARTADO | C97: PRE-FIS-MSC-2021-05/23-1083 | D97: Ljubinka Basic | E97: CS-2021-53272 | F97: Greenvic | G97: MSC | H97: MSC CHLOE | I97: Buenaventura | J97: 24.05.2021 | K97: ACI | L97: Falta subro,AoR,SR. | M97: SE hizo JS, cliente demora en retiro TT14 días + problemas de calidad. | N97: 24.05.2023
B98: DESCARTADO | C98: PRE-FIS-MSC-2021-04/23-1084 | D98: Ljubinka Basic | E98: CS-2021-53267 | F98: Greenvic | G98: MSC | H98: MSC NITYA B | I98: Buenaventura | J98: 30.04.2021 | K98: ACI | L98: Falta subro,AoR,SR | M98: cliente demora en retiro de unidad. Se indica vicio inherente. | N98: 30.04.2023
B99: DESCARTADO | C99: PRE-FIS-MSC-2021-04/23-1085 | D99: Ljubinka Basic | E99: CS-2021-53268 | F99: Greenvic | G99: MSC | H99: MSC NITYA B | I99: Buenaventura | J99: 30.04.2021 | K99: ACI | L99: Falta subro,AoR,SR | M99: Se hizo inspección conjunta. CLIENTE DEMORA EN RETIRO. sE INDICA VICIO INHERENTE. | N99: 30.04.2023
B100: DESCARTADO | C100: PRE-FIS-MSC-2021-04/23-1088 | D100: Ljubinka Basic | E100: CS-2021-53264 | F100: Greenvic | G100: MSC | H100: MSC NITYA B | I100: Buenaventura | J100: 30.04.2021 | K100: ACI | L100: Falta subro,AoR,SR | M100: Daño de origen y delay. Cnee demora en retirar. Se hizo JS. | N100: 30.04.2023
...

Sheet Negotiated
B1: Id | C1: Reference No | D1: Claim Handler | E1: CS Claim No | F1: Assured | G1: Opponent | H1: Vessel | I1: Place of Discharge | J1: Date of Discharge | K1: Surveyorcomp | L1: Status
B2: TRASPASADO | C2: PRE-FIS-MAE-2024-11/24-2928 | D2: Camila Sanhueza | E2: CS-2023-11849 | F2: Van Der Lans | G2: Maersk Line | H2: (NOT IN LIST) | I2: Rotterdam | J2: 25.11.2023 | K2: HDG B.V. | L2: 344N | M2: Falta Harvest, Origen, Stuffing Report
B3: PRESENTAR | C3: PRE-FIS-CC-2023-03/25-2718 | D3: Thomas Chatterton | E3: CS-2023-04253 | F3: Agricom | G3: Cool Carriers | H3: (NOT IN LIST) | I3: Philadelphia | J3: 09.03.2023 | K3: PCCC | L3: EC170 | M3: OK
B4: PRESENTAR | C4: PRE-FIS-CMA-2023-03/25-2814 | D4: Thomas Chatterton | E4: CS-2023-04205 | F4: FRUSAN | G4: CMA CGM | H4: (NOT IN LIST) | I4: Philadelphia | J4: 21.03.2023 | K4: PCCC | L4: 0LI0MN1MA | M4: Falta AoR, Harvest, DUS, IVV, Booking, Stuffing
B5: PRESENTAR | C5: PRE-FIS-CMA-2024-11/25-2910 | D5: Thomas Chatterton | E5: CS-2024-01478 | F5: Agricola Rapel | G5: CMA CGM | H5: (NOT IN LIST) | I5: Yokohama | J5: 24.11.2023 | K5: SCUA | L5: 0DVGWN1MA | M5: ok
C6: FIS-DLA-2021-12/21-0578 | D6: Ljubinka Basic | E6: cs2020-01205 | F6: Los Lirios | G6: Delta Air | H6: AIRFREIGHT | I6: Los Angeles | J6: 06.12.2019 | L6: Falta CN | M6: Alza de T° durante custodia autoridad. Caso debil. PERDIDA TOTAL
B7: PRESENTAR. Extrajudicial | C7: PRE-FIS-DLA-2023-12/23-2407 | D7: Victor Vilches | E7: CS-2022-12364 | F7: El Parque Chile | G7: Delta Air | H7: AIRFREIGHT | I7: Incheon | J7: 03.12.2022 | K7: Hyopsung | L7: 116W | M7: Falta AoR, Loading report with temperature, liquidación comparative
B8: TRASPASADO | C8: FIS-LTM-2022-11/22-1389 | D8: MATIAS | E8: CS-2021-50645 | F8: Gidding Cerasus S.A. | G8: Latam Airlines | H8: AIRFREIGHT | I8: Shanghai | J8: 28.11.2020 | K8: Teamhead | M8: Falta intercambio con Aerolinea
B9: TRASPASADO | C9: FIS-LTM-2022-11/22-1394 | D9: MATIAS | E9: CS-2021-50292 | F9: Gidding Cerasus S.A. | G9: Latam Airlines | H9: AIRFREIGHT | I9: Shanghai | J9: 25.11.2020 | K9: Teamhead | M9: ok
B10: TRASPASADO | C10: FIS-LTM-2022-11/22-1395 | D10: MATIAS | E10: CS-2021-50646 | F10: Gidding Cerasus S.A. | G10: Latam Airlines | H10: AIRFREIGHT | I10: Shanghai | J10: 28.11.2020 | K10: Teamhead | M10: Falta CN,intercambio con AEROLINEA (No se recibirá CN)
B11: presentar | C11: PRE-FIS-LUF-2023-12/24-2566 | D11: camila sanhuza | E11: CS-2023-04349 | F11: Copefrut | G11: Lufthansa | H11: AIRFREIGHT | I11: Nhava Sheva | J11: 01.12.2022 | K11: Intertek, IND | M11: Falta , AoR, harvest,
B12: Asignar a Víctor cuando sea presentable. PRESENTAR | C12: PRE-FIS-DEL-2023-12/24-2568 | D12: isidora Martinez | E12: CS-2023-04491 | F12: Gidding Cerasus S.A. | G12: Delta Air | H12: AIRFREIGHT | I12: Incheon | J12: 03.12.2022 | K12: Hyopsung | M12: ok
B13: PRESENTAR | C13: PRE-FIS-DHL-2023-11/24-2472 | D13: isidora Martinez | E13: CS-2023-04249 | F13: Agricom | H13: AIRFREIGHT | I13: Incheon | J13: 12.11.2022 | K13: not necessary | M13: OK
B14: TRASPASADO | C14: PRE-FIS-DHL-2023-11/24-2684 | D14: Isidora Martinez | E14: CS-2022-12571 | F14: David del Curto | G14: DHL | H14: AIRFREIGHT | I14: Incheon | J14: 25.11.2022 | K14: Hyopsung | M14: OK
B15: PRE-FIS-QAW-2023-01/25-2851 | C15: Thomas Chatterton | D15: 1854 | F15: Valle Maule | G15: QATAR AIRWAYS | H15: AIRFREIGHT | I15: KUALA PUMPUR | L15: 18.01.2023
A16: 24076.96 | B16: TRASPASADO | C16: PRE-FIS-DHL-2023-11/24-2338 | D16: Thomas Chatterton | E16: CS-2022-12273 | F16: Eosta | G16: DHL | H16: AIRFREIGHT | I16: Guayaquil / Amsterdam | J16: 21.11.2022 | K16: Fruit Inspection & Consultancy BV | M16: QY387 || M61002 | N16: Temperature too low and delay 42 days - Pendiente SMV para determinar monto (28.07.2022 se ha llegado a acuerdo con la naviera.) | Q16: 44959
A17: 19969.49 | B17: PRESENTAR | C17: PRE-FIS-LAN-2024-12/25-3116 | D17: Matias Farcuh | E17: CS-2024-01428 | F17: BB Trading | G17: Latam | H17: AIRFREIGHT | I17: Shanghai | J17: 12.12.2023 | K17: Teamhead | L17: Flight No.: M38495 | M17: ok | N17: Te anormal durante viaje. | O17: Blueberries | P17: 09.02.2021 | Q17: 44614
A18: 6447 | B18: PRESENTAR | C18: PRE-FIS-LAN-2024-12/25-3118 | D18: Matias Farcuh | E18: CS-2024-01429 | F18: BB Trading | G18: Latam | H18: AIRFREIGHT | I18: Shanghai | J18: 15.12.2023 | K18: Teamhead | L18: Flight No.:LA801 | M18: Falta claim notice | N18: 20.07.2023
A19: 1864.87 | B19: PRESENTAR | C19: PRE-FIS-LAN-2024-12/25-3229 | D19: Isidora Martinez | E19: CS-2024-01403 | F19: Rucaray | G19: Latam Airlines | H19: AIRFREIGHT | I19: Hong Kong | J19: 09.12.2023 | K19: Teamhead | L19: UC1400 | M19: ok | N19: 01.05.2022 | O19: NA
A20: 15724.8 | B20: PRESENTAR | C20: PRE-FIS-QAW-2024-11/25-3043 | D20: Matias Farcuh | E20: CS-2024-01398 | F20: Agricom | G20: Qatar Airways | H20: AIRFREIGHT | I20: Mumbai | J20: 30.11.2023 | K20: Intertek, IND | L20: QR8307 | M20: ok | N20: 13.10.2022 | O20: 15724.8
B21: TRASPASADO/SR | C21: PRE-FIS-ONE-2023-04/24-2753 | D21: Isidora Martinez | E21: CS-2023-05343 | F21: Altius S.A. | G21: ONE | H21: AL RIFFA | I21: Hong Kong | J21: 30.04.2023 | K21: Cott&Lambert | L21: 022E | M21: Falta Phyto, SR.
B22: SOLICITADO | C22: PRE-FIS-CMA-2023-08/23-2484 | D22: isidora Martinez | E22: CS-2022-08999 | F22: Itacu Corporation ltda. | G22: CMA CGM | H22: ALEXIS | I22: Leghorn | J22: 02.08.2022 | K22: Spolidoro | L22: 0DVCHN1MA | M22: ok
B23: PRESENTAR | C23: FIS-CMA-2023-03/25-2811 | D23: Isidora Martinez | E23: CS-2023-10459 | F23: Sunshine /GH | G23: CMA CGM | H23: ALEXIS | I23: LONDON | J23: 17.03.2023 | K23: na | N23: 28.11.2022 | O23: NA
A24: 13511.27 | B24: PRESENTAR | C24: PRE-FIS-CMA-2024-04/25-3081 | D24: Thomas Chatterton | E24: CS-2024-04105 | F24: Itacu Corporation ltda. | G24: CMA CGM | H24: ALEXIS | I24: Jeddah | J24: 11.04.2024 | K24: SISLA | L24: 0DVHGN1MA | M24: ok | N24: 30.06.2022 | O24: NA
A25: 41574.73 | B25: PRESENTAR | C25: PRE-FIS-SEA-2022-05/22-1448 | D25: Jan Klempau | E25: CS-2022-00531 | F25: Robinson Fresh | G25: Seaboard Marine | H25: ALGOL | I25: Miami | J25: 13.05.2021 | K25: PCCC | L25: Falta TR,PC. | M25: Delay 7 días + TEMPERATURE | N25: Delay 10 days and Temperature sobre 2°C (0C°) | Q25: 44728
A26: 6186.29 | B26: PRESENTAR | C26: FIS-SEA-2022-05/22-1449 | D26: Jan Klempau | E26: CS-2022-00532 | F26: Robinson Fresh | G26: Seaboard Marine | H26: ALGOL | I26: Miami | J26: 13.05.2021 | K26: PCCC | L26: OK | M26: Delay 7 días | N26: Delay 14-Mixed condition, and part of the condition problems are likely related condition of the fruit upon loading of the container, the extended voyage could be considered a contributory factor exacerbating the problems found on arrival / 1. 04.08.2022(CA) Reviewed - Request time extension. (TE). | O26: Avocados | P26: 08.07.2021 | Q26: 20.08.2022
A27: 30918.34 | B27: extrajudicial | C27: FIS-MSC-2022-02/23-1953 | D27: Isidora Martinez | E27: CS-2022-02333 | F27: Sunshine Peru | G27: MSC | H27: ALGOL | I27: Paita/ | J27: 06.02.2022 | K27: PCCC | L27: 21023NR | M27: ok | N27: Temperature incidents and the transhipment periods - thet° incidents should be considered a contributory factor exacerbating the problems found on arrival, and therefore merely to be considered as potentially damage-inducing / 1. 04.08.2022(CA) Reviewed - Request time extension. (TE). | O27: Avocados | P27: 29.07.2021 | Q27: 29.08.2022
A28: 25707.82 | C28: PRE-FIS-ONE-2021-01/22-1044 | D28: Ljubinka Basic | E28: CS-2021-50625 | F28: Frusan Agro | G28: ONE | H28: ALIOTH | I28: Los Angeles | J28: 21.01.2021 | K28: PCCC | L28: ok | M28: Delay 13 dias ETA 08.01 descargó 12.01 | N28: Abnormal temperature (The Temperature Recorders indicated the carrying temperature was abnormal during the period of sea transportation) | O28: Grapes | P28: 03.03.2021 | Q28: 45338
A29: 41143.33 | B29: Thomas Chatterton | C29: 1892 | D29: PRE-FIS-KLM-2023-02/05-2855 | E29: Valle Maule | F29: KLM | G29: AIRFREIGHT | H29: Amsterdam | I29: 13.02.2023 | L29: OK | N29: Temperature issue & total loss | O29: Plums | P29: 05.04.2022 | Q29: 45387
A30: 24209.89 | B30: Thomas Chatterton | C30: 1891 | D30: PRE-FIS-KLM-2023-02/05-2854 | E30: Valle Maule | F30: KLM | G30: AIRFREIGHT | H30: Amsterdam | I30: 13.02.2023 | L30: OK | N30: temperature variation during transit and transit delay about 22 days than the normal transit period. | O30: Kiwis | P30: 16.06.2021 | Q30: 45160
B31: TRASPASADO | C31: PRE-FIS-COS-2023-01/25-2488(EX) | D31: Victor Vilches | E31: CS-2023-04654 | F31: Prize | G31: COSCO | H31: ANTHEA Y | I31: Nansha | J31: 15.01.2023 | K31: Teamhead | L31: 033W | M31: ok | N31: 06.12.2021
B32: PRESENTAR | C32: PRE-FIS-CMA-2022-02/23-2104 | D32: Isidora Martinez | E32: CS-2022-09086 | F32: Frusan Agro | G32: CMA CGM | H32: AS PATRIA | I32: Paita/Hong Kong | J32: 19.02.2022 | K32: Teamhead | L32: 0VF78N1MA | M32: Falta notificación naviera, reporte consolidado con temperaturas, reporte de calidad | N32: 31.08.2021
B33: TRASPASADO | C33: FIS-HLL-2022-03/23-1701 | D33: Isidora Martinez | E33: CS-2022-05351 | F33: Robinson Fresh | G33: Hapag Lloyd | H33: AS PATRIA | I33: Port Everglades | J33: 04.03.2022 | K33: PCCC | L33: 202N | M33: Falta Stuffing R., DUS, IVV, | N33: 13.01.2022
B34: PRESENTAR | C34: PRE-FIS-CC-2023-02/25-2827 | D34: Thomas Chatterton | E34: CS-2023-04137 | F34: Quintay | G34: Cool Carriers | H34: BALTIC LADY | I34: Gloucester City | J34: 08.02.2023 | K34: PCCC | L34: EC070 | M34: OK | N34: 23.03.2022
B35: PRESENTAR | C35: PRE-FIS-HLL-2024-02/25-3239 | D35: Thomas Chatterton | E35: CS-2024-03069 | F35: ROVEG | G35: Hapag Lloyd | H35: BREMERHAVEN EXPRESS | I35: Hamburg | J35: 23.02.2024 | K35: Fruit Inspection & Consultancy BV | L35: NA402R | M35: Falta sr | N35: 27.07.2021
B36: PRESENTAR | C36: PRE-FIS-FTR-2024-12/24-3019 | D36: Isidora Martinez | E36: CS-2023-11755 | F36: ROVEG | H36: BREMERHAVEN EXPRESS | I36: Rotterdam | J36: 06.12.2023 | K36: Fruit Inspection & Consultancy BV | L36: NA344R | M36: Falta SR | N36: 20.07.2021
B37: TRASPASADO | C37: PRE-FIS-COS-2023-07/25-2867 (EX) | D37: Matias Farcuh | E37: CS-2023-08136 | F37: Copefrut | G37: COSCO | H37: BUENOS AIRES EXPRESS | I37: Rotterdam | J37: 25.07.2023 | K37: Fruit Inspection & Consultancy BV | L37: 3217N | M37: Falta Stuffing, SR. se requiere liquidación del embarque 2958 que se usó como comparativo | N37: 24.05.2021
C38: FIS-CMA-2021-08/21-0594 | D38: Ljubinka Basic | E38: cs2020-07404 | F38: Huarmey | G38: CMA CGM | H38: CALLAO EXPRESS | I38: Port Everglades | J38: 31.08.2020 | L38: 2 reminder 11.06 | M38: Delay 7 días, daño físico carga. | N38: 27.07.2021
B39: A DISCUTIR/ TRASPASADO/ Solicitado Plataforma/ Lunes 25 de julio | C39: FIS-CMA-2022-07/23-1492 | D39: Matías | E39: CS-2021-56120 | F39: FRUSAN | G39: CMA CGM | H39: CALLAO EXPRESS | I39: Rotterdam | J39: 16.07.2021 | K39: Fruit Inspection & Consultancy BV | L39: 129N | M39: Falta SR ( considerando que Lia indica caso no relacionado a transporte por lo que caso se cerraría. Este caso se debe indicar que estaba traspasado para exhibición a Matias) 07.07.2022 Caso se encuentra traspasado para exhibición, posibilidad de continuar sin mostrar reporte. | N39: 28.05.2021
B40: PRESENTAR | C40: PRE-FIS-CMA-2023-04/25-2751 | D40: Isidora Martinez | E40: CS-2023-05301 | F40: Greenvic | G40: CMA CGM | H40: CALLAO EXPRESS | I40: Algeciras | J40: 24.04.2023 | K40: Eurovet | L40: 206N | M40: ok | N40: 07.08.2021
B41: PRESENTAR | C41: PRE-FIS-CMA-2024-01/26-3154 | D41: Thomas Chatterton | E41: CS-2024-01412 | F41: Propal | G41: CMA CGM | H41: CALLAO EXPRESS | I41: Rotterdam | J41: 30.01.2024 | K41: Fruit Inspection & Consultancy BV | L41: 246N | M41: Falta SR | N41: 14.03.2022
B42: TRASPASADO | C42: PRE-FIS-HBS-2024-04/24-2949 | D42: Isidora Martinez | E42: CS-2023-04114 | F42: ROVEG | G42: Hamburg Süd | H42: CAP SAN ARTEMISSIO | I42: Rotterdam | J42: 07.04.2023 | K42: Fruit Inspection & Consultancy BV | L42: 310N | M42: ok | N42: 17.06.2022
B43: PRESENTAR | C43: PRE-FIS-MAE-2024-04/25-3165 | D43: Thomas Chatterton | E43: CS-2024-05426 | F43: Pilz-Schindler | G43: Maersk Line | H43: CAP SAN ARTEMISSIO | I43: Hamburg | J43: 20.04.2024 | K43: Berner | L43: 409N | M43: ok | N43: 09.02.2022
B44: PRESENTAR | C44: PRE-FIS-MAE-2024-04/25-3259 | D44: Thomas Chatterton | E44: CS-2024-04591 | F44: ROVEG | G44: Maersk | H44: CAP SAN LAZARO | I44: Rotterdam | J44: 22.04.2024 | K44: Fruit Inspection & Consultancy BV | L44: 409W | M44: ok ( no existe fotos proceso stuffing, repacking invoice) | N44: 21.05.2021
B45: TRASPASADO/Jueves 11 de agosto por correo | C45: FIS-MAE-2022-08/22-1803 | D45: Isidora | E45: CS-2021-56069 | F45: ROVEG | G45: Maersk | H45: CAP SAN MALEAS | I45: Rotterdam | J45: 20.08.2021 | K45: Fruit Inspection & Consultancy BV | L45: 129N | M45: SMV, CO | N45: 05.04.2022
B46: TRASPASADO/SR | C46: PRE-FIS-MSC-2022-04/23-1999 | D46: Isidora Martinez | E46: CS-2022-05390 | F46: Asica Farms SAC | G46: MSC | H46: CAPE AKRITAS | I46: London Gateway | J46: 10.04.2022 | K46: MMS | M46: ok | N46: 15.02.2022
B47: PRESENTAR | C47: PRE-FIS-MSC-2023-03/25-2688 | D47: Thomas Chatterton | E47: CS-2023-04159 | F47: Geofrut | G47: MSC | H47: CAPE AKRITAS | I47: Rotterdam | J47: 25.03.2023 | K47: Fruit Inspection & Consultancy BV | L47: NX305R | M47: ok | N47: 03.12.2021
B48: PRESENTAR | C48: PRE-FIS-CMA-2024-05/26-3182 | D48: Isidora Martinez | E48: CS-2024-04596 | F48: Verfrut | G48: CMA CGM | H48: CAPE QUEST | I48: Philadelphia | J48: 01.05.2024 | K48: PCCC | L48: 0LIE7N1MA | N48: 31.12.2021
B49: TRASPASADO | C49: PRE-FIS-MSC-2022-01/24-2229(EX) | D49: Victor Vilches | E49: CS-2022-05465 | F49: Bamenex S.A. | G49: MSC | H49: CAPE TAINARO | I49: Valparaiso/Rotterdam | J49: 21.01.2022 | K49: Fruit Inspection & Consultancy BV | L49: NX147R | M49: OK | N49: 09.09.2021
B50: TRASPASADO | C50: PRE-FIS-HBS-2023-03/24-2380 | D50: Camila Sanhueza | E50: CS-2022-09578 | F50: Geofrut | G50: Hamburg Süd | H50: CAROLINE MAERSK | I50: Hong Kong | J50: 16.03.2022 | K50: Teamhead | L50: 205W | M50: Falta Export invoice, Loading report, Phyto & Origin, DUS, IVV. | N50: 11.03.2023
B51: PRESENTAR | C51: PRE-FIS-MAE-2024-03/26-2957 | D51: Thomas Chatterton | E51: CS-2024-03062 | F51: A5 Export | G51: Maersk | H51: CAROLINE MAERSK | I51: Hong Kong | J51: 11.03.2024 | K51: Teamhead | L51: 405W | M51: ok | N51: 24.12.2021
B52: PRESENTAR | C52: PRE-FIS-MAE-2024-06/26-3178 | D52: Thomas Chatterton | E52: CS-2024-07035 | F52: Rio Blanco SpA | G52: Maersk Line | H52: CAROLINE MAERSK | I52: Port Kelang | J52: 16.06.2024 | K52: Harper Wira | L52: 416W | M52: ok | N52: 25.10.2021
B53: PRESENTAR | C53: PRE-FIS-HLL-2022-04/23-1455(EX) | D53: Matias | E53: CS-2021-53389 | F53: FRUSAN | G53: Hapag Lloyd | H53: CARTAGENA EXPRESS | I53: Leghorn | J53: 28.04.2021 | K53: Spolidoro | M53: Falta AoR, DUS | N53: 07.01.2022
B54: TRASPASADO | C54: PRE-FIS-CMA-2022-07/23-2298 | D54: Isidora Martinez | E54: CS-2022-09062 | F54: Frutos Tropicales Europe BV | G54: CMA CGM | H54: CARTAGENA EXPRESS | I54: Rotterdam | J54: 06.07.2022 | K54: Fruit Inspection & Consultancy BV | L54: 0WCC0N1MA (ICA BL Ref: ICLCAURTM20608) | M54: ok (reporte consolidado con temperaturas no disponible) | N54: 29.03.2023
B55: TRASPASADO | C55: FIS-HLL-2022-10/22-1948 | D55: Victor Vilches | E55: cs2020-09361 | F55: Propal | G55: Hapag Lloyd | H55: CARTAGENA EXPRESS | I55: London Gateway | J55: 16.10.2020 | K55: Fresh Produce | L55: 0133N | M55: Ok | N55: 08.12.2021
B56: TRASPASADO | C56: PRE-FIS-HLL-2022-03/24-1871 | D56: Matias Farcuh | E56: CS-2022-05195 | F56: David del Curto | G56: Hapag Lloyd | H56: CARTAGENA EXPRESS | I56: San Antonio/New York | J56: 08.03.2022 | K56: PCCC | L56: 1252N | M56: Export invoice, Notificación naviera | N56: Se ve un alza de temperatura durante viaje + delay de 9 días.
B57: PRESENTAR. EX. | C57: PRE-FIS-HLL-2023-03/24-2370(EX) | D57: Francisco Meneses | E57: CS-2022-04922 | F57: Valle Maule | G57: Hapag Lloyd | H57: CARTAGENA EXPRESS | I57: Rotterdam | J57: 03.03.2022 | K57: Fruit Inspection & Consultancy BV | L57: 1252N | M57: Falta SR | N57: delay 5 días
B58: Traspasado | C58: PRE-FIS-HLL-2021-06/22-0850(EX) | D58: Matias | E58: cs2020-05390 | F58: Copefrut | G58: Hapag Lloyd | H58: CAUQUENES | I58: Keelung | J58: 30.06.2020 | K58: Teamhead | L58: Falta SR | M58: Se indica daño de origen. Termógrafo muestra te irregular. | N58: 05.05.2022
B59: TRASPASADO/ Nota de credito es por$242,0000, se indemnizaron $8.500. /Solicitado Plataforma/martes 23 de agosto por correo | C59: FIS-HLL-2021-10/22-0853 | D59: Jan Klempau | E59: cs2020-09356 | F59: Copefrut | G59: Hapag Lloyd | H59: CAUQUENES | I59: Port Kelang | J59: 13.10.2020 | K59: Harper Wira | L59: 2027W | M59: Falta reporte consolidado con temperaturas, DUS, IVV, reporte de calidad | N59: 20.06.2022
B60: TRASPASADO | C60: PRE-FIS-HLL-2022-04/24-2201 (EX) | D60: Camila Sanhueza | E60: CS-2022-08748 | F60: Subsole | G60: Hapag Lloyd | H60: CAUQUENES | I60: Valparaiso/Nansha | J60: 07.04.2022 | K60: Teamhead | L60: 2201W | M60: Falta AoR | N60: 27.12.2021
B61: TRASPASADO | C61: PRE-FIS-ONE-2022-03/24-2021(EX) | D61: Isidora Martinez | F61: Prize | G61: ONE | H61: CAUQUENES | I61: Hong Kong | J61: 21.03.2022 | K61: Teamhead | L61: 2201W | M61: Falta , BO, Stuffing R., HC, SMV, QC R. IVV | N61: 03.10.2021
B62: TRASPASADO | C62: FIS-HLL-2021-02/22-0652 | D62: Matias Farcuh | E62: cs2020-01523 | F62: rucaray | G62: Hapag Lloyd | H62: CAUQUENES | I62: Hong Kong | J62: 43876 | M62: Falta SMV | N62: 22.12.2022
B63: TRASPASADO | C63: PRE-FIS-HLL-2022-04/24-2269 | D63: Camila Sanhueza | E63: CS-2022-11867 | F63: Verfrut | G63: Hapag Lloyd | H63: CAUQUENES | I63: Hong Kong | J63: 05.04.2022 | K63: Teamhead | L63: 2201W | M63: OK | N63: 21.03.2022
B64: TRASPASADO | C64: PRE-FIS-HLL-2022-01/24-1992 | D64: Nicolas Aravena | E64: CS-2022-02311 | F64: David del Curto | G64: Hapag Lloyd | H64: CAUQUENES | I64: Valparaiso/Busan | J64: 20.01.2022 | K64: Hyopsung | L64: 2141W | M64: ok
B65: TRASPASADO | C65: PRE-FIS-HLL-2022-04/24-1812 | D65: Barbara Choque | F65: CYD | G65: Hapag Lloyd | H65: CAUQUENES | I65: Yantian | J65: 07.04.2022 | L65: 2201W | M65: OK | N65: 27.12.2021
B66: TRASPASADO | C66: PRE-FIS-HLL-2023-05/25-2720 | D66: Thomas Chatterton | E66: CS-2023-07085 | F66: CFN | G66: Hapag Lloyd | H66: CAUQUENES | I66: Nhava Sheva | J66: 25.05.2023 | K66: Intertek, IND | L66: 2308W | M66: ok
B67: TRASPASADO | C67: PRE-FIS-HLL-2021-02/22-0653(C19) | D67: Victor Vilches | E67: cs2020-02731 | F67: fortunep | G67: Hapag Lloyd | H67: CAUQUENES | I67: Hong Kong | J67: 43877 | M67: dispo. Subro cnee
B68: TRASPASADO | C68: PRE-FIS-HLL-2021-02/22-0654(C19) | D68: Victor Vilches | E68: cs2020-02233 | F68: fortunep | G68: Hapag Lloyd | H68: CAUQUENES | I68: Hong Kong | J68: 43877 | K68: Teamhead | M68: dispo. Subro cnee
B69: TRASPASADO | C69: PRE-FIS-HLL-2021-02/22-0655(C19) | D69: Victor Vilches | E69: cs2020-02232 | F69: fortunep | G69: Hapag Lloyd | H69: CAUQUENES | I69: Hong Kong | J69: 43877 | K69: Teamhead | M69: dispo. Subro cnee
B70: TRASPASADO | C70: PRE-FIS-MSC-2024-02/25-2895 | D70: Thomas Chatterton | E70: CS-2023-04678 | F70: Prize | G70: MSC | H70: CAUQUENES | I70: Keelung | J70: 17.02.2023 | K70: Teamhead | L70: 2249W | M70: ok
C71: FIS-ONE-2021-10/21-0820 | D71: Ljubinka Basic | E71: cs2020-01293 | F71: A5 Export | G71: ONE | H71: CAUTIN | I71: Shanghai | J71: 03.12.2019 | K71: no surveyor involved | L71: Falta SMV No se hizo inspección. | M71: Carga roleada generando 1 semana de delay y posteriormente segunda nave tuvo demoras en operaciones. Cliente retira unidad y vende en mercado local.
B72: PRESENTAR / NOTIFICAR Y NEGOCIAR CON LESLIE RIGHT AWAY | C72: PRE-FIS-HLL-2022-04/24-2210 | D72: Matias Farcuh | E72: CS-2022-08750 | F72: Subsole | G72: Hapag Lloyd | H72: CAUTIN | I72: Valparaiso/Hong Kong | J72: 13.04.2022 | K72: Teamhead | L72: 2204W | M72: Falta CLAIM NOTICE, SR
A73: 88252.87 | B73: PRESENTAR | C73: PRE-FIS-ONE-2022-01/24-1649 | D73: Isidora Martinez | E73: CS-2022-05180 | F73: Copefrut | G73: ONE | H73: CAUTIN | I73: Hong Kong | J73: 26.01.2022 | K73: Teamhead | L73: 2144W | M73: ok | N73: Delay before departure, Vessel suffered engine problem, vienen Certificados de Destrucción costo de 5.659,20 | O73: Bananas | P73: 02.11.2021 | Q73: 44891
A74: 111301.27 | B74: TRASPASADO | C74: FIS-HLL-2022-01/24-1811 | D74: Victor Vilches | E74: CS-2022-03104 | F74: Greenex SpA | G74: Hapag Lloyd | H74: CAUTIN | I74: Hong Kong | J74: 26.01.2022 | K74: Teamhead | L74: 2144W | M74: OK | N74: 03.06.2022
A75: 27494.43 | B75: TRASPASADO | C75: PRE-FIS-ONE-2022-01/24-1669 | D75: Camila Sanhueza | E75: CS-2022-05172 | F75: Copefrut | G75: ONE | H75: CAUTIN | I75: Hong Kong | J75: 26.01.2022 | K75: Teamhead | L75: 2144W | M75: OK | N75: Falla CA - controlled atmosphere system malfunction/BL requested controlled atmospheric settings are: CO 6%; O 5%. | O75: Mangoes | P75: 03.10.2021 | Q75: 44848 | R75: AGREGAR SALES ACCOUNT
B76: TRASPASADO | C76: PRE-FIS-ONE-2022-01/24-1644 | D76: Isidora Martinez | E76: CS-2022-02299 | F76: Copefrut | G76: ONE | H76: CAUTIN | I76: Hong Kong | J76: 22.01.2022 | K76: Teamhead | L76: 2144W | M76: Falta notificación naviera, export invoice | N76: 01.04.2023
B77: TRASPASADO | C77: FIS-MAE-2021-05/22-0844 | D77: Moritz Dimter | E77: cs2020-05361 | F77: Agricom | G77: Maersk Line | H77: CCNI ANGOL | I77: Auckland | J77: 08.05.2020 | K77: Other | M77: ok | N77: 01.12.2021
A78: 35398.34 | B78: TRASPASADO | C78: PRE-FIS-UWL-2023-12/23-2423 | D78: Isidora Martinez | E78: CS-2023-02689 | F78: Monteco / Sun Fresh | G78: UWL | H78: CHANGSHA | I78: Hai Phòng | J78: 12.12.2022 | K78: Baoviet | L78: 2207W | M78: ok | N78: Delay 12 days/Poor/total loss - Attending parties agreed that the consignment would be destroyed as it was no longer suitable for human consumption. - • Temperature incident to 29°C between start ± 20/08/2021 til 08/09/2021. | O78: Avocados | P78: 20.08.2021 | Q78: 22.09.2022
B79: PRESENTAR | C79: PRE-FIS-MAE-2021-01/23-0815 | D79: Moritz Dimter | E79: CS-2021-51213 | F79: Rucaray | G79: Maersk Line | H79: CHARLOTTE MAERSK | I79: Hong Kong | J79: 20.01.2021 | K79: Teamhead | M79: OK
B80: PRESENTAR | C80: PRE-FIS-MAE-2024-02/26-2971 | D80: Isidora Martinez | E80: CS-2024-01541 | F80: San Andres | G80: Maersk | H80: CHARLOTTE MAERSK | I80: Nansha | J80: 03.02.2024 | K80: Teamhead | L80: 352W | M80: ok | N80: 16.04.2022 | O80: 10700
A81: 10.974,13$ | B81: TRASPASADO/Solicitado Plataforma/martes 30 de agosto por correo | C81: FIS-HLL-2022-04/24-1592(EX) | D81: Matias Farcuh | F81: David del Curto | G81: Hapag Lloyd | H81: CISNES | I81: Hong Kong | J81: 05.04.2022 | K81: Teamhead | L81: 2203W | M81: ok | N81: 30.08.2022
A82: 87107 | B82: TRASPASADO | C82: PRE-FIS-HLL-2021-04/22-0889 | D82: Rafael San Martin | E82: cs2020-03215 | F82: Lo Garces | G82: Hapag Lloyd | H82: CISNES | I82: Hong Kong | J82: 10.04.2020 | K82: Teamhead | M82: ok | N82: Based on the condition of cargo, we can estimate that the problem was caused by an inadequate temperature exposure during the traveling time. High temperatures of +5.0C accelerate the ripening process and damaged the condition of the fruit in an adverse manner. The most common damage of the cargo is rotten units and soft pulp (Recibido caso 21 de julio) | O82: Nectarines-peaches-plums | P82: 01.08.2021 | Q82: 25.08.2022
A83: 48068.8 | B83: TRASPASADO | C83: PRE-FIS-HLL-2021-04/22-0854 | D83: Rafael San Martin | E83: cs2020-03239 | F83: Compania Frigorifica del Norte | G83: Hapag Lloyd | H83: CISNES | I83: Shanghai | J83: 15.04.2020 | K83: Teamhead | M83: ok | N83: 13.10.2022 | O83: NA
A84: 15417.14 | B84: TRASPASADO / Cliente proporciona subro con monto en rojo (indemnizado figuran 500 dolares menos) pero acorde a SMV de Kelly el monto serìa de 2.690,44USD a reclamar. Estamos solicitando SMV a asegurado. | C84: FIS-ONE-2021-05/23-1325 | D84: Isidora Martínez | E84: CS-2021-56240 | F84: Noble Fruit | G84: ONE | H84: CISNES | I84: Valparaíso/Hong Kong | J84: 22.05.2021 | K84: Teamhead | L84: 2110W | M84: DUS, IVV | N84: Temperature Issues (Plazo para conseguir documentos principios julio, sino se discute en reunión 14.07.2022) ( Se discute ya que no se encuentra con doc necesaria para determinar perdida, caso cercano a presescribir, se indemnizaron 5.000 USD) - 30.06.2022 Mandar correo a Isi con solicitud de documentos a Karina para determinar si vale la pena continuar con el recupero. ( Reunión 21-07.2022 se sigue insistiendo por documentación y sino caso se deja morir.)(Reunión 11,08,2022 (CA) Transfer to Matias Farcuh to present the case and notify, while Isidora Martinez gets TE, the judicial part is left open.) | O84: Grapes | P84: 07.08.2021 | Q84: 44802
A85: 68228 | B85: Si toca p&i complejo se pasa a judicial | C85: PRE-FIS-ONE-2021-03/23-0795 | D85: Camila Sanhueza | E85: CS-2021-51209 | F85: Agricom | G85: ONE | H85: CISNES | I85: Valparaiso/Busan | J85: 19.03.2021 | K85: Hyopsung | L85: 2051W | M85: ok | N85: Temperature issues - According to the temperature recorder that accompanied the cargo, damage must be attributed to the lack of cold or refrigeration stoppage between 26-27/04/2022 and 04/05/2022.- Total Loss | O85: Grapes | P85: 22.04.2023 | Q85: 45404
A86: 17876,27eur | B86: ya presentado | C86: PRE-FIS-ONE-2023-02/25-2570 | D86: Isidora Martinez | E86: CS-2023-04495 | F86: Gidding Cerasus S.A. | G86: ONE | H86: CISNES | I86: Hong Kong | J86: 03.02.2023 | K86: Teamhead | L86: 2247W | M86: ok | N86: 09.07.2022 | O86: 17.876,27EUR | P86: FUE presentado con el FIS N° FIS-MSC-2021-07/22-1059, pero corresponde HLL
A87: 24999.99 | B87: TRASPASADO | C87: PRE-FIS-HLL-2022-08/23-1656 | D87: Isidora Martinez | E87: CS-2021-56192 | F87: Propal | G87: Hapag Lloyd | H87: CISNES | I87: Shanghai | J87: 29.08.2021 | K87: Teamhead | L87: 2121W | M87: Falta AoR | N87: 27.05.2023
A88: 27428.38 | B88: TRASPASADO | C88: PRE-FIS-ONE-2021-04/22-0838 | D88: Matias Farcuh | E88: cs2020-03229 | F88: BB Trading | G88: ONE | H88: CISNES | I88: Hong Kong | J88: 10.04.2020 | K88: Teamhead | M88: Falta AoR. Nota crédito 28.091,00USD | N88: Perdida Total / delay 22 días, TT más de 60 días. | O88: Pears | P88: 23.05.2021 | Q88: 45127
A89: 44590.49 | B89: TRASPASADO | C89: PRE-FIS-HLL-2022-01/24-1839 | D89: Isidora Martinez | E89: CS-2022-05260 | F89: Lo Garces | G89: Hapag Lloyd | H89: CISNES | I89: Hong Kong | J89: 17.01.2022 | K89: Teamhead | L89: 2143W | M89: ok | N89: To high temperature during the sea carriage | O89: Kiwis | P89: 30,06,2021 | Q89: 45127
A90: 12932.25 | B90: TRASPASADO | C90: PRE-FIS-ONE-2021-04/22-0837 | D90: Nicolas Aravena | E90: cs2020-03553 | F90: BB Trading | G90: ONE | H90: CISNES | I90: Hong Kong | J90: 09.04.2020 | K90: Teamhead | M90: ok | N90: Delay 23 days of Cnee. due to strike and rioting & Temperature issues (-0,5 °C) | O90: Grapes-Plums | P90: 24.04.2021 | Q90: 45050
A91: 24258.4 | B91: 89774.67 | C91: PRE-FIS-ONE-2023-02/25-2713 | D91: Isidora Martinez | E91: CS-2023-04230 | F91: Agricom | G91: ONE | H91: CISNES | I91: Hong Kong | J91: 03.02.2023 | K91: Teamhead | L91: 2247W | M91: ok | N91: Delay 31 days and problems to the condition and quality of the product | O91: Grapes | P91: 23.04.2021 | Q91: 45050
A92: 16188.72 | B92: TRASPASADO/ Solicitado Plataforma/martes 19 de julio | C92: FIS-HLL-2022-02/23-1410(SDA) | D92: Francisco Menses | E92: CS-2021-50651 | F92: Gidding Cerasus S.A. | G92: Hapag Lloyd | H92: CMA CGM ARKANSAS | I92: Rotterdam | J92: 04.02.2021 | K92: MMS | M92: OK | N92: (Se presentan, ante primer rechazo se cierran)Delay 31 days due to strike and rioting-Problems in the condition and quality of the product *Puede ser por Huelga en POD | O92: Apples | P92: 24.04.2021 | Q92: 45050
A93: 18766.82 | B93: TRASPASADO/SR | C93: PRE-FIS-HLL-2023-06/24-2661 | D93: Isidora Martinez | E93: CS-2022-12279 | F93: Lo Garces | G93: Hapag Lloyd | H93: CMA CGM ARKANSAS | I93: Rotterdam | J93: 21.06.2022 | K93: McLeans | L93: 2216N | M93: Falta AoR, booking, SMV, harvest | N93: (Se presentan, ante primer rechazo se cierran)Delay 31 days due to strike and rioting and temperatures Issues (Brotytis/ quality of the product) *Puede ser por Huelga en POD | O93: Grapes | P93: 23.04.2021 | Q93: 45050
A94: 39253 | B94: TRASPASADO | C94: PRE-FIS-HLL-2022-04/23-1451(EX) | D94: Nicolas Aravena | E94: CS-2021-53385 | F94: FRUSAN | G94: Hapag Lloyd | H94: CMA CGM ARKANSAS | I94: Leghorn | J94: 14.04.2021 | K94: Spolidoro | M94: Falta DUS | N94: Delay y problema condición fruta de origen | O94: plums | P94: 24.04.2021 | Q94: 45050
A95: 23428.2 | B95: TRASPASADO | C95: PRE-FIS-HLL-2022-04/23-1452(EX) | D95: Nicolas Aravena | E95: CS-2021-56113 | F95: FRUSAN | G95: Hapag Lloyd | H95: CMA CGM ARKANSAS | I95: Leghorn | J95: 14.04.2021 | K95: Spolidoro | M95: Falta BL original,DUS | N95: Filtración gases atmosfera, contenedor mal funcionamiento- Due to the gases found in the container for which lead to the loss of the necessary atmosphere to sound condition of avocados | O95: Avocados | P95: 29.10.2021 | Q95: 45228
B96: TRASPASADO | C96: FIS-COS-2022-02/24-1599(EX) | D96: Matias Farcuh | E96: CS-2022-05009 | F96: Agricom | G96: COSCO | H96: CMA CGM ARKANSAS | I96: Rotterdam | J96: 20.02.2022 | K96: McLeans | L96: 125N | M96: Ok | N96: 21 Delay on arrival - Due to to long transit time our customer remarked that quality and storage potential of the fruit might be affected due to this issue during transit. | O96: Blueberries | P96: 02.10.2021 | Q96: 15.11.2022
A97: 30856.49 | B97: TRASPASADO | C97: PRE-FIS-CMA-2023-05/25-2781 | D97: Thomas Chatterton | E97: CS-2023-07075 | F97: FRUSAN | G97: CMA CGM | H97: CMA CGM BALBOA | I97: Leghorn | J97: 14.05.2023 | K97: Spolidoro | L97: 0L100N1MA | M97: Falta Booking, Stuffing, DUS, IVV | N97: Delay 37 días (Reunión 21.07.2022 En caso se pasen a judicial se deben manejar en conjunto 1563) | O97: Grapes | P97: 01.03.2021 | Q97: 45049
A98: 13666.71 | B98: PRESENTAR | C98: PRE-FIS-CMA-2024-01/26-3066 | D98: Ljubinka Basic | E98: CS-2024-01343 | F98: Prize | G98: CMA CGM | H98: CMA CGM BEIRA | I98: Port Everglades | J98: 23.01.2024 | K98: PCCC | L98: 0LID3N1MA | M98: ok | N98: Delay before departure-Packed time too long- ETA 11.06.2021 - 04.08.2022 (CA) Reviewed - For delay the damage does not correspond, given the type of fruit, if there are temperature variations, data logger will be checked. | O98: Kiwis | P98: 05.06.2021 | Q98: 45114
A99: 36796.5 | B99: TRASPASADO | C99: PRE-FIS-CMA-2023-08/24-2798 | D99: Camila Sanhueza | E99: CS-2023-08143 | F99: Fairtrasa | G99: CMA CGM | H99: CMA CGM CARL ANTOINE | I99: Rotterdam | J99: 17.08.2023 | K99: Fruit Inspection & Consultancy BV | L99: 0WCF8N1MA | M99: Falta Tracking. | N99: Container malfunction and elevated transit /Disposal | O99: Mangoes | P99: 17.09.2021 | Q99: 44836
A100: 61399.54 | B100: TRASPASADO/SR | C100: PRE-FIS-BAL-2023-02/25-2431 | D100: Thomas Chatterton | E100: CS-2023-02688 | F100: Fairtrasa | G100: Blue Anchor Line | H100: CMA CGM CARL ANTOINE | I100: Rotterdam | J100: 01.02.2023 | K100: Fruit Inspection & Consultancy BV | L100: 0WCDON1MA | M100: Stuffing report with temperatures, SMV (comparative liquidation), SR
...

Sheet Subsole
A1: Claim Subsole | B1: Claim NC | C1: Claim amount SMV | D1: Id Plataforma | E1: Reference No | F1: Claim Handler | G1: Ref | H1: Handler | I1: Container | J1: Assured | K1: Opponent | L1: Vessel | M1: Place of Discharge | N1: Date of Discharge | O1: Surveyorco | P1: Voyage | Q1: Status | R1: Summary | S1: Commodity | T1: Harvest Date | U1: Date of Loading | V1: TB
A2: 21640.62 | B2: 36670 | C2: NA | D2: 32125 | G2: FIS/SUB-HLL-2025-04/27-4179 | H2: Thomas Chatterton | I2: HLBU9238859 | J2: Subsole | K2: Hapag Lloyd | L2: Seaspan Raptor | M2: Valparaiso | N2: Keelung | O2: Teamhead | P2: 2501W | Q2: Ok | R2: Delay, según Kelly de +2 semanas | S2: Grapes | T2: 18.02.2025 | U2: 28.02.2025 | V2: 09.04.2027
A3: 20959.2 | B3: 23901.04 | C3: NA | D3: 32214 | G3: FIS/SUB-HLL-2025-04/27-4180 | H3: Thomas Chatterton | I3: HLBU9757900 | J3: Subsole | K3: Hapag Lloyd | L3: Seaspan Raptor | M3: Valparaiso | N3: Keelung | O3: Teamhead | P3: 2501W | Q3: Ok | R3: Delay, según Kelly de +2 semanas | S3: Grapes | T3: 13.02.2025 | U3: 28.02.2025 | V3: 10.04.2027
A4: 42066 | B4: 20983.98 | C4: NA | D4: 32171 | G4: FIS/SUB-HLL-2025-04/27-4181 | H4: Thomas Chatterton | I4: HLBU9973215 | J4: Subsole | K4: Hapag Lloyd | L4: Seaspan Raptor | M4: Valparaiso | N4: Keelung | O4: Teamhead | P4: 2501W | Q4: Ok | R4: Delay, según Kelly de +2 semanas | S4: Grapes | T4: 11.02.2025 | U4: 28.02.2025 | V4: 09.04.2027
A5: 42059.36 | B5: 20983.98 | C5: NA | D5: 32172 | G5: FIS/SUB-HLL-2025-04/27-4182 | H5: Thomas Chatterton | I5: HLBU9781104 | J5: Subsole | K5: Hapag Lloyd | L5: Seaspan Raptor | M5: Valparaiso | N5: Keelung | O5: Teamhead | P5: 2501W | Q5: Ok | R5: Delay, según Kelly de +2 semanas | S5: Grapes | T5: 11.02.2025 | U5: 28.02.2025 | V5: 10.04.2027
A6: 21998.96 | B6: 36860 | C6: NA | D6: 32148 | G6: FIS/SUB-HLL-2025-04/27-4183 | H6: Thomas Chatterton | I6: HLBU9430753 | J6: Subsole | K6: Hapag Lloyd | L6: Seaspan Raptor | M6: Valparaiso | N6: Keelung | O6: Teamhead | P6: 2501W | Q6: Ok | R6: Delay, según Kelly de +2 semanas | S6: Grapes | T6: 18.02.2025 | U6: 28.02.2025 | V6: 09.04.2027
A8: =SUM(A2:A15) -> 153924.14 | B8: =SUM(B2:B6,C15) -> 151477.75
A14: Negociados:
A15: 5200 | B15: NA | C15: 12078.75 | D15: 32261 | G15: FIS/SUB-HLL-2025-04/27-4184 | H15: Thomas Chatterton | I15: GESU9533556 | J15: Subsole | K15: Hapag Lloyd | L15: Cosco Shipping Seine | M15: San Antonio | N15: Rotterdam | O15: FIC | P15: 5204N | Q15: Ok | R15: Delay, +20días | S15: Grapes | T15: 24.02.2025 | U15: 07.03.2025 | V15: 22.04.2027

Sheet MV SALTORO
A1: Claim amount | B1: Id | C1: Reference No | D1: Referencia ExtraJudicial | E1: Container | F1: Claim Handler | G1: CS Claim No | H1: Assured | I1: Opponent | J1: Vessel | K1: Place of Discharge | L1: Date of Discharge | M1: Surveyorco | N1: Voyage | O1: Status | P1: Summary | Q1: Commodity | R1: Date of Loading | S1: TB | T1: Participation | U1: Comentarios Reunión | V1: Itinerario MSC | W1: TT OFRECIDO | X1: TT REAL
B2: 31708 | C2: PRE-FIS/ALM-MAE-2025-02/27-3573 | D2: FIS-MAE-SALT-ALMAFR-508 | E2: MNBU4236410 | F2: Nico Núñez | G2: CS-2025-03939 | H2: Exportadora Almafruit | I2: Maersk | J2: MAERSK SALTORO | K2: Nansha | L2: 25.02.2025 | M2: Teamhead | N2: 450W | P2: delay | Q2: Cherries | R2: 25.12.2024 | S2: 25.02.2027
B3: 31965 | C3: PRE-FIS/POL-MAE-2025-02/27-3800 | D3: FIS-MAE-SALT-POLF-28 | E3: MNBU4006459 | F3: Thomas | G3: CS-2025-06000 | H3: Polar Fruit Chile | I3: Maersk | J3: MAERSK SALTORO | K3: Nansha | L3: 25.02.2025 | M3: Teamhead | N3: 450W | P3: Delay | Q3: Cherries | R3: 26.12.2024 | S3: 25.02.2027
B4: 32064 | C4: PRE-FIS/POL-MAE-2025-02/27-3806 | D4: FIS-MAE-SALT-POLF-33 | E4: MNBU9076166 | F4: Thomas | G4: CS-2025-06003 | H4: Polar Fruit Chile | I4: Maersk | J4: MAERSK SALTORO | K4: Nansha | L4: 25.02.2025 | M4: Teamhead | N4: 450W | P4: delay | Q4: Cherries | R4: 25.12.2024 | S4: 25.02.2027
B5: 31846 | C5: PRE-FIS/POL-MAE-2025-02/27-3809 | D5: FIS-MAE-SALT-POLF-26 | E5: MNBU3733216 | F5: Thomas | G5: CS-2025-03649 | H5: Polar Fruit Chile | I5: Maersk | J5: MAERSK SALTORO | K5: Nansha | L5: 25.02.2025 | M5: Teamhead | N5: 450W | P5: delay | Q5: Cherries | R5: 25.12.2024 | S5: 25.02.2027
B6: 31634 | C6: PRE-FIS/POL-MAE-2025-02/27-3811 | D6: FIS-MAE-SALT-POLF-36 | E6: MNBU3999762 | F6: Thomas | G6: CS-2025-03645 | H6: Polar Fruit Chile | I6: Maersk | J6: MAERSK SALTORO | K6: Nansha | L6: 25.02.2025 | M6: Teamhead | N6: 450W | P6: delay | Q6: Cherries | R6: 25.12.2024 | S6: 25.02.2027
B7: 31653 | C7: PRE-FIS/POL-MAE-2025-02/27-3814 | D7: FIS-MAE-SALT-POLF-30 | E7: MNBU3701029 | F7: Thomas | G7: CS-2025-03648 | H7: Polar Fruit Chile | J7: MAERSK SALTORO | K7: Nansha | L7: 25.02.2025 | M7: Teamhead | N7: 450W | R7: 26.12.2024 | S7: 25.02.2027
B8: 31934 | C8: PRE-FIS/SUB-MAE-2025-02/27-3574 | D8: FIS-MAE-SALT-SUBSOLE-98 | E8: MNBU4223602 | F8: Thomas | G8: CS-2025-04260 | H8: Subsole | I8: Maersk | J8: MAERSK SALTORO | K8: Nansha | L8: 25.02.2025 | M8: Asia IBS | N8: 450W | P8: delay | R8: 26.12.2024 | S8: 25.02.2027
B9: 32141 | C9: PRE-FIS/XSUR-MAE-02/27-3571 | D9: FIS-MAE-SALT-XSUR-06 | E9: MNBU3956117 | F9: Thomas | G9: CS-2025-03792 | H9: Xsur | I9: Maersk | J9: MAERSK SALTORO | K9: Nansha | L9: 25.02.2025 | M9: Teamhead | N9: 450W | P9: delay | Q9: cherries | R9: 25.12.2024 | S9: 25.02.2027
B10: 32150 | C10: PRE-FIS/XSUR-MAR-02/27-3572 | D10: FIS-MAE-SALT-XSUR-08 | E10: MNBU4232707 | F10: Thomas | G10: CS-2025-03638 | H10: Xsur | I10: Maersk | J10: MAERSK SALTORO | K10: Nansha | L10: 25.02.2025 | M10: Teamhead | N10: 450W | P10: delay | Q10: cherries | R10: 25.12.2024 | S10: 25.02.2027
B11: 31668 | C11: PRE-FIS-MAE-2025-01/27-3496 | D11: FIS-MAE-SALT-RIO-142 | E11: MNBU4328840 | F11: Thomas | G11: CS-2025-03698 | H11: Rio Blanco SpA | I11: Maersk | J11: MAERSK SALTORO | K11: Nansha | L11: 24.02.2025 | M11: Asia IBS | N11: 450W | P11: delay | Q11: Cherries | S11: 24.02.207
B12: 31739 | C12: PRE-FIS-MAE-2025-02/27-3468 | D12: FIS-MAE-SALT-RIO-136 | E12: MMAU1280889 | F12: Thomas | G12: CS-2025-03700 | H12: Rio Blanco SpA | I12: Maersk | J12: MAERSK SALTORO | K12: Nansha | L12: 25.02.2025 | M12: Asia IBS | N12: 450W | P12: delay | Q12: Cherries | S12: 25.02.2027
B13: 31740 | C13: PRE-FIS-MAE-2025-02/27-3469 | D13: FIS-MAE-SALT-RIO-138 | E13: MNBU4247287 | F13: Thomas | G13: CS-2025-03701 | H13: Rio Blanco SpA | I13: Maersk | J13: MAERSK SALTORO | K13: Nansha | L13: 25.02.2025 | M13: Asia IBS | N13: 450W | P13: delay | Q13: Cherries | S13: 25.02.2027
B14: 31527 | C14: PRE-FIS-MAE-2025-02/27-3475 | D14: FIS-MAE-SALT-RIO-141 | E14: MMAU1256732 | F14: Thomas | G14: CS-2025-02896 | H14: Rio Blanco SpA | I14: Maersk | J14: MAERSK SALTORO | K14: Nansha | L14: 25.02.2025 | M14: Teamhead | N14: 450W | P14: delay | Q14: Cherries | S14: 25.02.2027
B15: 31548 | C15: PRE-FIS-MAE-2025-02/27-3476 | D15: FIS-MAE-SALT-RIO-139 | E15: MNBU4437625 | F15: Thomas | G15: CS-2025-02897 | H15: Rio Blanco SpA | I15: Maersk | J15: MAERSK SALTORO | K15: Nansha | L15: 25.02.2025 | M15: Teamhead | N15: 450W | P15: delay | Q15: Cherries | S15: 25.02.2027
B16: 31612 | C16: PRE-FIS-MAE-2025-02/27-3488 | D16: FIS-MAE-SALT-AGROEX-506 | E16: MNBU0370396 | F16: Nico Núñez | G16: CS-2025-03727 | H16: Agroexportaciones Chile S.A. | I16: Maersk | J16: MAERSK SALTORO | K16: Nansha | L16: 25.02.2025 | M16: Teamhead | N16: 450W | P16: delay | Q16: Cherries | S16: 25.02.2027
B17: 31879 | C17: PRE-FIS-MAE-2025-02/27-3492 | D17: FIS-MAE-SALT-RIO-140 | E17: MNBU4480935 | F17: Thomas | G17: CS-2025-03699 | H17: Rio Blanco SpA | I17: Maersk | J17: MAERSK SALTORO | K17: Nansha | L17: 24.02.2024 | M17: Teamhead | N17: 450W | P17: delay | Q17: Cherries | S17: 24.02.2027
B18: 31474 | C18: PRE-FIS-MAE-2025-02/27-3505 | D18: FIS-MAE-SALT-NOB-03 | E18: MNBU4499545 | F18: Thomas | G18: CS-2025-02985 | H18: Noble Fruit | I18: Maersk | J18: MAERSK SALTORO | K18: Nansha | L18: 26.02.2025 | M18: Teamhead | N18: 450W | P18: delay | S18: 26.02.2027
B19: 31478 | C19: PRE-FIS-MAE-2025-02/27-3506 | D19: FIS-MAE-SALT-AGRO-43(cld) | E19: MNBU4497223 | F19: Nico Núñez | G19: CS-2025-03747 | H19: Agrofruta Cherries | I19: Maersk | J19: MAERSK SALTORO | K19: Nansha | L19: 17.02.2025 | M19: Teamhead | N19: 450W | P19: delay | S19: 17.02.2027
B20: 32034 | C20: PRE-FIS-MAE-2025-02/27-3508 | D20: FIS-MAE-SALT-COPEFRUT-248 | E20: TLLU1173877 | F20: Thomas | G20: CS-2025-03997 | H20: Copefrut | I20: Maersk | J20: MAERSK SALTORO | K20: Nansha | L20: 26.02.2025 | M20: no surveyor involved | N20: 450W | P20: delay | S20: 26.02.2027
B21: 32035 | C21: PRE-FIS-MAE-2025-02/27-3509 | D21: FIS-MAE-SALT-COPEFRUT-178 | E21: MNBU9175702 | F21: Thomas | G21: CS-2025-03998 | H21: Copefrut | I21: Maersk | J21: MAERSK SALTORO | K21: Nansha | L21: 17.02.2025 | N21: 450W | P21: delay | S21: 17.02.2027
B22: 31544 | C22: PRE-FIS-MAE-2025-02/27-3511 | D22: FIS-MAE-SALT-AGRO-137(cld) | E22: TLLU1167494 | F22: Nico Núñez | G22: CS-2025-03748 | H22: Agrofruta Cherries | I22: Maersk | J22: MAERSK SALTORO | K22: Nansha | L22: 25.02.2025 | M22: Teamhead | N22: 450W | P22: delay
B23: 31956 | C23: PRE-FIS-MAE-2025-02/27-3512 | D23: FIS-MAE-SALT-SAN-18(CLD) | E23: MNBU4059145 | F23: Thomas | G23: CS-2025-03977 | H23: San Andres | I23: Maersk | J23: MAERSK SALTORO | K23: Nansha | L23: 26.02.2025 | M23: Teamhead | N23: 450W | P23: delay | Q23: Cherries | R23: 26.12.2024 | S23: 26.02.2027
B24: 32096 | C24: PRE-FIS-MAE-2025-02/27-3513 | D24: FIS-MAE-SALT-AGRO-39(cld) | E24: MNBU0627695 | F24: Nico Núñez | G24: CS-2025-04145 | H24: Agrofruta Cherries | I24: Maersk | J24: MAERSK SALTORO | K24: Nansha | L24: 25.02.2025 | M24: Teamhead | N24: 450W | P24: delay | Q24: Cherries | R24: 26.12.2024 | S24: 25.02.2027
B25: 31702 | C25: PRE-FIS-MAE-2025-02/27-3514 | D25: FIS-MAE-SALT-GRIN-513 | E25: TTNU8756190 | F25: Nico Núñez | G25: CS-2025-03942 | H25: Grin Export | I25: Maersk | J25: MAERSK SALTORO | K25: Nansha | L25: 26.02.2025 | M25: Teamhead | N25: 450W | P25: delay
B26: 31468 | C26: PRE-FIS-MAE-2025-02/27-3515 | D26: FIS-MAE-SALT-XSUR-05 | E26: MNBU0328246 | F26: Thomas | G26: CS-2025-03637 | H26: Xsur | I26: Maersk | J26: MAERSK SALTORO | K26: Nansha | L26: 17.02.2025 | M26: Teamhead | N26: 450W | P26: delay | Q26: Cherries | R26: 26.12.2024 | S26: 17.02.2027
B27: 31473 | C27: PRE-FIS-MAE-2025-02/27-3516 | D27: FIS-MAE-SALT-SAN-23(CLD) | E27: MNBU9162768 | F27: Thomas | G27: CS-2025-02883 | H27: San Andres | I27: Maersk | J27: MAERSK SALTORO | K27: Nansha | L27: 24.02.2025 | M27: Teamhead | N27: 450W | P27: delay | Q27: Cherries | R27: 25.12.2024 | S27: 24.02.2027
B28: 32015 | C28: PRE-FIS-MAE-2025-02/27-3517 | D28: FIS-MAE-SALT-NOB-04 | E28: MNBU4246573 | F28: Thomas | G28: CS-2025-04142 | H28: Noble Fruit | I28: Maersk | J28: MAERSK SALTORO | K28: Nansha | L28: 26.02.2025 | M28: Teamhead | N28: 450W
B29: 31511 | C29: PRE-FIS-MAE-2025-02/27-3518 | D29: FIS-MAE-SALT-BAKU-01 | E29: MNBU0316923 | F29: Thomas | G29: CS-2025-03940 | H29: Servicios Baku | I29: Maersk | J29: MAERSK SALTORO | K29: Nansha | L29: 17.02.2025 | M29: Teamhead | N29: 450W | P29: delay | Q29: Cherries | R29: 26.12.2024 | S29: 17.02.2027
B30: 31526 | C30: PRE-FIS-MAE-2025-02/27-3519 | D30: FIS-MAE-SALT-XSUR-07 | E30: MNBU4080219 | F30: Thomas | G30: CS-2025-03638 | H30: Xsur | I30: Maersk | J30: MAERSK SALTORO | K30: Nansha | L30: 26.02.2025 | M30: Teamhead | N30: 450W | P30: delay | Q30: Cherries | R30: 25.12.2024 | S30: 26.02.2027
B31: 31541 | C31: PRE-FIS-MAE-2025-02/27-3520 | D31: FIS-MAE-SALT-XSUR-12 | E31: MNBU3743261 | F31: Thomas | G31: CS-2025-03636 | H31: Xsur | I31: Maersk | J31: MAERSK SALTORO | K31: Nansha | L31: 24.02.2025 | M31: Teamhead | N31: 450W | P31: delay | Q31: Cherries | R31: 26.12.2024 | S31: 24.02.2027
B32: 31562 | C32: PRE-FIS-MAE-2025-02/27-3521 | D32: FIS-MAE-SALT-AGRO-44(cld) | E32: MNBU4507105 | F32: Nico Núñez | G32: CS-2025-03749 | H32: Agrofruta Cherries | I32: Maersk | J32: MAERSK SALTORO | K32: Nansha | L32: 17.02.2025 | M32: Teamhead | N32: 450W | P32: delay | Q32: Cherries | R32: 26.12.2024 | S32: 17.02.2027
B33: 31569 | C33: PRE-FIS-MAE-2025-02/27-3522 | D33: FIS-MAE-SALT-AGRO-37(cld) | E33: MNBU9140917 | F33: Nico Núñez | G33: CS-2025-03750 | H33: Agrofruta Cherries | I33: Maersk | J33: MAERSK SALTORO | K33: Nansha | L33: 25.02.2025 | M33: Teamhead | N33: 450W | P33: delay | Q33: Cherries | R33: 26.12.2024 | S33: 25.02.2027
B34: 31571 | C34: PRE-FIS-MAE-2025-02/27-3523 | D34: FIS-MAE-SALT-NOB-01 | E34: MNBU4191824 | F34: Thomas | G34: CS-2025-03711 | H34: Noble Fruit | I34: Maersk | J34: MAERSK SALTORO | K34: Nansha | L34: 25.02.2025 | M34: Teamhead | N34: 450W | P34: delay | Q34: Cherries | R34: 26.12.2024 | S34: 25.02.2027
B35: 31828 | C35: PRE-FIS-MAE-2025-02/27-3525 | D35: FIS-MAE-SALT-GRIN-510 | E35: MNBU0614933 | F35: Nico Núñez | G35: CS-2025-03943 | H35: Grin Export | I35: Maersk | J35: MAERSK SALTORO | K35: Nansha | L35: 26.02.2025 | M35: Teamhead | N35: 450W | P35: delay | Q35: Cherries | R35: 26.12.2024 | S35: 26.02.2027
B36: 31591 | C36: PRE-FIS-MAE-2025-02/27-3527 | D36: FIS-MAE-SALT-XSUR-15 | E36: MNBU3975837 | F36: Thomas | G36: CS-2025-03635 | H36: Xsur | I36: Maersk | J36: MAERSK SALTORO | K36: Nansha | L36: 26.02.2025 | M36: Teamhead | N36: 450W | P36: delay | Q36: Cherries | R36: 26.12.2024 | S36: 26.02.2027
B37: 31850 | C37: PRE-FIS-MAE-2025-02/27-3528 | D37: FIS-MAE-SALT-SAN-20(CLD) | E37: MNBU4470942 | F37: Thomas | G37: CS-2025-03794 | H37: San Andres | I37: Maersk | J37: MAERSK SALTORO | K37: Nansha | L37: 25.02.2025 | M37: Teamhead | N37: 450W | P37: delay | Q37: Cherries | R37: 26.12.2024 | S37: 25.02.2027
B38: 31862 | C38: PRE-FIS-MAE-2025-02/27-3530 | D38: FIS-MAE-SALT-XSUR-13 | E38: MNBU0228062 | F38: Thomas | G38: CS-2025-03792 | H38: Xsur | I38: Maersk | J38: MAERSK SALTORO | K38: Nansha | L38: 25.02.2025 | M38: Teamhead | N38: 450W | P38: delay | Q38: Cherries | R38: 26.12.2024 | S38: 25.02.2027
B39: 31882 | C39: PRE-FIS-MAE-2025-02/27-3531 | D39: FIS-MAE-SALT-ALMAFR-509 | E39: MNBU4392990 | F39: Nico Núñez | G39: CS-2025-03939 | H39: Exportadora Almafruit | I39: Maersk | J39: MAERSK SALTORO | K39: Nansha | L39: 25.02.2025 | M39: Teamhead | N39: 450W | P39: delay | Q39: Cherries | R39: 26.12.2024 | S39: 25.02.2027
B40: 32118 | C40: PRE-FIS-MAE-2025-02/27-3532 | D40: FIS-MAE-SALT-GRIN-511 | E40: MNBU0620812 | F40: Nico Núñez | G40: CS-2025-04358 | H40: Grin Export | I40: Maersk | J40: MAERSK SALTORO | K40: Nansha | L40: 26.02.2025 | M40: Teamhead | N40: 450W | P40: delay | Q40: Cherries | R40: 26.12.2024 | S40: 26.02.2027
... B43: 31654 | C43: PRE-FIS-MAE-2025-02/27-3538 | D43: FIS-MAE-SALT-NOB-02 | E43: TLLU1194925 | F43: Thomas | G43: CS-2025-03712 | H43: Noble Fruit | I43: Maersk | J43: MAERSK SALTORO | K43: Nansha | L43: 25.02.2025 | M43: Teamhead | N43: 450W | P43: delay | Q43: Cherries | R43: 26.12.2024 | S43: 25.02.2027
B44: 31394 | C44: PRE-FIS-MAE-2025-02/27-3542 | D44: FIS-MAE-SALT-SAN-21(CLD) | E44: MNBU4498620 | F44: Thomas | G44: CS-2025-02882 | H44: San Andres | I44: Maersk | J44: MAERSK SALTORO | K44: Nansha | L44: 25.02.2025 | M44: Teamhead | N44: 450W | P44: delay | Q44: Cherries | R44: 26.12.2024 | S44: 25.02.2027
B45: 31909 | C45: PRE-FIS-MAE-2025-02/27-3543 | D45: FIS-MAE-SALT-XSUR-14 | E45: MNBU4065343 | F45: Thomas | G45: CS-2025-03791 | H45: Xsur | I45: Maersk | J45: MAERSK SALTORO | K45: Nansha | L45: 17.02.2025 | M45: Teamhead | N45: 450W | P45: delay | Q45: Cherries | R45: 26.12.2024 | S45: 17.02.2027
B46: 31678 | C46: PRE-FIS-MAE-2025-02/27-3557 | D46: FIS-MAE-SALT-MACE-128(CLD) | E46: MNBU0645739 | F46: Nico Núñez | G46: CS-2025-04355 | H46: Mace | I46: Maersk | J46: MAERSK SALTORO | K46: Nansha | L46: 26.02.2025 | M46: Asia IBS | N46: 450W | P46: delay | R46: 26.12.2024 | S46: 26.02.2027
B47: 31679 | C47: PRE-FIS-MAE-2025-02/27-3558 | D47: FIS-MAE-SALT-MACE-129(CLD) | E47: MNBU3826710 | F47: Nico Núñez | G47: CS-2025-04356 | H47: Mace | I47: Maersk | J47: MAERSK SALTORO | K47: Nansha | L47: 25.02.2025 | M47: Asia IBS | N47: 450W | P47: delay | R47: 26.12.2024 | S47: 25.02.2027
B48: 31693 | C48: PRE-FIS-MAE-2025-02/27-3559 | D48: FIS-MAE-SALT-LQFR-441 | E48: MNBU3798201 | F48: Nico Núñez | G48: CS-2025-03965 | H48: LQ Fruit | I48: Maersk | J48: MAERSK SALTORO | K48: Nansha | L48: 25.02.2025 | M48: Teamhead | N48: 450W | P48: delay | R48: 26.12.2024 | S48: 25.02.2027
B49: 31701 | C49: PRE-FIS-MAE-2025-02/27-3560 | D49: FIS-MAE-SALT-NEWDAY-504(cld) | E49: MNBU0596038 | F49: Nico Núñez | G49: CS-2025-03714 | H49: Newdayfruits | I49: Maersk | J49: MAERSK SALTORO | K49: Nansha | L49: 24.02.2025 | M49: Teamhead | N49: 450W | P49: delay | R49: 26.12.2024 | S49: 24.02.2027
